Workbook

Sheet Read Me
B2: Transaction Experience — LBO returns models
B3: Built on the Leland LBO Modeling template (September 2026). The original template sheets are preserved unchanged at the end of the workbook.
B5: WHAT IS HERE
B6: Summary — one row per deal with entry structure, underwritten returns (template run on the entry facts) and actual returns where an exit is disclosed.
B7: P01–P11 — Paper LBO tabs, one per deal, in the template's own layout. Cells B2:J49 are the template; the INPUTS block at L4:P20 drives them and carries a source and a tag for every number. Rows 52–77 hold the actual outcome and notes.
B8: F01–F04 — Full LBO Model Solution tabs for the four deals with enough filed data: KKR/Varsity 2024, Bain/Varsity 2018, Cerberus/Chrysler 2007, Caterpillar/Bucyrus 2011.
B9: M01–M02 — Sunoco LP acquisition models (NuStar 2024, Parkland 2025): accretion/dilution to distributable cash flow per unit and pro forma net debt / EBITDA, year 1 to year 3. These are strategic MLP acquisitions, not LBOs, and are built as the acquirer's board would have looked at them. Inputs are tagged like the other tabs.
B10: HOW TO READ THE TAGS
B11: F = filed or rating-agency figure (SEC filing, court record, Moody's/S&P release, company release). P = press-reported (Reuters, LCD, Bloomberg, trade press). A = assumption, shown in blue on a yellow fill. Change any blue cell and the tab recalculates.
B13: TWO DEALS ARE NOT LBOs
B14: P07 Caterpillar/Bucyrus and P08 NRG/Direct Energy were strategic acquisitions financed with corporate notes. They are included, with a red banner, because the template mechanics still answer the question "what did the price require", and because both are among the best-documented transactions in the book. Their "equity" is the acquirer's cash, not sponsor equity, and there was no exit.
B16: ONE DEAL NEVER HAPPENED
... B26: Compiled 6 September 2026 from the sources listed on each tab. Not investment advice.

Sheet Summary
B2: Transaction Experience — LBO returns models
B3: Underwritten case = the template run on the entry structure and stated assumptions. Actual = the realised exit where one exists. All figures US$ millions. Blue cells on the deal tabs are assumptions.
B5: # | C5: Deal | D5: Classification | E5: Status | F5: Entry EV | G5: Entry EBITDA | H5: Entry x | I5: Debt | J5: Leverage x | K5: Equity | L5: Exit x | M5: MoM (uw) | N5: IRR (uw) | O5: MoM (actual) | P5: IRR (actual) | Q5: Full model tab
B6: 1 | C6: KKR / Varsity Brands (2024) | D6: Sponsor buyout | E6: Pending (hold) | F6: ='P01 KKR-Varsity 2024'!N5 | G6: ='P01 KKR-Varsity 2024'!N6 | H6: ='P01 KKR-Varsity 2024'!N7 | I6: ='P01 KKR-Varsity 2024'!N8 | J6: ='P01 KKR-Varsity 2024'!N9 | K6: ='P01 KKR-Varsity 2024'!E6 | L6: ='P01 KKR-Varsity 2024'!N18 | M6: ='P01 KKR-Varsity 2024'!E45 | N6: ='P01 KKR-Varsity 2024'!E46 | O6: n/a | P6: n/a | Q6: F01 KKR-Varsity 2024
B7: 2 | C7: Bain Capital / Varsity Brands (2018-24) | D7: Secondary buyout | E7: Realised Aug-2024 | F7: ='P02 Bain-Varsity 2018'!N5 | G7: ='P02 Bain-Varsity 2018'!N6 | H7: ='P02 Bain-Varsity 2018'!N7 | I7: ='P02 Bain-Varsity 2018'!N8 | J7: ='P02 Bain-Varsity 2018'!N9 | K7: ='P02 Bain-Varsity 2018'!E6 | L7: ='P02 Bain-Varsity 2018'!N18 | M7: ='P02 Bain-Varsity 2018'!E45 | N7: ='P02 Bain-Varsity 2018'!E46 | O7: ='P02 Bain-Varsity 2018'!E57 | P7: ='P02 Bain-Varsity 2018'!E58 | Q7: F02 Bain-Varsity 2018
B8: 3 | C8: Charlesbank + Partners Group / Varsity Brands (2014-18) | D8: ESOP buyout | E8: Realised Jul-2018 | F8: ='P03 Charlesbank-Varsity 2014'!N5 | G8: ='P03 Charlesbank-Varsity 2014'!N6 | H8: ='P03 Charlesbank-Varsity 2014'!N7 | I8: ='P03 Charlesbank-Varsity 2014'!N8 | J8: ='P03 Charlesbank-Varsity 2014'!N9 | K8: ='P03 Charlesbank-Varsity 2014'!E6 | L8: ='P03 Charlesbank-Varsity 2014'!N18 | M8: ='P03 Charlesbank-Varsity 2014'!E45 | N8: ='P03 Charlesbank-Varsity 2014'!E46 | O8: ='P03 Charlesbank-Varsity 2014'!E57 | P8: ='P03 Charlesbank-Varsity 2014'!E58
B9: 4 | C9: Leonard Green / Varsity Brands (2003-11) | D9: Take-private (13E-3) | E9: Realised Aug-2011 (price undisclosed) | F9: ='P04 LGP-Varsity 2003'!N5 | G9: ='P04 LGP-Varsity 2003'!N6 | H9: ='P04 LGP-Varsity 2003'!N7 | I9: ='P04 LGP-Varsity 2003'!N8 | J9: ='P04 LGP-Varsity 2003'!N9 | K9: ='P04 LGP-Varsity 2003'!E6 | L9: ='P04 LGP-Varsity 2003'!N18 | M9: ='P04 LGP-Varsity 2003'!E45 | N9: ='P04 LGP-Varsity 2003'!E46 | O9: n/a | P9: n/a
B10: 5 | C10: ONCAP / Sport Supply Group (2010-13) | D10: Take-private with rollover | E10: Realised Jun-2013 (price undisclosed) | F10: ='P05 ONCAP-SportSupply 2010'!N5 | G10: ='P05 ONCAP-SportSupply 2010'!N6 | H10: ='P05 ONCAP-SportSupply 2010'!N7 | I10: ='P05 ONCAP-SportSupply 2010'!N8 | J10: ='P05 ONCAP-SportSupply 2010'!N9 | K10: ='P05 ONCAP-SportSupply 2010'!E6 | L10: ='P05 ONCAP-SportSupply 2010'!N18 | M10: ='P05 ONCAP-SportSupply 2010'!E45 | N10: ='P05 ONCAP-SportSupply 2010'!E46 | O10: n/a | P10: n/a
B11: 6 | C11: Cerberus / Chrysler (2007-09) | D11: Private equity carve-out | E11: Realised 2009: equity written to zero | F11: ='P06 Cerberus-Chrysler 2007'!N5 | G11: ='P06 Cerberus-Chrysler 2007'!N6 | H11: ='P06 Cerberus-Chrysler 2007'!N7 | I11: ='P06 Cerberus-Chrysler 2007'!N8 | J11: ='P06 Cerberus-Chrysler 2007'!N9 | K11: ='P06 Cerberus-Chrysler 2007'!E6 | L11: ='P06 Cerberus-Chrysler 2007'!N18 | M11: ='P06 Cerberus-Chrysler 2007'!E45 | N11: ='P06 Cerberus-Chrysler 2007'!E46 | O11: ='P06 Cerberus-Chrysler 2007'!E57 | P11: ='P06 Cerberus-Chrysler 2007'!E58 | Q11: F03 Cerberus-Chrysler 2007
B12: 7 | C12: Caterpillar / Bucyrus (2011) [STRATEGIC] | D12: STRATEGIC public M&A, debt-financed (not an LBO) | E12: Held; $595m goodwill impairment Q4-2016 | F12: ='P07 Caterpillar-Bucyrus 2011'!N5 | G12: ='P07 Caterpillar-Bucyrus 2011'!N6 | H12: ='P07 Caterpillar-Bucyrus 2011'!N7 | I12: ='P07 Caterpillar-Bucyrus 2011'!N8 | J12: ='P07 Caterpillar-Bucyrus 2011'!N9 | K12: ='P07 Caterpillar-Bucyrus 2011'!E6 | L12: ='P07 Caterpillar-Bucyrus 2011'!N18 | M12: ='P07 Caterpillar-Bucyrus 2011'!E45 | N12: ='P07 Caterpillar-Bucyrus 2011'!E46 | O12: n/a | P12: n/a | Q12: F04 CAT-Bucyrus 2011 STRAT
B13: 8 | C13: NRG / Direct Energy (2021) [STRATEGIC] | D13: STRATEGIC corporate carve-out, note-financed (not an LBO) | E13: Held; $300m synergy programme completed 2023 | F13: ='P08 NRG-DirectEnergy 2021'!N5 | G13: ='P08 NRG-DirectEnergy 2021'!N6 | H13: ='P08 NRG-DirectEnergy 2021'!N7 | I13: ='P08 NRG-DirectEnergy 2021'!N8 | J13: ='P08 NRG-DirectEnergy 2021'!N9 | K13: ='P08 NRG-DirectEnergy 2021'!E6 | L13: ='P08 NRG-DirectEnergy 2021'!N18 | M13: ='P08 NRG-DirectEnergy 2021'!E45 | N13: ='P08 NRG-DirectEnergy 2021'!E46 | O13: n/a | P13: n/a
B14: 9 | C14: Wind Point / Pacific Cycle (2000-04) | D14: Sponsor platform build and exit | E14: Realised Feb-2004 | F14: ='P09 WindPoint-Pacific 2001'!N5 | G14: ='P09 WindPoint-Pacific 2001'!N6 | H14: ='P09 WindPoint-Pacific 2001'!N7 | I14: ='P09 WindPoint-Pacific 2001'!N8 | J14: ='P09 WindPoint-Pacific 2001'!N9 | K14: ='P09 WindPoint-Pacific 2001'!E6 | L14: ='P09 WindPoint-Pacific 2001'!N18 | M14: ='P09 WindPoint-Pacific 2001'!E45 | N14: ='P09 WindPoint-Pacific 2001'!E46 | O14: ='P09 WindPoint-Pacific 2001'!E57 | P14: ='P09 WindPoint-Pacific 2001'!E58
B15: 10 | C15: Pegasus Capital / Cannondale (2003-08) | D15: Distressed 363 purchase and exit | E15: Realised Q1-2008 | F15: ='P10 Pegasus-Cannondale 2003'!N5 | G15: ='P10 Pegasus-Cannondale 2003'!N6 | H15: ='P10 Pegasus-Cannondale 2003'!N7 | I15: ='P10 Pegasus-Cannondale 2003'!N8 | J15: ='P10 Pegasus-Cannondale 2003'!N9 | K15: ='P10 Pegasus-Cannondale 2003'!E6 | L15: ='P10 Pegasus-Cannondale 2003'!N18 | M15: ='P10 Pegasus-Cannondale 2003'!E45 | N15: ='P10 Pegasus-Cannondale 2003'!E46 | O15: ='P10 Pegasus-Cannondale 2003'!E57 | P15: ='P10 Pegasus-Cannondale 2003'!E58
B16: 11 | C16: Cerberus + Koch / Dorel (2021) [TERMINATED] | D16: Take-private with family rollover (terminated 15 Feb 2021) | E16: Terminated; counterfactual shown | F16: ='P11 Cerberus-Dorel 2021 TERM'!N5 | G16: ='P11 Cerberus-Dorel 2021 TERM'!N6 | H16: ='P11 Cerberus-Dorel 2021 TERM'!N7 | I16: ='P11 Cerberus-Dorel 2021 TERM'!N8 | J16: ='P11 Cerberus-Dorel 2021 TERM'!N9 | K16: ='P11 Cerberus-Dorel 2021 TERM'!E6 | L16: ='P11 Cerberus-Dorel 2021 TERM'!N18 | M16: ='P11 Cerberus-Dorel 2021 TERM'!E45 | N16: ='P11 Cerberus-Dorel 2021 TERM'!E46 | O16: ='P11 Cerberus-Dorel 2021 TERM'!E57 | P16: ='P11 Cerberus-Dorel 2021 TERM'!E58
B18: Portfolio arithmetic (sponsor deals only, excluding the two strategic rows and the terminated deal)
B19: Deals with a realised, disclosed exit | F19: =COUNTIF(O6:O16,">0")
B20: Median MoM, underwritten (all rows) | F20: =MEDIAN(M6:M16)
B21: Median MoM, actual (where disclosed) | F21: =IFERROR(MEDIAN(O6:O16),"n/a")
B22: Aggregate entry EV, all rows | F22: =SUM(F6:F16)
B25: Acquisition models (Sunoco LP; strategic, not LBOs)
B26: # | C26: Deal | D26: Classification | E26: Status | F26: Target EV | G26: Target EBITDA | H26: EV / EBITDA | I26: Units issued (m) | J26: Accretion Y1 | K26: Accretion Y3 | L26: Leverage at close | M26: Leverage Y3 | N26: Mgmt accretion target
B27: M1 | C27: Sunoco LP / NuStar Energy L.P. (2024) | D27: All-equity MLP merger | E27: Closed 3 May 2024 | F27: ='M01 SUN-NuStar 2024'!C48 | G27: ='M01 SUN-NuStar 2024'!E20 | H27: ='M01 SUN-NuStar 2024'!C49 | I27: ='M01 SUN-NuStar 2024'!E30 | J27: ='M01 SUN-NuStar 2024'!C62 | K27: ='M01 SUN-NuStar 2024'!E62 | L27: ='M01 SUN-NuStar 2024'!C70 | M27: ='M01 SUN-NuStar 2024'!E75 | N27: 10%+ by year 3
B28: M2 | C28: Sunoco LP / Parkland Corporation (2025) | D28: Cash-and-units plan of arrangement | E28: Closed 31 Oct 2025 | F28: ='M02 SUN-Parkland 2025'!C48 | G28: ='M02 SUN-Parkland 2025'!E20 | H28: ='M02 SUN-Parkland 2025'!C49 | I28: ='M02 SUN-Parkland 2025'!E30 | J28: ='M02 SUN-Parkland 2025'!C62 | K28: ='M02 SUN-Parkland 2025'!E62 | L28: ='M02 SUN-Parkland 2025'!C70 | M28: ='M02 SUN-Parkland 2025'!E75 | N28: 10%+ by year 3

Sheet P01 KKR-Varsity 2024
B2: KKR / Varsity Brands (2024) — Paper LBO
B4: Sources | G4: Uses | L4: INPUTS | N4: Value | O4: Tag | P4: Source (F = filed / rating agency, P = press, A = assumption; blue = assumption)
B5: Debt | E5: =E12 | G5: Purchase Price | J5: =J12 | L5: Entry enterprise value ($m) | N5: 4750 | O5: P | P5: PitchBook LCD / Sportico
B6: Equity (plug) | E6: =E7-E5 | L6: Entry EBITDA, LTM ($m) | N6: 400 | O6: P | P6: Trade press '>$400m'; Moody's 6.2x on ~$2.48bn debt implies ~$400m
B7: Total Sources | E7: =J7 | G7: Total Uses | J7: =J5 | L7: Entry multiple (x) | N7: =N5/N6 | O7: calc | P7: Derived
L8: Debt raised ($m) | N8: 2475 | O8: F | P8: $2,375m TLB + $100m ABL drawn at close (LCD, Sportico)
B9: Build to Debt | G9: Build to Purchase Price | L9: Leverage (x EBITDA) | N9: =N8/N6 | O9: calc | P9: Derived
B10: 2024 EBITDA (LTM) | E10: =E18 | G10: 2024 EBITDA (LTM) | J10: =E18 | L10: Blended cash interest rate | N10: 0.0905 | O10: F | P10: TLB S+375 (fund holdings show TSFR3M+3.75%); 3M SOFR ~5.30% Aug-2024
B11: (x) Leverage | E11: =N9 | G11: (x) Multiple of 2023 EBITDA | J11: =N7 | L11: Tax rate | N11: 0.25 | O11: A | P11: Blended US federal+state assumption
B12: Debt | E12: =E10*E11 | G12: Purchase Price | J12: =J10*J11 | L12: Base-year revenue ($m) | N12: 2600 | O12: F | P12: Moody's: ~$2.6bn LTM Mar-2025 (SGB Media, Jul 2025)
L13: Incremental revenue p.a. ($m) | N13: 130 | O13: A | P13: 5% p.a.; Moody's projected mid-single-digit growth
B14: Simple P&L | E14: 2024 | F14: =E14+1 | G14: =F14+1 | H14: =G14+1 | I14: =H14+1 | J14: =I14+1 | L14: EBITDA margin, base year | N14: =N6/N12 | O14: calc | P14: Derived
B15: Revenue | E15: =N12 | F15: =E15+F16 | G15: =F15+G16 | H15: =G15+H16 | I15: =H15+I16 | J15: =I15+J16 | L15: D&A p.a. ($m) | N15: 78 | O15: A | P15: 3.0% of revenue, assumption
B16: $ Incremental Revenue | F16: =N13 | G16: =F16 | H16: =G16 | I16: =H16 | J16: =I16 | L16: Capex p.a. ($m) | N16: 62 | O16: A | P16: 80% of D&A, assumption
L17: Change in NWC p.a. ($m, negative = investment) | N17: 0 | O17: A | P17: Assumed flat
B18: EBITDA | E18: =E19*E15 | F18: =F19*F15 | G18: =G19*G15 | H18: =H19*H15 | I18: =I19*I15 | J18: =J19*J15 | L18: Exit multiple (x) | N18: 11 | O18: A | P18: Entry 11.9x; modest compression assumed
B19: % margin | E19: =N14 | F19: =E19 | G19: =F19 | H19: =G19 | I19: =H19 | J19: =I19 | L19: Entry date | N19: 45530 | O19: F | P19: Closing date per filings
L20: Underwritten exit date (5-year hold) | N20: 47356 | O20: A | P20: Template convention: five projection years
B21: LFCF Build | L21: Actual exit / valuation date | N21: n/a | O21: F | P21: No realised exit
B22: EBITDA | F22: =F18 | G22: =G18 | H22: =H18 | I22: =I18 | J22: =J18
B23: (-) D&A | F23: =-$N$15 | G23: =-$N$15 | H23: =-$N$15 | I23: =-$N$15 | J23: =-$N$15
B24: EBIT | F24: =F22+F23 | G24: =G22+G23 | H24: =H22+H23 | I24: =I22+I23 | J24: =J22+J23
B25: (-) Cash Interest | D25: =N10 | F25: =$E$12*-$D$25 | G25: =$E$12*-$D$25 | H25: =$E$12*-$D$25 | I25: =$E$12*-$D$25 | J25: =$E$12*-$D$25
B26: EBT | F26: =F24+F25 | G26: =G24+G25 | H26: =H24+H25 | I26: =I24+I25 | J26: =J24+J25
B27: (-) Taxes | D27: =N11 | F27: =F26*-$D27 | G27: =G26*-$D27 | H27: =H26*-$D27 | I27: =I26*-$D27 | J27: =J26*-$D27
B28: Net Income | F28: =F26+F27 | G28: =G26+G27 | H28: =H26+H27 | I28: =I26+I27 | J28: =J26+J27
B29: (+) D&A | F29: =-F23 | G29: =-G23 | H29: =-H23 | I29: =-I23 | J29: =-J23
B30: (-) Capex | F30: =-$N$16 | G30: =-$N$16 | H30: =-$N$16 | I30: =-$N$16 | J30: =-$N$16
B31: (-) Change in NWC | F31: =$N$17 | G31: =$N$17 | H31: =$N$17 | I31: =$N$17 | J31: =$N$17
B32: Levered FCF | F32: =SUM(F28:F31) | G32: =SUM(G28:G31) | H32: =SUM(H28:H31) | I32: =SUM(I28:I31) | J32: =SUM(J28:J31)
B33: Cumulative LFCF | F33: =SUM($E32:F32) | G33: =SUM($E32:G32) | H33: =SUM($E32:H32) | I33: =SUM($E32:I32) | J33: =SUM($E32:J32)
B35: Returns — UNDERWRITTEN CASE (template mechanics: interest on opening debt, all LFCF accumulates as cash)
B37: Exit EBITDA (2029) | E37: =J18
B38: (x) Exit Multiple | E38: =N18
B39: Enterprise Value | E39: =E37*E38
B40: (-) Debt | E40: =-E12
B41: (+) Cash | E41: =J33
B42: Equity Value at Exit | E42: =SUM(E39:E41)
B43: Initial Equity Investment | E43: =E6
B45: MoM | E45: =E42/E43
B46: IRR | E46: =XIRR(E48:E49,B48:B49)
B48: =N19 | E48: =-E6
B49: =N20 | E49: =E42
B52: ACTUAL OUTCOME
B53: Exit enterprise value, actual ($m) | E53: not applicable
B54: Debt at exit ($m)
B55: Equity value at exit ($m)
B56: Equity invested (from Sources) ($m)
B57: MoM, actual
B58: IRR, actual
B59: MoM variance vs underwritten
B60: IRR variance vs underwritten (pts)
B65: Actual outcome note:
B66: No realised exit; the deal is a current holding.
B71: Deal note:
B72: Prospective. KKR contributed ~$2.5bn of equity against ~$2.48bn of debt, an unusually thick cheque for a B3/B- credit. S&P and Moody's both upgraded in mid-2025 on deleveraging.
B77: Classification: Sponsor buyout | Status: Pending (hold)

Sheet P02 Bain-Varsity 2018
B2: Bain Capital / Varsity Brands (2018-24) — Paper LBO
B4: Sources | G4: Uses | L4: INPUTS | N4: Value | O4: Tag | P4: Source (F = filed / rating agency, P = press, A = assumption; blue = assumption)
B5: Debt | E5: =E12 | G5: Purchase Price | J5: =J12 | L5: Entry enterprise value ($m) | N5: 2900 | O5: F | P5: Moody's: 'total implied enterprise value of approximately $2.9 billion' (press said ~$2.5bn)
B6: Equity (plug) | E6: =E7-E5 | L6: Entry EBITDA, LTM ($m) | N6: 290 | O6: A | P6: Assumption: $2.9bn EV at 10.0x; Moody's showed 7.7x on ~$2.0bn debt at Dec-2019 (~$260m)
B7: Total Sources | E7: =J7 | G7: Total Uses | J7: =J5 | L7: Entry multiple (x) | N7: =N5/N6 | O7: calc | P7: Derived
L8: Debt raised ($m) | N8: 1990 | O8: F | P8: $1,370m 1L TL + $620m 2L TL (Moody's); $180m revolver undrawn
B9: Build to Debt | G9: Build to Purchase Price | L9: Leverage (x EBITDA) | N9: =N8/N6 | O9: calc | P9: Derived
B10: 2018 EBITDA (LTM) | E10: =E18 | G10: 2018 EBITDA (LTM) | J10: =E18 | L10: Blended cash interest rate | N10: 0.0715 | O10: A | P10: 1L L+350 (~5.75%) and 2L assumed L+800 (~10.25%), blended
B11: (x) Leverage | E11: =N9 | G11: (x) Multiple of 2023 EBITDA | J11: =N7 | L11: Tax rate | N11: 0.25 | O11: A | P11: Assumption
B12: Debt | E12: =E10*E11 | G12: Purchase Price | J12: =J10*J11 | L12: Base-year revenue ($m) | N12: 2000 | O12: F | P12: Moody's: ~$2.0bn LTM Dec-2019
L13: Incremental revenue p.a. ($m) | N13: 120 | O13: A | P13: Path to ~$400m EBITDA by 2023 at constant margin (6% p.a.)
B14: Simple P&L | E14: 2018 | F14: =E14+1 | G14: =F14+1 | H14: =G14+1 | I14: =H14+1 | J14: =I14+1 | L14: EBITDA margin, base year | N14: =N6/N12 | O14: calc | P14: Derived
B15: Revenue | E15: =N12 | F15: =E15+F16 | G15: =F15+G16 | H15: =G15+H16 | I15: =H15+I16 | J15: =I15+J16 | L15: D&A p.a. ($m) | N15: 60 | O15: A | P15: 3.0% of revenue, assumption
B16: $ Incremental Revenue | F16: =N13 | G16: =F16 | H16: =G16 | I16: =H16 | J16: =I16 | L16: Capex p.a. ($m) | N16: 50 | O16: A | P16: Assumption
L17: Change in NWC p.a. ($m, negative = investment) | N17: 0 | O17: A | P17: Assumed flat
B18: EBITDA | E18: =E19*E15 | F18: =F19*F15 | G18: =G19*G15 | H18: =H19*H15 | I18: =I19*I15 | J18: =J19*J15 | L18: Exit multiple (x) | N18: 11.875 | O18: P | P18: $4,750m KKR price on ~$400m EBITDA
B19: % margin | E19: =N14 | F19: =E19 | G19: =F19 | H19: =G19 | I19: =H19 | J19: =I19 | L19: Entry date | N19: 43312 | O19: F | P19: Closing date per filings
L20: Underwritten exit date (5-year hold) | N20: 45135 | O20: A | P20: Template convention: five projection years
B21: LFCF Build | L21: Actual exit / valuation date | N21: 45530 | O21: F | P21: Realised exit date per filings
B22: EBITDA | F22: =F18 | G22: =G18 | H22: =H18 | I22: =I18 | J22: =J18
B23: (-) D&A | F23: =-$N$15 | G23: =-$N$15 | H23: =-$N$15 | I23: =-$N$15 | J23: =-$N$15
B24: EBIT | F24: =F22+F23 | G24: =G22+G23 | H24: =H22+H23 | I24: =I22+I23 | J24: =J22+J23
B25: (-) Cash Interest | D25: =N10 | F25: =$E$12*-$D$25 | G25: =$E$12*-$D$25 | H25: =$E$12*-$D$25 | I25: =$E$12*-$D$25 | J25: =$E$12*-$D$25
B26: EBT | F26: =F24+F25 | G26: =G24+G25 | H26: =H24+H25 | I26: =I24+I25 | J26: =J24+J25
B27: (-) Taxes | D27: =N11 | F27: =F26*-$D27 | G27: =G26*-$D27 | H27: =H26*-$D27 | I27: =I26*-$D27 | J27: =J26*-$D27
B28: Net Income | F28: =F26+F27 | G28: =G26+G27 | H28: =H26+H27 | I28: =I26+I27 | J28: =J26+J27
B29: (+) D&A | F29: =-F23 | G29: =-G23 | H29: =-H23 | I29: =-I23 | J29: =-J23
B30: (-) Capex | F30: =-$N$16 | G30: =-$N$16 | H30: =-$N$16 | I30: =-$N$16 | J30: =-$N$16
B31: (-) Change in NWC | F31: =$N$17 | G31: =$N$17 | H31: =$N$17 | I31: =$N$17 | J31: =$N$17
B32: Levered FCF | F32: =SUM(F28:F31) | G32: =SUM(G28:G31) | H32: =SUM(H28:H31) | I32: =SUM(I28:I31) | J32: =SUM(J28:J31)
B33: Cumulative LFCF | F33: =SUM($E32:F32) | G33: =SUM($E32:G32) | H33: =SUM($E32:H32) | I33: =SUM($E32:I32) | J33: =SUM($E32:J32)
B35: Returns — UNDERWRITTEN CASE (template mechanics: interest on opening debt, all LFCF accumulates as cash)
B37: Exit EBITDA (2023) | E37: =J18
B38: (x) Exit Multiple | E38: =N18
B39: Enterprise Value | E39: =E37*E38
B40: (-) Debt | E40: =-E12
B41: (+) Cash | E41: =J33
B42: Equity Value at Exit | E42: =SUM(E39:E41)
B43: Initial Equity Investment | E43: =E6
B45: MoM | E45: =E42/E43
B46: IRR | E46: =XIRR(E48:E49,B48:B49)
B48: =N19 | E48: =-E6
B49: =N20 | E49: =E42
B52: ACTUAL OUTCOME
B53: Exit enterprise value, actual ($m) | E53: 4750
B54: Debt at exit ($m) | E54: 2447
B55: Equity value at exit ($m) | E55: =E53-E54
B56: Equity invested (from Sources) ($m) | E56: =E6
B57: MoM, actual | E57: =E55/E56
B58: IRR, actual | E58: =IFERROR(XIRR(E62:E63,B62:B63),"n/m")
B59: MoM variance vs underwritten | E59: =E57-E45
B60: IRR variance vs underwritten (pts) | E60: =IFERROR((E58-E46)*100,"n/m")
B62: =N19 | E62: =-E6 | G62: cash flows for XIRR (actual)
B63: =N21 | E63: =E55
B65: Actual outcome note:
B66: Exit debt = $1,132m 1L TL + $450m 1L notes + $620m 2L + ~$245m ABL drawn (LCD; Moody's Nov-2023). Equity in = EV $2,900m + fees less $1,990m debt. Charlesbank rolled a minority; Herff Jones graduation sold Oct-2023 for an undisclosed sum, not credited here.
B71: Deal note:
B72: Leverage never came down: Moody's had it at 7.7x (2019), 8.6x (2022), 6.9x (mid-2023). The return came almost entirely from EBITDA growth and the exit multiple, not deleveraging.
B77: Classification: Secondary buyout | Status: Realised Aug-2024

Sheet P03 Charlesbank-Varsity 2014
B2: Charlesbank + Partners Group / Varsity Brands (2014-18) — Paper LBO
B4: Sources | G4: Uses | L4: INPUTS | N4: Value | O4: Tag | P4: Source (F = filed / rating agency, P = press, A = assumption; blue = assumption)
B5: Debt | E5: =E12 | G5: Purchase Price | J5: =J12 | L5: Entry enterprise value ($m) | N5: 1500 | O5: P | P5: Charlesbank site / CNBC '~$1.5bn'
B6: Equity (plug) | E6: =E7-E5 | L6: Entry EBITDA, LTM ($m) | N6: 155 | O6: A | P6: Assumption: ~9.7x entry on $1.5bn; B2 CFR at 6.5x leverage
B7: Total Sources | E7: =J7 | G7: Total Uses | J7: =J5 | L7: Entry multiple (x) | N7: =N5/N6 | O7: calc | P7: Derived
L8: Debt raised ($m) | N8: 1000 | O8: A | P8: Assumption: 1L (L+500, 1% floor) ~$700m + 2L (L+875) ~$300m; Ares held $175m of 2L par
B9: Build to Debt | G9: Build to Purchase Price | L9: Leverage (x EBITDA) | N9: =N8/N6 | O9: calc | P9: Derived
B10: 2014 EBITDA (LTM) | E10: =E18 | G10: 2014 EBITDA (LTM) | J10: =E18 | L10: Blended cash interest rate | N10: 0.0713 | O10: F | P10: 1L 6.00% and 2L 9.75% (BDC filings), blended 70/30
B11: (x) Leverage | E11: =N9 | G11: (x) Multiple of 2023 EBITDA | J11: =N7 | L11: Tax rate | N11: 0.3 | O11: A | P11: Assumption
B12: Debt | E12: =E10*E11 | G12: Purchase Price | J12: =J10*J11 | L12: Base-year revenue ($m) | N12: 1200 | O12: F | P12: Company release: 'combined sales in excess of $1.2 billion'
L13: Incremental revenue p.a. ($m) | N13: 80 | O13: A | P13: ~6.5% p.a., assumption
B14: Simple P&L | E14: 2014 | F14: =E14+1 | G14: =F14+1 | H14: =G14+1 | I14: =H14+1 | J14: =I14+1 | L14: EBITDA margin, base year | N14: =N6/N12 | O14: calc | P14: Derived
B15: Revenue | E15: =N12 | F15: =E15+F16 | G15: =F15+G16 | H15: =G15+H16 | I15: =H15+I16 | J15: =I15+J16 | L15: D&A p.a. ($m) | N15: 36 | O15: A | P15: 3.0% of revenue, assumption
B16: $ Incremental Revenue | F16: =N13 | G16: =F16 | H16: =G16 | I16: =H16 | J16: =I16 | L16: Capex p.a. ($m) | N16: 30 | O16: A | P16: Assumption
L17: Change in NWC p.a. ($m, negative = investment) | N17: 0 | O17: A | P17: Assumed flat
B18: EBITDA | E18: =E19*E15 | F18: =F19*F15 | G18: =G19*G15 | H18: =H19*H15 | I18: =I19*I15 | J18: =J19*J15 | L18: Exit multiple (x) | N18: 10 | O18: A | P18: $2.9bn Bain EV on ~$290m EBITDA (assumption)
B19: % margin | E19: =N14 | F19: =E19 | G19: =F19 | H19: =G19 | I19: =H19 | J19: =I19 | L19: Entry date | N19: 41988 | O19: F | P19: Closing date per filings
L20: Underwritten exit date (5-year hold) | N20: 43814 | O20: A | P20: Template convention: five projection years
B21: LFCF Build | L21: Actual exit / valuation date | N21: 43312 | O21: F | P21: Realised exit date per filings
B22: EBITDA | F22: =F18 | G22: =G18 | H22: =H18 | I22: =I18 | J22: =J18
B23: (-) D&A | F23: =-$N$15 | G23: =-$N$15 | H23: =-$N$15 | I23: =-$N$15 | J23: =-$N$15
B24: EBIT | F24: =F22+F23 | G24: =G22+G23 | H24: =H22+H23 | I24: =I22+I23 | J24: =J22+J23
B25: (-) Cash Interest | D25: =N10 | F25: =$E$12*-$D$25 | G25: =$E$12*-$D$25 | H25: =$E$12*-$D$25 | I25: =$E$12*-$D$25 | J25: =$E$12*-$D$25
B26: EBT | F26: =F24+F25 | G26: =G24+G25 | H26: =H24+H25 | I26: =I24+I25 | J26: =J24+J25
B27: (-) Taxes | D27: =N11 | F27: =F26*-$D27 | G27: =G26*-$D27 | H27: =H26*-$D27 | I27: =I26*-$D27 | J27: =J26*-$D27
B28: Net Income | F28: =F26+F27 | G28: =G26+G27 | H28: =H26+H27 | I28: =I26+I27 | J28: =J26+J27
B29: (+) D&A | F29: =-F23 | G29: =-G23 | H29: =-H23 | I29: =-I23 | J29: =-J23
B30: (-) Capex | F30: =-$N$16 | G30: =-$N$16 | H30: =-$N$16 | I30: =-$N$16 | J30: =-$N$16
B31: (-) Change in NWC | F31: =$N$17 | G31: =$N$17 | H31: =$N$17 | I31: =$N$17 | J31: =$N$17
B32: Levered FCF | F32: =SUM(F28:F31) | G32: =SUM(G28:G31) | H32: =SUM(H28:H31) | I32: =SUM(I28:I31) | J32: =SUM(J28:J31)
B33: Cumulative LFCF | F33: =SUM($E32:F32) | G33: =SUM($E32:G32) | H33: =SUM($E32:H32) | I33: =SUM($E32:I32) | J33: =SUM($E32:J32)
B35: Returns — UNDERWRITTEN CASE (template mechanics: interest on opening debt, all LFCF accumulates as cash)
B37: Exit EBITDA (2019) | E37: =J18
B38: (x) Exit Multiple | E38: =N18
B39: Enterprise Value | E39: =E37*E38
B40: (-) Debt | E40: =-E12
B41: (+) Cash | E41: =J33
B42: Equity Value at Exit | E42: =SUM(E39:E41)
B43: Initial Equity Investment | E43: =E6
B45: MoM | E45: =E42/E43
B46: IRR | E46: =XIRR(E48:E49,B48:B49)
B48: =N19 | E48: =-E6
B49: =N20 | E49: =E42
B52: ACTUAL OUTCOME
B53: Exit enterprise value, actual ($m) | E53: 2900
B54: Debt at exit ($m) | E54: 1000
B55: Equity value at exit ($m) | E55: =E53-E54
B56: Equity invested (from Sources) ($m) | E56: =E6
B57: MoM, actual | E57: =E55/E56
B58: IRR, actual | E58: =IFERROR(XIRR(E62:E63,B62:B63),"n/m")
B59: MoM variance vs underwritten | E59: =E57-E45
B60: IRR variance vs underwritten (pts) | E60: =IFERROR((E58-E46)*100,"n/m")
B62: =N19 | E62: =-E6 | G62: cash flows for XIRR (actual)
B63: =N21 | E63: =E55
B65: Actual outcome note:
B66: Exit EV per Moody's; press said $2.5bn. Exit debt assumed equal to entry (no paydown, consistent with later leverage history). Charlesbank retained a minority stake in the Bain deal, not credited here.
B71: Deal note:
B72: Best-returning link in the chain on any assumption set: ~3.5 years, EV roughly doubled, equity roughly tripled.
B77: Classification: ESOP buyout | Status: Realised Jul-2018

Sheet P04 LGP-Varsity 2003
B2: Leonard Green / Varsity Brands (2003-11) — Paper LBO
B4: Sources | G4: Uses | L4: INPUTS | N4: Value | O4: Tag | P4: Source (F = filed / rating agency, P = press, A = assumption; blue = assumption)
B5: Debt | E5: =E12 | G5: Purchase Price | J5: =J12 | L5: Entry enterprise value ($m) | N5: 144.6 | O5: F | P5: Rothschild adjusted EV incl. $10.4m deal costs; $164.2m 'aggregate transaction value' incl. fees
B6: Equity (plug) | E6: =E7-E5 | L6: Entry EBITDA, LTM ($m) | N6: 20.7 | O6: F | P6: 2002A adjusted EBITDA $19.0m + $1.7m add-backs (SC 13E-3 Ex-99(c)(3))
B7: Total Sources | E7: =J7 | G7: Total Uses | J7: =J5 | L7: Entry multiple (x) | N7: =N5/N6 | O7: calc | P7: Derived
L8: Debt raised ($m) | N8: 85 | O8: A | P8: Assumption: Wells Fargo/Merrill senior ~$55m + NML/BancAmerica sub-debt ~$30m (sizes not in the DEFM14A extract)
B9: Build to Debt | G9: Build to Purchase Price | L9: Leverage (x EBITDA) | N9: =N8/N6 | O9: calc | P9: Derived
B10: 2002 EBITDA (LTM) | E10: =E18 | G10: 2002 EBITDA (LTM) | J10: =E18 | L10: Blended cash interest rate | N10: 0.081 | O10: A | P10: Senior ~6% / sub-debt ~12%, blended
B11: (x) Leverage | E11: =N9 | G11: (x) Multiple of 2023 EBITDA | J11: =N7 | L11: Tax rate | N11: 0.38 | O11: A | P11: Assumption
B12: Debt | E12: =E10*E11 | G12: Purchase Price | J12: =J10*J11 | L12: Base-year revenue ($m) | N12: 156.4 | O12: F | P12: Rothschild fairness materials: 2002A revenue (SC 13E-3 Ex-99(c)(2))
L13: Incremental revenue p.a. ($m) | N13: 14 | O13: F | P13: 2003E revenue $170.5m per Rothschild; ~9% p.a.
B14: Simple P&L | E14: 2002 | F14: =E14+1 | G14: =F14+1 | H14: =G14+1 | I14: =H14+1 | J14: =I14+1 | L14: EBITDA margin, base year | N14: =N6/N12 | O14: calc | P14: Derived
B15: Revenue | E15: =N12 | F15: =E15+F16 | G15: =F15+G16 | H15: =G15+H16 | I15: =H15+I16 | J15: =I15+J16 | L15: D&A p.a. ($m) | N15: 4.5 | O15: A | P15: Assumption ~2.9% of revenue
B16: $ Incremental Revenue | F16: =N13 | G16: =F16 | H16: =G16 | I16: =H16 | J16: =I16 | L16: Capex p.a. ($m) | N16: 4 | O16: A | P16: Assumption
L17: Change in NWC p.a. ($m, negative = investment) | N17: -1 | O17: A | P17: Growth working capital, assumption
B18: EBITDA | E18: =E19*E15 | F18: =F19*F15 | G18: =G19*G15 | H18: =H19*H15 | I18: =I19*I15 | J18: =J19*J15 | L18: Exit multiple (x) | N18: 7 | O18: A | P18: Assumed equal to entry (exit price to Herff Jones undisclosed)
B19: % margin | E19: =N14 | F19: =E19 | G19: =F19 | H19: =G19 | I19: =H19 | J19: =I19 | L19: Entry date | N19: 37888 | O19: F | P19: Closing date per filings
L20: Underwritten exit date (5-year hold) | N20: 39715 | O20: A | P20: Template convention: five projection years
B21: LFCF Build | L21: Actual exit / valuation date | N21: n/a | O21: F | P21: No realised exit
B22: EBITDA | F22: =F18 | G22: =G18 | H22: =H18 | I22: =I18 | J22: =J18
B23: (-) D&A | F23: =-$N$15 | G23: =-$N$15 | H23: =-$N$15 | I23: =-$N$15 | J23: =-$N$15
B24: EBIT | F24: =F22+F23 | G24: =G22+G23 | H24: =H22+H23 | I24: =I22+I23 | J24: =J22+J23
B25: (-) Cash Interest | D25: =N10 | F25: =$E$12*-$D$25 | G25: =$E$12*-$D$25 | H25: =$E$12*-$D$25 | I25: =$E$12*-$D$25 | J25: =$E$12*-$D$25
B26: EBT | F26: =F24+F25 | G26: =G24+G25 | H26: =H24+H25 | I26: =I24+I25 | J26: =J24+J25
B27: (-) Taxes | D27: =N11 | F27: =F26*-$D27 | G27: =G26*-$D27 | H27: =H26*-$D27 | I27: =I26*-$D27 | J27: =J26*-$D27
B28: Net Income | F28: =F26+F27 | G28: =G26+G27 | H28: =H26+H27 | I28: =I26+I27 | J28: =J26+J27
B29: (+) D&A | F29: =-F23 | G29: =-G23 | H29: =-H23 | I29: =-I23 | J29: =-J23
B30: (-) Capex | F30: =-$N$16 | G30: =-$N$16 | H30: =-$N$16 | I30: =-$N$16 | J30: =-$N$16
B31: (-) Change in NWC | F31: =$N$17 | G31: =$N$17 | H31: =$N$17 | I31: =$N$17 | J31: =$N$17
B32: Levered FCF | F32: =SUM(F28:F31) | G32: =SUM(G28:G31) | H32: =SUM(H28:H31) | I32: =SUM(I28:I31) | J32: =SUM(J28:J31)
B33: Cumulative LFCF | F33: =SUM($E32:F32) | G33: =SUM($E32:G32) | H33: =SUM($E32:H32) | I33: =SUM($E32:I32) | J33: =SUM($E32:J32)
B35: Returns — UNDERWRITTEN CASE (template mechanics: interest on opening debt, all LFCF accumulates as cash)
B37: Exit EBITDA (2007) | E37: =J18
B38: (x) Exit Multiple | E38: =N18
B39: Enterprise Value | E39: =E37*E38
B40: (-) Debt | E40: =-E12
B41: (+) Cash | E41: =J33
B42: Equity Value at Exit | E42: =SUM(E39:E41)
B43: Initial Equity Investment | E43: =E6
B45: MoM | E45: =E42/E43
B46: IRR | E46: =XIRR(E48:E49,B48:B49)
B48: =N19 | E48: =-E6
B49: =N20 | E49: =E42
B52: ACTUAL OUTCOME
B53: Exit enterprise value, actual ($m) | E53: undisclosed
B54: Debt at exit ($m)
B55: Equity value at exit ($m)
B56: Equity invested (from Sources) ($m)
B57: MoM, actual
B58: IRR, actual
B59: MoM variance vs underwritten
B60: IRR variance vs underwritten (pts)
B65: Actual outcome note:
B66: Exit price not disclosed by the parties.
B71: Deal note:
B72: Rothschild's own multiples: 7.6x 2002A / 6.7x 2003E adjusted EBITDA. Exit to Herff Jones in 2011 was undisclosed, so the realised return cannot be stated.
B77: Classification: Take-private (13E-3) | Status: Realised Aug-2011 (price undisclosed)

Sheet P05 ONCAP-SportSupply 2010
B2: ONCAP / Sport Supply Group (2010-13) — Paper LBO
B4: Sources | G4: Uses | L4: INPUTS | N4: Value | O4: Tag | P4: Source (F = filed / rating agency, P = press, A = assumption; blue = assumption)
B5: Debt | E5: =E12 | G5: Purchase Price | J5: =J12 | L5: Entry enterprise value ($m) | N5: 180.2 | O5: F | P5: $179.4m equity consideration (SC 13E-3) + $0.8m net debt
B6: Equity (plug) | E6: =E7-E5 | L6: Entry EBITDA, LTM ($m) | N6: 25.8 | O6: F | P6: LTM adjusted EBITDA to 31 Mar 2010 (8-K Ex-99.1)
B7: Total Sources | E7: =J7 | G7: Total Uses | J7: =J5 | L7: Entry multiple (x) | N7: =N5/N6 | O7: calc | P7: Derived
L8: Debt raised ($m) | N8: 101.1 | O8: F | P8: DEFM14A: term loan $74.6m + Manulife mezz $26.5m; $25m revolver undrawn
B9: Build to Debt | G9: Build to Purchase Price | L9: Leverage (x EBITDA) | N9: =N8/N6 | O9: calc | P9: Derived
B10: 2010 EBITDA (LTM) | E10: =E18 | G10: 2010 EBITDA (LTM) | J10: =E18 | L10: Blended cash interest rate | N10: 0.076 | O10: A | P10: Term loan ~6% / mezz ~12%, blended (rates not disclosed)
B11: (x) Leverage | E11: =N9 | G11: (x) Multiple of 2023 EBITDA | J11: =N7 | L11: Tax rate | N11: 0.38 | O11: A | P11: Assumption
B12: Debt | E12: =E10*E11 | G12: Purchase Price | J12: =J10*J11 | L12: Base-year revenue ($m) | N12: 262 | O12: F | P12: LTM to Mar-2010: FY09 $250.2m, 9-mo FY10 $198.5m (8-K Ex-99.1)
L13: Incremental revenue p.a. ($m) | N13: 15 | O13: A | P13: ~6% p.a. plus nine bolt-ons under ONCAP, assumption
B14: Simple P&L | E14: 2010 | F14: =E14+1 | G14: =F14+1 | H14: =G14+1 | I14: =H14+1 | J14: =I14+1 | L14: EBITDA margin, base year | N14: =N6/N12 | O14: calc | P14: Derived
B15: Revenue | E15: =N12 | F15: =E15+F16 | G15: =F15+G16 | H15: =G15+H16 | I15: =H15+I16 | J15: =I15+J16 | L15: D&A p.a. ($m) | N15: 5 | O15: A | P15: Assumption
B16: $ Incremental Revenue | F16: =N13 | G16: =F16 | H16: =G16 | I16: =H16 | J16: =I16 | L16: Capex p.a. ($m) | N16: 4 | O16: A | P16: Assumption
L17: Change in NWC p.a. ($m, negative = investment) | N17: -1 | O17: A | P17: Assumption
B18: EBITDA | E18: =E19*E15 | F18: =F19*F15 | G18: =G19*G15 | H18: =H19*H15 | I18: =I19*I15 | J18: =J19*J15 | L18: Exit multiple (x) | N18: 7 | O18: A | P18: Assumed equal to entry (Herff Jones price undisclosed)
B19: % margin | E19: =N14 | F19: =E19 | G19: =F19 | H19: =G19 | I19: =H19 | J19: =I19 | L19: Entry date | N19: 40395 | O19: F | P19: Closing date per filings
L20: Underwritten exit date (5-year hold) | N20: 42221 | O20: A | P20: Template convention: five projection years
B21: LFCF Build | L21: Actual exit / valuation date | N21: n/a | O21: F | P21: No realised exit
B22: EBITDA | F22: =F18 | G22: =G18 | H22: =H18 | I22: =I18 | J22: =J18
B23: (-) D&A | F23: =-$N$15 | G23: =-$N$15 | H23: =-$N$15 | I23: =-$N$15 | J23: =-$N$15
B24: EBIT | F24: =F22+F23 | G24: =G22+G23 | H24: =H22+H23 | I24: =I22+I23 | J24: =J22+J23
B25: (-) Cash Interest | D25: =N10 | F25: =$E$12*-$D$25 | G25: =$E$12*-$D$25 | H25: =$E$12*-$D$25 | I25: =$E$12*-$D$25 | J25: =$E$12*-$D$25
B26: EBT | F26: =F24+F25 | G26: =G24+G25 | H26: =H24+H25 | I26: =I24+I25 | J26: =J24+J25
B27: (-) Taxes | D27: =N11 | F27: =F26*-$D27 | G27: =G26*-$D27 | H27: =H26*-$D27 | I27: =I26*-$D27 | J27: =J26*-$D27
B28: Net Income | F28: =F26+F27 | G28: =G26+G27 | H28: =H26+H27 | I28: =I26+I27 | J28: =J26+J27
B29: (+) D&A | F29: =-F23 | G29: =-G23 | H29: =-H23 | I29: =-I23 | J29: =-J23
B30: (-) Capex | F30: =-$N$16 | G30: =-$N$16 | H30: =-$N$16 | I30: =-$N$16 | J30: =-$N$16
B31: (-) Change in NWC | F31: =$N$17 | G31: =$N$17 | H31: =$N$17 | I31: =$N$17 | J31: =$N$17
B32: Levered FCF | F32: =SUM(F28:F31) | G32: =SUM(G28:G31) | H32: =SUM(H28:H31) | I32: =SUM(I28:I31) | J32: =SUM(J28:J31)
B33: Cumulative LFCF | F33: =SUM($E32:F32) | G33: =SUM($E32:G32) | H33: =SUM($E32:H32) | I33: =SUM($E32:I32) | J33: =SUM($E32:J32)
B35: Returns — UNDERWRITTEN CASE (template mechanics: interest on opening debt, all LFCF accumulates as cash)
B37: Exit EBITDA (2015) | E37: =J18
B38: (x) Exit Multiple | E38: =N18
B39: Enterprise Value | E39: =E37*E38
B40: (-) Debt | E40: =-E12
B41: (+) Cash | E41: =J33
B42: Equity Value at Exit | E42: =SUM(E39:E41)
B43: Initial Equity Investment | E43: =E6
B45: MoM | E45: =E42/E43
B46: IRR | E46: =XIRR(E48:E49,B48:B49)
B48: =N19 | E48: =-E6
B49: =N20 | E49: =E42
B52: ACTUAL OUTCOME
B53: Exit enterprise value, actual ($m) | E53: undisclosed
B54: Debt at exit ($m)
B55: Equity value at exit ($m)
B56: Equity invested (from Sources) ($m)
B57: MoM, actual
B58: IRR, actual
B59: MoM variance vs underwritten
B60: IRR variance vs underwritten (pts)
B65: Actual outcome note:
B66: Exit price not disclosed by the parties.
B71: Deal note:
B72: Filed sources and uses: ONCAP $89.6m + management $3.5m equity, $74.6m term loan, $26.5m mezz. Entry 7.0x LTM / 7.2x FY2009 adjusted EBITDA.
B77: Classification: Take-private with rollover | Status: Realised Jun-2013 (price undisclosed)

Sheet P06 Cerberus-Chrysler 2007
B2: Cerberus / Chrysler (2007-09) — Paper LBO
B4: Sources | G4: Uses | L4: INPUTS | N4: Value | O4: Tag | P4: Source (F = filed / rating agency, P = press, A = assumption; blue = assumption)
B5: Debt | E5: =E12 | G5: Purchase Price | J5: =J12 | L5: Entry enterprise value ($m) | N5: 17400 | O5: F | P5: Cerberus equity into Chrysler Corp LLC $5.4bn (Daimler AR 2007 / TTAC) + $12bn acquisition debt
B6: Equity (plug) | E6: =E7-E5 | L6: Entry EBITDA, LTM ($m) | N6: 1500 | O6: A | P6: Assumption: 2006 operating loss EUR(1,118)m plus segment D&A (not disclosed at segment level; group D&A implies ~$2.5-3bn incl. leasing)
B7: Total Sources | E7: =J7 | G7: Total Uses | J7: =J5 | L7: Entry multiple (x) | N7: =N5/N6 | O7: calc | P7: Derived
L8: Debt raised ($m) | N8: 12000 | O8: F | P8: $10bn first-lien TL + $2bn second-lien (Moody's / S&P, Jul-Aug 2007); $2.5bn of the 1L sat in a collateral account
B9: Build to Debt | G9: Build to Purchase Price | L9: Leverage (x EBITDA) | N9: =N8/N6 | O9: calc | P9: Derived
B10: 2006 EBITDA (LTM) | E10: =E18 | G10: 2006 EBITDA (LTM) | J10: =E18 | L10: Blended cash interest rate | N10: 0.091 | O10: A | P10: 1L assumed ~8.5% and 2L ~12% (spreads/OIDs after the failed July-2007 syndication not found)
B11: (x) Leverage | E11: =N9 | G11: (x) Multiple of 2023 EBITDA | J11: =N7 | L11: Tax rate | N11: 0.35 | O11: A | P11: Assumption
B12: Debt | E12: =E10*E11 | G12: Purchase Price | J12: =J10*J11 | L12: Base-year revenue ($m) | N12: 59000 | O12: F | P12: Chrysler Group 2006 revenue EUR47,116m (DaimlerChrysler 20-F) at ~1.25 $/EUR
L13: Incremental revenue p.a. ($m) | N13: 0 | O13: A | P13: Sponsor case: flat revenue, margin recovery via Nardelli cost plan
B14: Simple P&L | E14: 2006 | F14: =E14+1 | G14: =F14+1 | H14: =G14+1 | I14: =H14+1 | J14: =I14+1 | L14: EBITDA margin, base year | N14: =N6/N12 | O14: calc | P14: Derived
B15: Revenue | E15: =N12 | F15: =E15+F16 | G15: =F15+G16 | H15: =G15+H16 | I15: =H15+I16 | J15: =I15+J16 | L15: D&A p.a. ($m) | N15: 2800 | O15: A | P15: Assumption ~4.7% of revenue
B16: $ Incremental Revenue | F16: =N13 | G16: =F16 | H16: =G16 | I16: =H16 | J16: =I16 | L16: Capex p.a. ($m) | N16: 2000 | O16: F | P16: 2006 capex EUR1,251m; assumed ~$2.0bn
L17: Change in NWC p.a. ($m, negative = investment) | N17: 0 | O17: A | P17: Assumed flat
B18: EBITDA | E18: =E19*E15 | F18: =F19*F15 | G18: =G19*G15 | H18: =H19*H15 | I18: =I19*I15 | J18: =J19*J15 | L18: Exit multiple (x) | N18: 6 | O18: A | P18: Auto OEM exit multiple, assumption
B19: % margin | E19: =N14 | F19: 0.035 | G19: 0.045 | H19: 0.055 | I19: 0.06 | J19: 0.06 | L19: Entry date | N19: 39297 | O19: F | P19: Closing date per filings
L20: Underwritten exit date (5-year hold) | N20: 41124 | O20: A | P20: Template convention: five projection years
B21: LFCF Build | L21: Actual exit / valuation date | N21: 39933 | O21: F | P21: Realised exit date per filings
B22: EBITDA | F22: =F18 | G22: =G18 | H22: =H18 | I22: =I18 | J22: =J18
B23: (-) D&A | F23: =-$N$15 | G23: =-$N$15 | H23: =-$N$15 | I23: =-$N$15 | J23: =-$N$15
B24: EBIT | F24: =F22+F23 | G24: =G22+G23 | H24: =H22+H23 | I24: =I22+I23 | J24: =J22+J23
B25: (-) Cash Interest | D25: =N10 | F25: =$E$12*-$D$25 | G25: =$E$12*-$D$25 | H25: =$E$12*-$D$25 | I25: =$E$12*-$D$25 | J25: =$E$12*-$D$25
B26: EBT | F26: =F24+F25 | G26: =G24+G25 | H26: =H24+H25 | I26: =I24+I25 | J26: =J24+J25
B27: (-) Taxes | D27: =N11 | F27: =F26*-$D27 | G27: =G26*-$D27 | H27: =H26*-$D27 | I27: =I26*-$D27 | J27: =J26*-$D27
B28: Net Income | F28: =F26+F27 | G28: =G26+G27 | H28: =H26+H27 | I28: =I26+I27 | J28: =J26+J27
B29: (+) D&A | F29: =-F23 | G29: =-G23 | H29: =-H23 | I29: =-I23 | J29: =-J23
B30: (-) Capex | F30: =-$N$16 | G30: =-$N$16 | H30: =-$N$16 | I30: =-$N$16 | J30: =-$N$16
B31: (-) Change in NWC | F31: =$N$17 | G31: =$N$17 | H31: =$N$17 | I31: =$N$17 | J31: =$N$17
B32: Levered FCF | F32: =SUM(F28:F31) | G32: =SUM(G28:G31) | H32: =SUM(H28:H31) | I32: =SUM(I28:I31) | J32: =SUM(J28:J31)
B33: Cumulative LFCF | F33: =SUM($E32:F32) | G33: =SUM($E32:G32) | H33: =SUM($E32:H32) | I33: =SUM($E32:I32) | J33: =SUM($E32:J32)
B35: Returns — UNDERWRITTEN CASE (template mechanics: interest on opening debt, all LFCF accumulates as cash)
B37: Exit EBITDA (2011) | E37: =J18
B38: (x) Exit Multiple | E38: =N18
B39: Enterprise Value | E39: =E37*E38
B40: (-) Debt | E40: =-E12
B41: (+) Cash | E41: =J33
B42: Equity Value at Exit | E42: =SUM(E39:E41)
B43: Initial Equity Investment | E43: =E6
B45: MoM | E45: =E42/E43
B46: IRR | E46: =XIRR(E48:E49,B48:B49)
B48: =N19 | E48: =-E6
B49: =N20 | E49: =E42
B52: ACTUAL OUTCOME
B53: Exit enterprise value, actual ($m) | E53: 2000
B54: Debt at exit ($m) | E54: 6900
B55: Equity value at exit ($m) | E55: =E53-E54
B56: Equity invested (from Sources) ($m) | E56: =E6
B57: MoM, actual | E57: =E55/E56
B58: IRR, actual | E58: =IFERROR(XIRR(E62:E63,B62:B63),"n/m")
B59: MoM variance vs underwritten | E59: =E57-E45
B60: IRR variance vs underwritten (pts) | E60: =IFERROR((E58-E46)*100,"n/m")
B62: =N19 | E62: =-E6 | G62: cash flows for XIRR (actual)
B63: =N21 | E63: =E55
B65: Actual outcome note:
B66: Chapter 11 filed 30 Apr 2009. First-lien lenders (~$6.9bn) took $2.0bn cash (~29c) in the 363 sale to New Chrysler; second lien and equity recovered nothing. 2008 EBITDA was $0.3bn on $55.9bn revenue (Chrysler restructuring plan to Treasury, Feb-2009). Sponsor equity: total loss.
B71: Deal note:
B72: The sponsor case required EBITDA to go from ~$1.5bn to ~$3.5bn. Actual 2008 EBITDA was $0.3bn. No capital structure survives that.
B77: Classification: Private equity carve-out | Status: Realised 2009: equity written to zero

Sheet P07 Caterpillar-Bucyrus 2011
B2: Caterpillar / Bucyrus (2011) [STRATEGIC] — Paper LBO
B3: STRATEGIC TRANSACTION, NOT AN LBO. The acquirer was a corporate; the "debt" is corporate notes and the "equity" is balance-sheet cash. The LBO template is applied only to show what the entry price required.
B4: Sources | G4: Uses | L4: INPUTS | N4: Value | O4: Tag | P4: Source (F = filed / rating agency, P = press, A = assumption; blue = assumption)
B5: Debt | E5: =E12 | G5: Purchase Price | J5: =J12 | L5: Entry enterprise value ($m) | N5: 8800 | O5: F | P5: Total purchase price as booked incl. $1.6bn assumed debt (CAT 2011 10-K)
B6: Equity (plug) | E6: =E7-E5 | L6: Entry EBITDA, LTM ($m) | N6: 637.3 | O6: F | P6: Bucyrus FY2010 EBITDA $637.3m; adjusted $720.6m (8-K Ex-99)
B7: Total Sources | E7: =J7 | G7: Total Uses | J7: =J5 | L7: Entry multiple (x) | N7: =N5/N6 | O7: calc | P7: Derived
L8: Debt raised ($m) | N8: 4500 | O8: F | P8: $4.5bn five-tranche notes, May-2011 (FWP)
B9: Build to Debt | G9: Build to Purchase Price | L9: Leverage (x EBITDA) | N9: =N8/N6 | O9: calc | P9: Derived
B10: 2010 EBITDA (LTM) | E10: =E18 | G10: 2010 EBITDA (LTM) | J10: =E18 | L10: Blended cash interest rate | N10: 0.0287 | O10: F | P10: Weighted coupon: fixed tranches 3.82%; all five ~2.87% at 3M LIBOR ~0.26%
B11: (x) Leverage | E11: =N9 | G11: (x) Multiple of 2023 EBITDA | J11: =N7 | L11: Tax rate | N11: 0.3 | O11: A | P11: Assumption
B12: Debt | E12: =E10*E11 | G12: Purchase Price | J12: =J10*J11 | L12: Base-year revenue ($m) | N12: 3650 | O12: F | P12: Bucyrus FY2010 sales (8-K Ex-99)
L13: Incremental revenue p.a. ($m) | N13: 365 | O13: A | P13: Underwritten case: ~10% p.a. plus >$400m synergies by 2015 (announcement)
B14: Simple P&L | E14: 2010 | F14: =E14+1 | G14: =F14+1 | H14: =G14+1 | I14: =H14+1 | J14: =I14+1 | L14: EBITDA margin, base year | N14: =N6/N12 | O14: calc | P14: Derived
B15: Revenue | E15: =N12 | F15: =E15+F16 | G15: =F15+G16 | H15: =G15+H16 | I15: =H15+I16 | J15: =I15+J16 | L15: D&A p.a. ($m) | N15: 100.6 | O15: F | P15: FY2010 depreciation $54.1m + amortisation $46.6m (10-K Ex-13); excludes the $3.9bn acquired-intangible amortisation
B16: $ Incremental Revenue | F16: =N13 | G16: =F16 | H16: =G16 | I16: =H16 | J16: =I16 | L16: Capex p.a. ($m) | N16: 100 | O16: F | P16: 2011 guidance ~$100m (FY2010 actual $69.4m)
L17: Change in NWC p.a. ($m, negative = investment) | N17: -50 | O17: A | P17: Assumption for a growing backlog business
B18: EBITDA | E18: =E19*E15 | F18: =F19*F15 | G18: =G19*G15 | H18: =H19*H15 | I18: =I19*I15 | J18: =J19*J15 | L18: Exit multiple (x) | N18: 10 | O18: A | P18: Mining equipment mid-cycle multiple, assumption
B19: % margin | E19: =N14 | F19: 0.19 | G19: 0.21 | H19: 0.23 | I19: 0.25 | J19: 0.26 | L19: Entry date | N19: 40732 | O19: F | P19: Closing date per filings
L20: Underwritten exit date (5-year hold) | N20: 42559 | O20: A | P20: Template convention: five projection years
B21: LFCF Build | L21: Actual exit / valuation date | N21: n/a | O21: F | P21: No realised exit
B22: EBITDA | F22: =F18 | G22: =G18 | H22: =H18 | I22: =I18 | J22: =J18
B23: (-) D&A | F23: =-$N$15 | G23: =-$N$15 | H23: =-$N$15 | I23: =-$N$15 | J23: =-$N$15
B24: EBIT | F24: =F22+F23 | G24: =G22+G23 | H24: =H22+H23 | I24: =I22+I23 | J24: =J22+J23
B25: (-) Cash Interest | D25: =N10 | F25: =$E$12*-$D$25 | G25: =$E$12*-$D$25 | H25: =$E$12*-$D$25 | I25: =$E$12*-$D$25 | J25: =$E$12*-$D$25
B26: EBT | F26: =F24+F25 | G26: =G24+G25 | H26: =H24+H25 | I26: =I24+I25 | J26: =J24+J25
B27: (-) Taxes | D27: =N11 | F27: =F26*-$D27 | G27: =G26*-$D27 | H27: =H26*-$D27 | I27: =I26*-$D27 | J27: =J26*-$D27
B28: Net Income | F28: =F26+F27 | G28: =G26+G27 | H28: =H26+H27 | I28: =I26+I27 | J28: =J26+J27
B29: (+) D&A | F29: =-F23 | G29: =-G23 | H29: =-H23 | I29: =-I23 | J29: =-J23
B30: (-) Capex | F30: =-$N$16 | G30: =-$N$16 | H30: =-$N$16 | I30: =-$N$16 | J30: =-$N$16
B31: (-) Change in NWC | F31: =$N$17 | G31: =$N$17 | H31: =$N$17 | I31: =$N$17 | J31: =$N$17
B32: Levered FCF | F32: =SUM(F28:F31) | G32: =SUM(G28:G31) | H32: =SUM(H28:H31) | I32: =SUM(I28:I31) | J32: =SUM(J28:J31)
B33: Cumulative LFCF | F33: =SUM($E32:F32) | G33: =SUM($E32:G32) | H33: =SUM($E32:H32) | I33: =SUM($E32:I32) | J33: =SUM($E32:J32)
B35: Returns — UNDERWRITTEN CASE (template mechanics: interest on opening debt, all LFCF accumulates as cash)
B37: Exit EBITDA (2015) | E37: =J18
B38: (x) Exit Multiple | E38: =N18
B39: Enterprise Value | E39: =E37*E38
B40: (-) Debt | E40: =-E12
B41: (+) Cash | E41: =J33
B42: Equity Value at Exit | E42: =SUM(E39:E41)
B43: Initial Equity Investment | E43: =E6
B45: MoM | E45: =E42/E43
B46: IRR | E46: =XIRR(E48:E49,B48:B49)
B48: =N19 | E48: =-E6
B49: =N20 | E49: =E42
B52: ACTUAL OUTCOME
B53: Exit enterprise value, actual ($m) | E53: undisclosed
B54: Debt at exit ($m)
B55: Equity value at exit ($m)
B56: Equity invested (from Sources) ($m)
B57: MoM, actual
B58: IRR, actual
B59: MoM variance vs underwritten
B60: IRR variance vs underwritten (pts)
B65: Actual outcome note:
B66: Never exited. Bucyrus contributed $2,524m of sales and a $(96)m operating loss in the 2011 stub, $4,758m and $257m in 2012. Caterpillar Resource Industries segment then fell from $21.2bn sales / $4.3bn profit (2012) to $5.7bn / $(1,047)m (2016), the year of the $595m Surface Mining & Technology goodwill impairment and $132m intangible write-down.
B71: Deal note:
B72: Not a sponsor deal. The notes were Caterpillar corporate debt at ~2.9%, and the 'equity' was balance-sheet cash. The template is used to show what the price required: EBITDA roughly doubling on a 13.8x entry. The cycle turned the other way within eighteen months.
B77: Classification: STRATEGIC public M&A, debt-financed (not an LBO) | Status: Held; $595m goodwill impairment Q4-2016

Sheet P08 NRG-DirectEnergy 2021
B2: NRG / Direct Energy (2021) [STRATEGIC] — Paper LBO
B3: STRATEGIC TRANSACTION, NOT AN LBO. The acquirer was a corporate; the "debt" is corporate notes and the "equity" is balance-sheet cash. The LBO template is applied only to show what the entry price required.
B4: Sources | G4: Uses | L4: INPUTS | N4: Value | O4: Tag | P4: Source (F = filed / rating agency, P = press, A = assumption; blue = assumption)
B5: Debt | E5: =E12 | G5: Purchase Price | J5: =J12 | L5: Entry enterprise value ($m) | N5: 3625 | O5: F | P5: Purchase price, debt-free cash-free (Centrica / NRG releases)
B6: Equity (plug) | E6: =E7-E5 | L6: Entry EBITDA, LTM ($m) | N6: 457 | O6: F | P6: 2019 underlying adjusted EBITDA $457m / GBP358m (Centrica Class 1 circular); 7.9x
B7: Total Sources | E7: =J7 | G7: Total Uses | J7: =J5 | L7: Entry multiple (x) | N7: =N5/N6 | O7: calc | P7: Derived
L8: Debt raised ($m) | N8: 2930 | O8: F | P8: $1.40bn secured notes (2.000%/2.450%) + $1.53bn unsecured (3.375%/3.625%); $900m P-Caps excluded
B9: Build to Debt | G9: Build to Purchase Price | L9: Leverage (x EBITDA) | N9: =N8/N6 | O9: calc | P9: Derived
B10: 2019 EBITDA (LTM) | E10: =E18 | G10: 2019 EBITDA (LTM) | J10: =E18 | L10: Blended cash interest rate | N10: 0.02944 | O10: F | P10: Weighted coupon on the $2.93bn: 2.944% (computed from the pricing release)
B11: (x) Leverage | E11: =N9 | G11: (x) Multiple of 2023 EBITDA | J11: =N7 | L11: Tax rate | N11: 0.21 | O11: A | P11: US federal rate
B12: Debt | E12: =E10*E11 | G12: Purchase Price | J12: =J10*J11 | L12: Base-year revenue ($m) | N12: 13935 | O12: F | P12: Direct Energy 2019 US GAAP revenue (NRG pro forma 8-K, Nov-2020)
L13: Incremental revenue p.a. ($m) | N13: 0 | O13: F | P13: Flat revenue; value case is the $300m synergy ramp
B14: Simple P&L | E14: 2019 | F14: =E14+1 | G14: =F14+1 | H14: =G14+1 | I14: =H14+1 | J14: =I14+1 | L14: EBITDA margin, base year | N14: =N6/N12 | O14: calc | P14: Derived
B15: Revenue | E15: =N12 | F15: =E15+F16 | G15: =F15+G16 | H15: =G15+H16 | I15: =H15+I16 | J15: =I15+J16 | L15: D&A p.a. ($m) | N15: 101 | O15: F | P15: Direct Energy 2019 US GAAP D&A (NRG pro forma)
B16: $ Incremental Revenue | F16: =N13 | G16: =F16 | H16: =G16 | I16: =H16 | J16: =I16 | L16: Capex p.a. ($m) | N16: 100 | O16: A | P16: Assumption (standalone capex not disclosed)
L17: Change in NWC p.a. ($m, negative = investment) | N17: 0 | O17: A | P17: Assumed flat
B18: EBITDA | E18: =E19*E15 | F18: =F19*F15 | G18: =G19*G15 | H18: =H19*H15 | I18: =I19*I15 | J18: =J19*J15 | L18: Exit multiple (x) | N18: 8 | O18: A | P18: Retail energy multiple, assumption (entry 7.9x)
B19: % margin | E19: =N14 | F19: 0.0425 | G19: 0.049 | H19: 0.0543 | I19: 0.0543 | J19: 0.0543 | L19: Entry date | N19: 44201 | O19: F | P19: Closing date per filings
L20: Underwritten exit date (5-year hold) | N20: 46027 | O20: A | P20: Template convention: five projection years
B21: LFCF Build | L21: Actual exit / valuation date | N21: n/a | O21: F | P21: No realised exit
B22: EBITDA | F22: =F18 | G22: =G18 | H22: =H18 | I22: =I18 | J22: =J18
B23: (-) D&A | F23: =-$N$15 | G23: =-$N$15 | H23: =-$N$15 | I23: =-$N$15 | J23: =-$N$15
B24: EBIT | F24: =F22+F23 | G24: =G22+G23 | H24: =H22+H23 | I24: =I22+I23 | J24: =J22+J23
B25: (-) Cash Interest | D25: =N10 | F25: =$E$12*-$D$25 | G25: =$E$12*-$D$25 | H25: =$E$12*-$D$25 | I25: =$E$12*-$D$25 | J25: =$E$12*-$D$25
B26: EBT | F26: =F24+F25 | G26: =G24+G25 | H26: =H24+H25 | I26: =I24+I25 | J26: =J24+J25
B27: (-) Taxes | D27: =N11 | F27: =F26*-$D27 | G27: =G26*-$D27 | H27: =H26*-$D27 | I27: =I26*-$D27 | J27: =J26*-$D27
B28: Net Income | F28: =F26+F27 | G28: =G26+G27 | H28: =H26+H27 | I28: =I26+I27 | J28: =J26+J27
B29: (+) D&A | F29: =-F23 | G29: =-G23 | H29: =-H23 | I29: =-I23 | J29: =-J23
B30: (-) Capex | F30: =-$N$16 | G30: =-$N$16 | H30: =-$N$16 | I30: =-$N$16 | J30: =-$N$16
B31: (-) Change in NWC | F31: =$N$17 | G31: =$N$17 | H31: =$N$17 | I31: =$N$17 | J31: =$N$17
B32: Levered FCF | F32: =SUM(F28:F31) | G32: =SUM(G28:G31) | H32: =SUM(H28:H31) | I32: =SUM(I28:I31) | J32: =SUM(J28:J31)
B33: Cumulative LFCF | F33: =SUM($E32:F32) | G33: =SUM($E32:G32) | H33: =SUM($E32:H32) | I33: =SUM($E32:I32) | J33: =SUM($E32:J32)
B35: Returns — UNDERWRITTEN CASE (template mechanics: interest on opening debt, all LFCF accumulates as cash)
B37: Exit EBITDA (2024) | E37: =J18
B38: (x) Exit Multiple | E38: =N18
B39: Enterprise Value | E39: =E37*E38
B40: (-) Debt | E40: =-E12
B41: (+) Cash | E41: =J33
B42: Equity Value at Exit | E42: =SUM(E39:E41)
B43: Initial Equity Investment | E43: =E6
B45: MoM | E45: =E42/E43
B46: IRR | E46: =XIRR(E48:E49,B48:B49)
B48: =N19 | E48: =-E6
B49: =N20 | E49: =E42
B52: ACTUAL OUTCOME
B53: Exit enterprise value, actual ($m) | E53: undisclosed
B54: Debt at exit ($m)
B55: Equity value at exit ($m)
B56: Equity invested (from Sources) ($m)
B57: MoM, actual
B58: IRR, actual
B59: MoM variance vs underwritten
B60: IRR variance vs underwritten (pts)
B65: Actual outcome note:
B66: Never exited. Synergies: $175m run-rate in 2021 vs $135m plan, $259m cumulative 2022, $300m completed 2023. Winter Storm Uri cost NRG $967m in Q1-2021, six weeks after closing. NRG East segment adjusted EBITDA (closest proxy for the ex-Texas Direct Energy book): $437m 2020, $988m 2021, $773m 2022, $780m 2023, $1,006m 2024.
B71: Deal note:
B72: Not a sponsor deal. Financed with investment-grade-style notes at 2.9%, so the equity is simply the ~$700m not covered by the notes. Shown to isolate what a 7.9x entry with a $300m synergy plan implies.
B77: Classification: STRATEGIC corporate carve-out, note-financed (not an LBO) | Status: Held; $300m synergy programme completed 2023

Sheet P09 WindPoint-Pacific 2001
B2: Wind Point / Pacific Cycle (2000-04) — Paper LBO
B4: Sources | G4: Uses | L4: INPUTS | N4: Value | O4: Tag | P4: Source (F = filed / rating agency, P = press, A = assumption; blue = assumption)
B5: Debt | E5: =E12 | G5: Purchase Price | J5: =J12 | L5: Entry enterprise value ($m) | N5: 146 | O5: P | P5: $60m Brunswick bicycle business + $86m Schwinn/GT auction (Forbes, Lincoln International, Crain's)
B6: Equity (plug) | E6: =E7-E5 | L6: Entry EBITDA, LTM ($m) | N6: 22 | O6: A | P6: Assumption: ~8% margin on 2001 revenue (no EBITDA ever disclosed)
B7: Total Sources | E7: =J7 | G7: Total Uses | J7: =J5 | L7: Entry multiple (x) | N7: =N5/N6 | O7: calc | P7: Derived
L8: Debt raised ($m) | N8: 120 | O8: A | P8: Assumption: Wind Point put $3m of equity into the $60m Brunswick deal (Forbes); structure otherwise undisclosed
B9: Build to Debt | G9: Build to Purchase Price | L9: Leverage (x EBITDA) | N9: =N8/N6 | O9: calc | P9: Derived
B10: 2001 EBITDA (LTM) | E10: =E18 | G10: 2001 EBITDA (LTM) | J10: =E18 | L10: Blended cash interest rate | N10: 0.08 | O10: A | P10: Assumption
B11: (x) Leverage | E11: =N9 | G11: (x) Multiple of 2023 EBITDA | J11: =N7 | L11: Tax rate | N11: 0.38 | O11: A | P11: Assumption
B12: Debt | E12: =E10*E11 | G12: Purchase Price | J12: =J10*J11 | L12: Base-year revenue ($m) | N12: 280 | O12: P | P12: Forbes (Oct-2002): 2001 revenue ~$280m after Brunswick and Schwinn/GT
L13: Incremental revenue p.a. ($m) | N13: 22 | O13: F | P13: 2003 sales 'in excess of US$325m' (Dorel 6-K)
B14: Simple P&L | E14: 2001 | F14: =E14+1 | G14: =F14+1 | H14: =G14+1 | I14: =H14+1 | J14: =I14+1 | L14: EBITDA margin, base year | N14: =N6/N12 | O14: calc | P14: Derived
B15: Revenue | E15: =N12 | F15: =E15+F16 | G15: =F15+G16 | H15: =G15+H16 | I15: =H15+I16 | J15: =I15+J16 | L15: D&A p.a. ($m) | N15: 1 | O15: F | P15: Dorel recorded only $0.5m of segment D&A in 2004; asset-light importer
B16: $ Incremental Revenue | F16: =N13 | G16: =F16 | H16: =G16 | I16: =H16 | J16: =I16 | L16: Capex p.a. ($m) | N16: 1.5 | O16: A | P16: Assumption
L17: Change in NWC p.a. ($m, negative = investment) | N17: -3 | O17: A | P17: Growth working capital, assumption
B18: EBITDA | E18: =E19*E15 | F18: =F19*F15 | G18: =G19*G15 | H18: =H19*H15 | I18: =I19*I15 | J18: =J19*J15 | L18: Exit multiple (x) | N18: 5.8 | O18: F | P18: $310m / annualised 2004 segment EBIT $53.9m (Dorel FY2004 MD&A); D&A negligible
B19: % margin | E19: =N14 | F19: =E19 | G19: =F19 | H19: =G19 | I19: =H19 | J19: =I19 | L19: Entry date | N19: 37164 | O19: F | P19: Closing date per filings
L20: Underwritten exit date (5-year hold) | N20: 38988 | O20: A | P20: Template convention: five projection years
B21: LFCF Build | L21: Actual exit / valuation date | N21: 38020 | O21: F | P21: Realised exit date per filings
B22: EBITDA | F22: =F18 | G22: =G18 | H22: =H18 | I22: =I18 | J22: =J18
B23: (-) D&A | F23: =-$N$15 | G23: =-$N$15 | H23: =-$N$15 | I23: =-$N$15 | J23: =-$N$15
B24: EBIT | F24: =F22+F23 | G24: =G22+G23 | H24: =H22+H23 | I24: =I22+I23 | J24: =J22+J23
B25: (-) Cash Interest | D25: =N10 | F25: =$E$12*-$D$25 | G25: =$E$12*-$D$25 | H25: =$E$12*-$D$25 | I25: =$E$12*-$D$25 | J25: =$E$12*-$D$25
B26: EBT | F26: =F24+F25 | G26: =G24+G25 | H26: =H24+H25 | I26: =I24+I25 | J26: =J24+J25
B27: (-) Taxes | D27: =N11 | F27: =F26*-$D27 | G27: =G26*-$D27 | H27: =H26*-$D27 | I27: =I26*-$D27 | J27: =J26*-$D27
B28: Net Income | F28: =F26+F27 | G28: =G26+G27 | H28: =H26+H27 | I28: =I26+I27 | J28: =J26+J27
B29: (+) D&A | F29: =-F23 | G29: =-G23 | H29: =-H23 | I29: =-I23 | J29: =-J23
B30: (-) Capex | F30: =-$N$16 | G30: =-$N$16 | H30: =-$N$16 | I30: =-$N$16 | J30: =-$N$16
B31: (-) Change in NWC | F31: =$N$17 | G31: =$N$17 | H31: =$N$17 | I31: =$N$17 | J31: =$N$17
B32: Levered FCF | F32: =SUM(F28:F31) | G32: =SUM(G28:G31) | H32: =SUM(H28:H31) | I32: =SUM(I28:I31) | J32: =SUM(J28:J31)
B33: Cumulative LFCF | F33: =SUM($E32:F32) | G33: =SUM($E32:G32) | H33: =SUM($E32:H32) | I33: =SUM($E32:I32) | J33: =SUM($E32:J32)
B35: Returns — UNDERWRITTEN CASE (template mechanics: interest on opening debt, all LFCF accumulates as cash)
B37: Exit EBITDA (2006) | E37: =J18
B38: (x) Exit Multiple | E38: =N18
B39: Enterprise Value | E39: =E37*E38
B40: (-) Debt | E40: =-E12
B41: (+) Cash | E41: =J33
B42: Equity Value at Exit | E42: =SUM(E39:E41)
B43: Initial Equity Investment | E43: =E6
B45: MoM | E45: =E42/E43
B46: IRR | E46: =XIRR(E48:E49,B48:B49)
B48: =N19 | E48: =-E6
B49: =N20 | E49: =E42
B52: ACTUAL OUTCOME
B53: Exit enterprise value, actual ($m) | E53: 310
B54: Debt at exit ($m) | E54: 90
B55: Equity value at exit ($m) | E55: =E53-E54
B56: Equity invested (from Sources) ($m) | E56: =E6
B57: MoM, actual | E57: =E55/E56
B58: IRR, actual | E58: =IFERROR(XIRR(E62:E63,B62:B63),"n/m")
B59: MoM variance vs underwritten | E59: =E57-E45
B60: IRR variance vs underwritten (pts) | E60: =IFERROR((E58-E46)*100,"n/m")
B62: =N19 | E62: =-E6 | G62: cash flows for XIRR (actual)
B63: =N21 | E63: =E55
B65: Actual outcome note:
B66: Exit EV $310m (Dorel 6-K; $320.5m 'total value' incl. balance of sale). Exit debt assumed $90m after three years of paydown. Wind Point held 43% (CIBC advisory notice); its total cost basis ($12.5m original + $3m Brunswick + Schwinn equity undisclosed) cannot be fully stated.
B71: Deal note:
B72: EV went from $146m to $310m in about 30 months. Everything about the equity return depends on undisclosed leverage.
B77: Classification: Sponsor platform build and exit | Status: Realised Feb-2004

Sheet P10 Pegasus-Cannondale 2003
B2: Pegasus Capital / Cannondale (2003-08) — Paper LBO
B4: Sources | G4: Uses | L4: INPUTS | N4: Value | O4: Tag | P4: Source (F = filed / rating agency, P = press, A = assumption; blue = assumption)
B5: Debt | E5: =E12 | G5: Purchase Price | J5: =J12 | L5: Entry enterprise value ($m) | N5: 58 | O5: P | P5: Bicycle assets bought for ~$55m at the 20 Mar 2003 auction; '~$58m' per Bicycle Retailer
B6: Equity (plug) | E6: =E7-E5 | L6: Entry EBITDA, LTM ($m) | N6: 8 | O6: A | P6: Assumption: post-emergence ~5.7% margin (FY2002 operating loss $(12.2)m)
B7: Total Sources | E7: =J7 | G7: Total Uses | J7: =J5 | L7: Entry multiple (x) | N7: =N5/N6 | O7: calc | P7: Derived
L8: Debt raised ($m) | N8: 30 | O8: A | P8: Assumption: CIT provided DIP and exit financing; quantum undisclosed
B9: Build to Debt | G9: Build to Purchase Price | L9: Leverage (x EBITDA) | N9: =N8/N6 | O9: calc | P9: Derived
B10: 2003 EBITDA (LTM) | E10: =E18 | G10: 2003 EBITDA (LTM) | J10: =E18 | L10: Blended cash interest rate | N10: 0.09 | O10: A | P10: Assumption
B11: (x) Leverage | E11: =N9 | G11: (x) Multiple of 2023 EBITDA | J11: =N7 | L11: Tax rate | N11: 0.38 | O11: A | P11: Assumption
B12: Debt | E12: =E10*E11 | G12: Purchase Price | J12: =J10*J11 | L12: Base-year revenue ($m) | N12: 140 | O12: A | P12: Assumption: FY2002 sales $156.7m (last 10-K) less the retained motorsports line and the bankruptcy year
L13: Incremental revenue p.a. ($m) | N13: 12 | O13: F | P13: Cannondale + Sugoi ~$200m sales in 2007 (Dorel 6-K)
B14: Simple P&L | E14: 2003 | F14: =E14+1 | G14: =F14+1 | H14: =G14+1 | I14: =H14+1 | J14: =I14+1 | L14: EBITDA margin, base year | N14: =N6/N12 | O14: calc | P14: Derived
B15: Revenue | E15: =N12 | F15: =E15+F16 | G15: =F15+G16 | H15: =G15+H16 | I15: =H15+I16 | J15: =I15+J16 | L15: D&A p.a. ($m) | N15: 4 | O15: A | P15: Assumption
B16: $ Incremental Revenue | F16: =N13 | G16: =F16 | H16: =G16 | I16: =H16 | J16: =I16 | L16: Capex p.a. ($m) | N16: 4 | O16: A | P16: Assumption
L17: Change in NWC p.a. ($m, negative = investment) | N17: -2 | O17: A | P17: Assumption
B18: EBITDA | E18: =E19*E15 | F18: =F19*F15 | G18: =G19*G15 | H18: =H19*H15 | I18: =I19*I15 | J18: =J19*J15 | L18: Exit multiple (x) | N18: 9.75 | O18: A | P18: $195m midpoint / ~$20m 2007 EBITDA (assumption; Dorel disclosed sales only)
B19: % margin | E19: =N14 | F19: 0.07 | G19: 0.08 | H19: 0.09 | I19: 0.1 | J19: 0.1 | L19: Entry date | N19: 37700 | O19: F | P19: Closing date per filings
L20: Underwritten exit date (5-year hold) | N20: 39527 | O20: A | P20: Template convention: five projection years
B21: LFCF Build | L21: Actual exit / valuation date | N21: 39482 | O21: F | P21: Realised exit date per filings
B22: EBITDA | F22: =F18 | G22: =G18 | H22: =H18 | I22: =I18 | J22: =J18
B23: (-) D&A | F23: =-$N$15 | G23: =-$N$15 | H23: =-$N$15 | I23: =-$N$15 | J23: =-$N$15
B24: EBIT | F24: =F22+F23 | G24: =G22+G23 | H24: =H22+H23 | I24: =I22+I23 | J24: =J22+J23
B25: (-) Cash Interest | D25: =N10 | F25: =$E$12*-$D$25 | G25: =$E$12*-$D$25 | H25: =$E$12*-$D$25 | I25: =$E$12*-$D$25 | J25: =$E$12*-$D$25
B26: EBT | F26: =F24+F25 | G26: =G24+G25 | H26: =H24+H25 | I26: =I24+I25 | J26: =J24+J25
B27: (-) Taxes | D27: =N11 | F27: =F26*-$D27 | G27: =G26*-$D27 | H27: =H26*-$D27 | I27: =I26*-$D27 | J27: =J26*-$D27
B28: Net Income | F28: =F26+F27 | G28: =G26+G27 | H28: =H26+H27 | I28: =I26+I27 | J28: =J26+J27
B29: (+) D&A | F29: =-F23 | G29: =-G23 | H29: =-H23 | I29: =-I23 | J29: =-J23
B30: (-) Capex | F30: =-$N$16 | G30: =-$N$16 | H30: =-$N$16 | I30: =-$N$16 | J30: =-$N$16
B31: (-) Change in NWC | F31: =$N$17 | G31: =$N$17 | H31: =$N$17 | I31: =$N$17 | J31: =$N$17
B32: Levered FCF | F32: =SUM(F28:F31) | G32: =SUM(G28:G31) | H32: =SUM(H28:H31) | I32: =SUM(I28:I31) | J32: =SUM(J28:J31)
B33: Cumulative LFCF | F33: =SUM($E32:F32) | G33: =SUM($E32:G32) | H33: =SUM($E32:H32) | I33: =SUM($E32:I32) | J33: =SUM($E32:J32)
B35: Returns — UNDERWRITTEN CASE (template mechanics: interest on opening debt, all LFCF accumulates as cash)
B37: Exit EBITDA (2008) | E37: =J18
B38: (x) Exit Multiple | E38: =N18
B39: Enterprise Value | E39: =E37*E38
B40: (-) Debt | E40: =-E12
B41: (+) Cash | E41: =J33
B42: Equity Value at Exit | E42: =SUM(E39:E41)
B43: Initial Equity Investment | E43: =E6
B45: MoM | E45: =E42/E43
B46: IRR | E46: =XIRR(E48:E49,B48:B49)
B48: =N19 | E48: =-E6
B49: =N20 | E49: =E42
B52: ACTUAL OUTCOME
B53: Exit enterprise value, actual ($m) | E53: 195
B54: Debt at exit ($m) | E54: 30
B55: Equity value at exit ($m) | E55: =E53-E54
B56: Equity invested (from Sources) ($m) | E56: =E6
B57: MoM, actual | E57: =E55/E56
B58: IRR, actual | E58: =IFERROR(XIRR(E62:E63,B62:B63),"n/m")
B59: MoM variance vs underwritten | E59: =E57-E45
B60: IRR variance vs underwritten (pts) | E60: =IFERROR((E58-E46)*100,"n/m")
B62: =N19 | E62: =-E6 | G62: cash flows for XIRR (actual)
B63: =N21 | E63: =E55
B65: Actual outcome note:
B66: Exit EV $190-200m, earnings-contingent to 30 Jun 2008 (Dorel 6-K); final price after the earnout is in Dorel's FY2008 SEDAR statements, not retrieved. Exit debt assumed equal to entry.
B71: Deal note:
B72: Roughly 3.4x on enterprise value in five years, on a business bought out of Chapter 11 at 0.37x sales.
B77: Classification: Distressed 363 purchase and exit | Status: Realised Q1-2008

Sheet P11 Cerberus-Dorel 2021 TERM
B2: Cerberus + Koch / Dorel (2021) [TERMINATED] — Paper LBO
B4: Sources | G4: Uses | L4: INPUTS | N4: Value | O4: Tag | P4: Source (F = filed / rating agency, P = press, A = assumption; blue = assumption)
B5: Debt | E5: =E12 | G5: Purchase Price | J5: =J12 | L5: Entry enterprise value ($m) | N5: 1012 | O5: F | P5: Aggregate purchase price incl. assumed debt and ~$65m fees (Dorel release, 1 Feb 2021); ~8.5x
B6: Equity (plug) | E6: =E7-E5 | L6: Entry EBITDA, LTM ($m) | N6: 119.6 | O6: F | P6: Buyer's adjusted LTM EBITDA to 30 Sep 2020 (Dorel release, 1 Feb 2021); Letko says it embeds $44.5m of downward adjustments
B7: Total Sources | E7: =J7 | G7: Total Uses | J7: =J5 | L7: Entry multiple (x) | N7: =N5/N6 | O7: calc | P7: Derived
L8: Debt raised ($m) | N8: 500 | O8: F | P8: Funded debt from third-party lenders (Dorel release, 1 Feb 2021)
B9: Build to Debt | G9: Build to Purchase Price | L9: Leverage (x EBITDA) | N9: =N8/N6 | O9: calc | P9: Derived
B10: 2020 EBITDA (LTM) | E10: =E18 | G10: 2020 EBITDA (LTM) | J10: =E18 | L10: Blended cash interest rate | N10: 0.07 | O10: A | P10: Assumption
B11: (x) Leverage | E11: =N9 | G11: (x) Multiple of 2023 EBITDA | J11: =N7 | L11: Tax rate | N11: 0.26 | O11: A | P11: Canadian blended, assumption
B12: Debt | E12: =E10*E11 | G12: Purchase Price | J12: =J10*J11 | L12: Base-year revenue ($m) | N12: 2762.5 | O12: F | P12: Dorel FY2020 revenue (Q4-2020 results)
L13: Incremental revenue p.a. ($m) | N13: 80 | O13: A | P13: ~3% p.a., assumption
B14: Simple P&L | E14: 2020 | F14: =E14+1 | G14: =F14+1 | H14: =G14+1 | I14: =H14+1 | J14: =I14+1 | L14: EBITDA margin, base year | N14: =N6/N12 | O14: calc | P14: Derived
B15: Revenue | E15: =N12 | F15: =E15+F16 | G15: =F15+G16 | H15: =G15+H16 | I15: =H15+I16 | J15: =I15+J16 | L15: D&A p.a. ($m) | N15: 98.1 | O15: F | P15: FY2020 consolidated D&A (cash-flow statement)
B16: $ Incremental Revenue | F16: =N13 | G16: =F16 | H16: =G16 | I16: =H16 | J16: =I16 | L16: Capex p.a. ($m) | N16: 40 | O16: A | P16: Assumption
L17: Change in NWC p.a. ($m, negative = investment) | N17: 0 | O17: A | P17: Assumed flat
B18: EBITDA | E18: =E19*E15 | F18: =F19*F15 | G18: =G19*G15 | H18: =H19*H15 | I18: =I19*I15 | J18: =J19*J15 | L18: Exit multiple (x) | N18: 8.5 | O18: A | P18: Assumed equal to entry
B19: % margin | E19: =N14 | F19: =E19 | G19: =F19 | H19: =G19 | I19: =H19 | J19: =I19 | L19: Entry date | N19: 44243 | O19: F | P19: Closing date per filings
L20: Underwritten exit date (5-year hold) | N20: 46069 | O20: A | P20: Template convention: five projection years
B21: LFCF Build | L21: Actual exit / valuation date | N21: 46069 | O21: F | P21: Realised exit date per filings
B22: EBITDA | F22: =F18 | G22: =G18 | H22: =H18 | I22: =I18 | J22: =J18
B23: (-) D&A | F23: =-$N$15 | G23: =-$N$15 | H23: =-$N$15 | I23: =-$N$15 | J23: =-$N$15
B24: EBIT | F24: =F22+F23 | G24: =G22+G23 | H24: =H22+H23 | I24: =I22+I23 | J24: =J22+J23
B25: (-) Cash Interest | D25: =N10 | F25: =$E$12*-$D$25 | G25: =$E$12*-$D$25 | H25: =$E$12*-$D$25 | I25: =$E$12*-$D$25 | J25: =$E$12*-$D$25
B26: EBT | F26: =F24+F25 | G26: =G24+G25 | H26: =H24+H25 | I26: =I24+I25 | J26: =J24+J25
B27: (-) Taxes | D27: =N11 | F27: =F26*-$D27 | G27: =G26*-$D27 | H27: =H26*-$D27 | I27: =I26*-$D27 | J27: =J26*-$D27
B28: Net Income | F28: =F26+F27 | G28: =G26+G27 | H28: =H26+H27 | I28: =I26+I27 | J28: =J26+J27
B29: (+) D&A | F29: =-F23 | G29: =-G23 | H29: =-H23 | I29: =-I23 | J29: =-J23
B30: (-) Capex | F30: =-$N$16 | G30: =-$N$16 | H30: =-$N$16 | I30: =-$N$16 | J30: =-$N$16
B31: (-) Change in NWC | F31: =$N$17 | G31: =$N$17 | H31: =$N$17 | I31: =$N$17 | J31: =$N$17
B32: Levered FCF | F32: =SUM(F28:F31) | G32: =SUM(G28:G31) | H32: =SUM(H28:H31) | I32: =SUM(I28:I31) | J32: =SUM(J28:J31)
B33: Cumulative LFCF | F33: =SUM($E32:F32) | G33: =SUM($E32:G32) | H33: =SUM($E32:H32) | I33: =SUM($E32:I32) | J33: =SUM($E32:J32)
B35: Returns — UNDERWRITTEN CASE (template mechanics: interest on opening debt, all LFCF accumulates as cash)
B37: Exit EBITDA (2025) | E37: =J18
B38: (x) Exit Multiple | E38: =N18
B39: Enterprise Value | E39: =E37*E38
B40: (-) Debt | E40: =-E12
B41: (+) Cash | E41: =J33
B42: Equity Value at Exit | E42: =SUM(E39:E41)
B43: Initial Equity Investment | E43: =E6
B45: MoM | E45: =E42/E43
B46: IRR | E46: =XIRR(E48:E49,B48:B49)
B48: =N19 | E48: =-E6
B49: =N20 | E49: =E42
B52: ACTUAL OUTCOME
B53: Exit enterprise value, actual ($m) | E53: 1440
B54: Debt at exit ($m) | E54: 500
B55: Equity value at exit ($m) | E55: =E53-E54
B56: Equity invested (from Sources) ($m) | E56: =E6
B57: MoM, actual | E57: =E55/E56
B58: IRR, actual | E58: =IFERROR(XIRR(E62:E63,B62:B63),"n/m")
B59: MoM variance vs underwritten | E59: =E57-E45
B60: IRR variance vs underwritten (pts) | E60: =IFERROR((E58-E46)*100,"n/m")
B62: =N19 | E62: =-E6 | G62: cash flows for XIRR (actual)
B63: =N21 | E63: =E55
B65: Actual outcome note:
B66: COUNTERFACTUAL, not a realised exit: within eleven months of termination Dorel sold Sports alone to Pon for $810m (~11x per the circular's Sports EBITDA), leaving Home + Juvenile with ~$90m of EBITDA that at 7x is ~$630m. $810m + $630m = ~$1,440m of value against a $947m ex-fee take-private EV. Sponsor equity would have been $314m + $83m family rollover.
B71: Deal note:
B72: TD Securities' formal valuation range was C$14.00-C$17.00; the deal died at C$16.00 with ~19% of the minority publicly opposed. The board's post-mortem argument, that the sum of the parts exceeded the offer, is what the Pon sale proved.
B77: Classification: Take-private with family rollover (terminated 15 Feb 2021) | Status: Terminated; counterfactual shown

Sheet F01 KKR-Varsity 2024
B1: KKR / Varsity Brands (2024) — Full LBO model (template: LBO Model Solution)
B2: Assumptions | L2: INPUT NOTES
B3: Entry Multiple | E3: 11.875 | G3: TL | I3: 6.1875 | J3: 0.0225 | L3: EBITDA at entry $400m and entry multiple 11.875x reproduce the filed/reported purchase price of $4,750m.
B4: Exit Multiple | E4: 11 | G4: Mezz | I4: 0 | J4: 0 | L4: Term loan 6.1875x EBITDA at 9.05%; mezz/second-lien 0.0x at 0.00%.
B5: EBITDA at Entry | E5: 400 | G5: Days | I5: 365 | L5: Purchase-accounting inputs (NPV of assets, PP&E allocation, DTL rate), working-capital days and D&A/capex ratios are assumptions unless the paper tab's source column says otherwise.
B6: Financing Fees Years | E6: 7 | G6: Tax Rate | I6: 0.25 | L6: Sensitivity tables (rows 173-186) are Excel data tables and recompute when opened in Excel; other spreadsheet apps may show the last cached values.
B7: D&A Life | E7: 15 | L7: Three template formulas are corrected on this tab so the model survives negative cash flow: CFF now includes the revolver draw (row 89); a negative cash balance no longer triggers a second revolver draw (row 110); the term-loan sweep only uses cash that exists (row 120). With positive cash flow the results are identical to the original.
B8: Rollover | E8: 0 | G8: circ | I8: 1 | J8: << interest is charged on opening balances on this tab, so no iteration is needed; 1 keeps interest on | L8: Interest is charged on opening balances, which removes the template's circular reference; switch I8 is left at 1 so the interest lines stay live.
B10: Sources | G10: Uses
B11: Term Loan | E11: =+I3*$E$5 | G11: Equity purchase price | J11: =+E18
B12: Mezz Loan | E12: =+I4*$E$5 | G12: M&A fee | J12: 70
B13: Management Rollover | E13: =+E18*E8 | G13: Fin. Fee | J13: =+J3*E11+J4*E12
B14: Sponsor Equity | E14: =E15-SUM(E11:E13)
B15: Total Sources | E15: =J15 | G15: Total Uses | J15: =SUM(J11:J14)
B17: Purchase Acct
B18: Purchase Price | E18: =+E3*E5
B19: (-) NPV | E19: -600
B20: Excess | E20: =SUM(E18:E19)
B21: (-) Alloc to PPE | D21: 0.1 | E21: =+-E20*D21
B22: DTL | D22: 0.25 | E22: =+-E21*D22
B23: Goodwill | E23: =SUM(E20:E22)
A25: x | B25: Income Statement | E25: 2024 | F25: =E25+1 | G25: =F25+1 | H25: =G25+1 | I25: =H25+1 | J25: =I25+1
B26: Revenue | E26: =+E31/E32 | F26: =+E26*(1+F27) | G26: =+F26*(1+G27) | H26: =+G26*(1+H27) | I26: =+H26*(1+I27) | J26: =+I26*(1+J27)
B27: % Growth | F27: 0.05 | G27: =+F27 | H27: =+G27 | I27: =+H27 | J27: =+I27
B28: (-) Cogs | E28: =E29-E26 | F28: =F29-F26 | G28: =G29-G26 | H28: =H29-H26 | I28: =I29-I26 | J28: =J29-J26
B29: Gross Profit | E29: =+E26*E30 | F29: =+F26*F30 | G29: =+G26*G30 | H29: =+H26*H30 | I29: =+I26*I30 | J29: =+J26*J30
B30: % Gross Margin | E30: 0.4 | F30: =+E30 | G30: =+F30 | H30: =+G30 | I30: =+H30 | J30: =+I30
B31: EBITDA | E31: =+E5 | F31: =+F26*F32 | G31: =+G26*G32 | H31: =+H26*H32 | I31: =+I26*I32 | J31: =+J26*J32
B32: % Margin | E32: 0.1538 | F32: =+E32 | G32: =+F32 | H32: =+G32 | I32: =+H32 | J32: =+I32
B33: (-) D&A | F33: =+-F26*F46+F42 | G33: =+-G26*G46+G42 | H33: =+-H26*H46+H42 | I33: =+-I26*I46+I42 | J33: =+-J26*J46+J42
B34: EBIT | F34: =+F31+F33 | G34: =+G31+G33 | H34: =+H31+H33 | I34: =+I31+I33 | J34: =+J31+J33
B35: (-) Interest Expense | F35: =+$I$8*F150 | G35: =+$I$8*G150 | H35: =+$I$8*H150 | I35: =+$I$8*I150 | J35: =+$I$8*J150
B36: (+) Interest Income | F36: =+$I$8*F148 | G36: =+$I$8*G148 | H36: =+$I$8*H148 | I36: =+$I$8*I148 | J36: =+$I$8*J148
B37: (-) Amort. Of Fin Fee | F37: =+-$J$13/$E$6 | G37: =+-$J$13/$E$6 | H37: =+-$J$13/$E$6 | I37: =+-$J$13/$E$6 | J37: =+-$J$13/$E$6
B38: EBT | F38: =SUM(F34:F37) | G38: =SUM(G34:G37) | H38: =SUM(H34:H37) | I38: =SUM(I34:I37) | J38: =SUM(J34:J37)
B39: (-) Taxes | F39: =+-F38*$I$6 | G39: =+-G38*$I$6 | H39: =+-H38*$I$6 | I39: =+-I38*$I$6 | J39: =+-J38*$I$6
B40: Net Income | F40: =SUM(F38:F39) | G40: =SUM(G38:G39) | H40: =SUM(H38:H39) | I40: =SUM(I38:I39) | J40: =SUM(J38:J39)
B42: Incremental D&A | F42: =+$E$21/$E$7 | G42: =+$E$21/$E$7 | H42: =+$E$21/$E$7 | I42: =+$E$21/$E$7 | J42: =+$E$21/$E$7
B43: DTL | F43: =+F42*$D$22 | G43: =+G42*$D$22 | H43: =+H42*$D$22 | I43: =+I42*$D$22 | J43: =+J42*$D$22
B44: Capex | F44: =-F47*F33 | G44: =-G47*G33 | H44: =-H47*H33 | I44: =-I47*I33 | J44: =-J47*J33
B46: D&A as % of Sales | F46: 0.03 | G46: =+F46 | H46: =+G46 | I46: =+H46 | J46: =+I46
B47: Capex as % of D&A | F47: 0.8 | G47: =+F47 | H47: =+G47 | I47: =+H47 | J47: =+I47
A49: x | B49: WC Schedule | E49: 2013 | F49: =E49+1 | G49: =F49+1 | H49: =G49+1 | I49: =H49+1 | J49: =I49+1
B50: AR | E50: =+E26*E57/$I$5 | F50: =+F26*F57/$I$5 | G50: =+G26*G57/$I$5 | H50: =+H26*H57/$I$5 | I50: =+I26*I57/$I$5 | J50: =+J26*J57/$I$5
B51: Inventory | E51: =-E28/E58 | F51: =-F28/F58 | G51: =-G28/G58 | H51: =-H28/H58 | I51: =-I28/I58 | J51: =-J28/J58
B52: AP | E52: =-E28*E59/$I$5 | F52: =-F28*F59/$I$5 | G52: =-G28*G59/$I$5 | H52: =-H28*H59/$I$5 | I52: =-I28*I59/$I$5 | J52: =-J28*J59/$I$5
B53: WC | E53: =+E50+E51-E52 | F53: =+F50+F51-F52 | G53: =+G50+G51-G52 | H53: =+H50+H51-H52 | I53: =+I50+I51-I52 | J53: =+J50+J51-J52
B54: Change in WC | F54: =+F53-E53 | G54: =+G53-F53 | H54: =+H53-G53 | I54: =+I53-H53 | J54: =+J53-I53
B56: Metrics
B57: AR | E57: 45 | F57: =+E57 | G57: =+F57 | H57: =+G57 | I57: =+H57 | J57: =+I57
B58: Inventory | E58: 5 | F58: =+E58 | G58: =+F58 | H58: =+G58 | I58: =+H58 | J58: =+I58
B59: AP | E59: 45 | F59: =+E59 | G59: =+F59 | H59: =+G59 | I59: =+H59 | J59: =+I59
A61: x | B61: Cap Table | E61: 2013 | F61: =E61+1 | G61: =F61+1 | H61: =G61+1 | I61: =H61+1 | J61: =I61+1
B62: Cash | E62: 0 | F62: =+E62+F92 | G62: =+F62+G92 | H62: =+G62+H92 | I62: =+H62+I92 | J62: =+I62+J92
B64: Revolver | E64: 0 | F64: =+F111 | G64: =+G111 | H64: =+H111 | I64: =+I111 | J64: =+J111
B65: Term Loan | E65: =+E11 | F65: =+F121 | G65: =+G121 | H65: =+H121 | I65: =+I121 | J65: =+J121
B66: Mezz Loan | E66: =+E12 | F66: =+F132 | G66: =+G132 | H66: =+H132 | I66: =+I132 | J66: =+J132
B67: Total Debt | E67: =SUM(E64:E66) | F67: =SUM(F64:F66) | G67: =SUM(G64:G66) | H67: =SUM(H64:H66) | I67: =SUM(I64:I66) | J67: =SUM(J64:J66)
B68: Equity | E68: =SUM(E13:E14)-J12 | F68: =+E68+F40 | G68: =+F68+G40 | H68: =+G68+H40 | I68: =+H68+I40 | J68: =+I68+J40
B69: Total Cap | E69: =SUM(E67:E68) | F69: =SUM(F67:F68) | G69: =SUM(G67:G68) | H69: =SUM(H67:H68) | I69: =SUM(I67:I68) | J69: =SUM(J67:J68)
B71: Term Loan / EBITDA | E71: =+E65/$E$31 | F71: =+F65/$E$31 | G71: =+G65/$E$31 | H71: =+H65/$E$31 | I71: =+I65/$E$31 | J71: =+J65/$E$31
B72: Mezz Loan / EBITDA | E72: =+E66/$E$31 | F72: =+F66/$E$31 | G72: =+G66/$E$31 | H72: =+H66/$E$31 | I72: =+I66/$E$31 | J72: =+J66/$E$31
B73: Total Debt / EBITDA | E73: =+E67/$E$31 | F73: =+F67/$E$31 | G73: =+G67/$E$31 | H73: =+H67/$E$31 | I73: =+I67/$E$31 | J73: =+J67/$E$31
B74: Total Debt / Cap | E74: =+E67/E69 | F74: =+F67/F69 | G74: =+G67/G69 | H74: =+H67/H69 | I74: =+I67/I69 | J74: =+J67/J69
A76: x | B76: Cash Flow Statement | E76: 2013 | F76: =E76+1 | G76: =F76+1 | H76: =G76+1 | I76: =H76+1 | J76: =I76+1
B77: Net Income | F77: =+F40 | G77: =+G40 | H77: =+H40 | I77: =+I40 | J77: =+J40
B78: (+) D&A | F78: =+-F33 | G78: =+-G33 | H78: =+-H33 | I78: =+-I33 | J78: =+-J33
B79: (-) DTL | F79: =+F43 | G79: =+G43 | H79: =+H43 | I79: =+I43 | J79: =+J43
B80: (+) PIK | F80: =-+F139 | G80: =-+G139 | H80: =-+H139 | I80: =-+I139 | J80: =-+J139
B81: (+) Amort Fee | F81: =+-F37 | G81: =+-G37 | H81: =+-H37 | I81: =+-I37 | J81: =+-J37
B82: (-) Change WC | F82: =+-F54 | G82: =+-G54 | H82: =+-H54 | I82: =+-I54 | J82: =+-J54
B83: CFO | F83: =SUM(F77:F82) | G83: =SUM(G77:G82) | H83: =SUM(H77:H82) | I83: =SUM(I77:I82) | J83: =SUM(J77:J82)
B85: Capex | F85: =+-F44 | G85: =+-G44 | H85: =+-H44 | I85: =+-I44 | J85: =+-J44
B86: CFI | F86: =SUM(F85) | G86: =SUM(G85) | H86: =SUM(H85) | I86: =SUM(I85) | J86: =SUM(J85)
B88: Mand. Paymnet | F88: =+F119 | G88: =+G119 | H88: =+H119 | I88: =+I119 | J88: =+J119
B89: Optional Payment | F89: =+SUM(F100,F102,F104) | G89: =+SUM(G100,G102,G104) | H89: =+SUM(H100,H102,H104) | I89: =+SUM(I100,I102,I104) | J89: =+SUM(J100,J102,J104)
B90: CFF | F90: =SUM(F88:F89) | G90: =SUM(G88:G89) | H90: =SUM(H88:H89) | I90: =SUM(I88:I89) | J90: =SUM(J88:J89)
B92: Change in Cash | F92: =+SUM(F83,F86,F90) | G92: =+SUM(G83,G86,G90) | H92: =+SUM(H83,H86,H90) | I92: =+SUM(I83,I86,I90) | J92: =+SUM(J83,J86,J90)
A94: x | B94: Debt Paydown | E94: 2013 | F94: =E94+1 | G94: =F94+1 | H94: =G94+1 | I94: =H94+1 | J94: =I94+1
B95: Beg Cash | F95: =+E62 | G95: =+F62 | H95: =+G62 | I95: =+H62 | J95: =+I62
B96: (-) Min Cash | F96: -50 | G96: -50 | H96: -50 | I96: -50 | J96: -50
B97: (+) CFO + CFI | F97: =+F83+F86 | G97: =+G83+G86 | H97: =+H83+H86 | I97: =+I83+I86 | J97: =+J83+J86
B98: (-) Mand. Payment | F98: =+F88 | G98: =+G88 | H98: =+H88 | I98: =+I88 | J98: =+J88
B99: Cash Avail for Revolver | F99: =SUM(F95:F98) | G99: =SUM(G95:G98) | H99: =SUM(H95:H98) | I99: =SUM(I95:I98) | J99: =SUM(J95:J98)
B100: (-) Drawdown / Paydown | F100: =+SUM(F109:F110) | G100: =+SUM(G109:G110) | H100: =+SUM(H109:H110) | I100: =+SUM(I109:I110) | J100: =+SUM(J109:J110)
B101: Cash Avail for Term Loan | F101: =SUM(F99:F100) | G101: =SUM(G99:G100) | H101: =SUM(H99:H100) | I101: =SUM(I99:I100) | J101: =SUM(J99:J100)
B102: (-) Paydown | F102: =+F120 | G102: =+G120 | H102: =+H120 | I102: =+I120 | J102: =+J120
B103: Cash Avail for Mezz Loan | F103: =SUM(F101:F102) | G103: =SUM(G101:G102) | H103: =SUM(H101:H102) | I103: =SUM(I101:I102) | J103: =SUM(J101:J102)
B104: (-) Paydown | F104: =+F131 | G104: =+G131 | H104: =+H131 | I104: =+I131 | J104: =+J131
B105: Excess Cash | F105: =SUM(F103:F104) | G105: =SUM(G103:G104) | H105: =SUM(H103:H104) | I105: =SUM(I103:I104) | J105: =SUM(J103:J104)
B107: Revolver
B108: Beg | F108: =+E111 | G108: =+F111 | H108: =+G111 | I108: =+H111 | J108: =+I111
B109: Drawdown | F109: =+-MIN(F99,0) | G109: =+-MIN(G99,0) | H109: =+-MIN(H99,0) | I109: =+-MIN(I99,0) | J109: =+-MIN(J99,0)
B110: Paydown | F110: =+IF(F108>0,-MIN(F108,MAX(F99,0)),0) | G110: =+IF(G108>0,-MIN(G108,MAX(G99,0)),0) | H110: =+IF(H108>0,-MIN(H108,MAX(H99,0)),0) | I110: =+IF(I108>0,-MIN(I108,MAX(I99,0)),0) | J110: =+IF(J108>0,-MIN(J108,MAX(J99,0)),0)
B111: End | E111: 0 | F111: =SUM(F108:F110) | G111: =SUM(G108:G110) | H111: =SUM(H108:H110) | I111: =SUM(I108:I110) | J111: =SUM(J108:J110)
B113: Avg | F113: =+E111 | G113: =+F111 | H113: =+G111 | I113: =+H111 | J113: =+I111
B114: Interest Rate | F114: 0.08 | G114: =+F114 | H114: =+G114 | I114: =+H114 | J114: =+I114
B115: Int Expense | F115: =+-F113*F114 | G115: =+-G113*G114 | H115: =+-H113*H114 | I115: =+-I113*I114 | J115: =+-J113*J114
B117: Term Loan
B118: Beg | F118: =+E121 | G118: =+F121 | H118: =+G121 | I118: =+H121 | J118: =+I121
...

Sheet F02 Bain-Varsity 2018
B1: Bain Capital / Varsity Brands (2018-24) — Full LBO model (template: LBO Model Solution)
B2: Assumptions | L2: INPUT NOTES
B3: Entry Multiple | E3: 10 | G3: TL | I3: 4.724 | J3: 0.0225 | L3: EBITDA at entry $290m and entry multiple 10.0x reproduce the filed/reported purchase price of $2,900m.
B4: Exit Multiple | E4: 11.875 | G4: Mezz | I4: 2.138 | J4: 0.0225 | L4: Term loan 4.724x EBITDA at 5.75%; mezz/second-lien 2.138x at 10.25%.
B5: EBITDA at Entry | E5: 290 | G5: Days | I5: 365 | L5: Purchase-accounting inputs (NPV of assets, PP&E allocation, DTL rate), working-capital days and D&A/capex ratios are assumptions unless the paper tab's source column says otherwise.
B6: Financing Fees Years | E6: 7 | G6: Tax Rate | I6: 0.25 | L6: Sensitivity tables (rows 173-186) are Excel data tables and recompute when opened in Excel; other spreadsheet apps may show the last cached values.
B7: D&A Life | E7: 15 | L7: Three template formulas are corrected on this tab so the model survives negative cash flow: CFF now includes the revolver draw (row 89); a negative cash balance no longer triggers a second revolver draw (row 110); the term-loan sweep only uses cash that exists (row 120). With positive cash flow the results are identical to the original.
B8: Rollover | E8: 0.1 | G8: circ | I8: 1 | J8: << interest is charged on opening balances on this tab, so no iteration is needed; 1 keeps interest on | L8: Interest is charged on opening balances, which removes the template's circular reference; switch I8 is left at 1 so the interest lines stay live.
B10: Sources | G10: Uses
B11: Term Loan | E11: =+I3*$E$5 | G11: Equity purchase price | J11: =+E18
B12: Mezz Loan | E12: =+I4*$E$5 | G12: M&A fee | J12: 45
B13: Management Rollover | E13: =+E18*E8 | G13: Fin. Fee | J13: =+J3*E11+J4*E12
B14: Sponsor Equity | E14: =E15-SUM(E11:E13)
B15: Total Sources | E15: =J15 | G15: Total Uses | J15: =SUM(J11:J14)
B17: Purchase Acct
B18: Purchase Price | E18: =+E3*E5
B19: (-) NPV | E19: -450
B20: Excess | E20: =SUM(E18:E19)
B21: (-) Alloc to PPE | D21: 0.1 | E21: =+-E20*D21
B22: DTL | D22: 0.25 | E22: =+-E21*D22
B23: Goodwill | E23: =SUM(E20:E22)
A25: x | B25: Income Statement | E25: 2018 | F25: =E25+1 | G25: =F25+1 | H25: =G25+1 | I25: =H25+1 | J25: =I25+1
B26: Revenue | E26: =+E31/E32 | F26: =+E26*(1+F27) | G26: =+F26*(1+G27) | H26: =+G26*(1+H27) | I26: =+H26*(1+I27) | J26: =+I26*(1+J27)
B27: % Growth | F27: 0.066 | G27: =+F27 | H27: =+G27 | I27: =+H27 | J27: =+I27
B28: (-) Cogs | E28: =E29-E26 | F28: =F29-F26 | G28: =G29-G26 | H28: =H29-H26 | I28: =I29-I26 | J28: =J29-J26
B29: Gross Profit | E29: =+E26*E30 | F29: =+F26*F30 | G29: =+G26*G30 | H29: =+H26*H30 | I29: =+I26*I30 | J29: =+J26*J30
B30: % Gross Margin | E30: 0.4 | F30: =+E30 | G30: =+F30 | H30: =+G30 | I30: =+H30 | J30: =+I30
B31: EBITDA | E31: =+E5 | F31: =+F26*F32 | G31: =+G26*G32 | H31: =+H26*H32 | I31: =+I26*I32 | J31: =+J26*J32
B32: % Margin | E32: 0.145 | F32: =+E32 | G32: =+F32 | H32: =+G32 | I32: =+H32 | J32: =+I32
B33: (-) D&A | F33: =+-F26*F46+F42 | G33: =+-G26*G46+G42 | H33: =+-H26*H46+H42 | I33: =+-I26*I46+I42 | J33: =+-J26*J46+J42
B34: EBIT | F34: =+F31+F33 | G34: =+G31+G33 | H34: =+H31+H33 | I34: =+I31+I33 | J34: =+J31+J33
B35: (-) Interest Expense | F35: =+$I$8*F150 | G35: =+$I$8*G150 | H35: =+$I$8*H150 | I35: =+$I$8*I150 | J35: =+$I$8*J150
B36: (+) Interest Income | F36: =+$I$8*F148 | G36: =+$I$8*G148 | H36: =+$I$8*H148 | I36: =+$I$8*I148 | J36: =+$I$8*J148
B37: (-) Amort. Of Fin Fee | F37: =+-$J$13/$E$6 | G37: =+-$J$13/$E$6 | H37: =+-$J$13/$E$6 | I37: =+-$J$13/$E$6 | J37: =+-$J$13/$E$6
B38: EBT | F38: =SUM(F34:F37) | G38: =SUM(G34:G37) | H38: =SUM(H34:H37) | I38: =SUM(I34:I37) | J38: =SUM(J34:J37)
B39: (-) Taxes | F39: =+-F38*$I$6 | G39: =+-G38*$I$6 | H39: =+-H38*$I$6 | I39: =+-I38*$I$6 | J39: =+-J38*$I$6
B40: Net Income | F40: =SUM(F38:F39) | G40: =SUM(G38:G39) | H40: =SUM(H38:H39) | I40: =SUM(I38:I39) | J40: =SUM(J38:J39)
B42: Incremental D&A | F42: =+$E$21/$E$7 | G42: =+$E$21/$E$7 | H42: =+$E$21/$E$7 | I42: =+$E$21/$E$7 | J42: =+$E$21/$E$7
B43: DTL | F43: =+F42*$D$22 | G43: =+G42*$D$22 | H43: =+H42*$D$22 | I43: =+I42*$D$22 | J43: =+J42*$D$22
B44: Capex | F44: =-F47*F33 | G44: =-G47*G33 | H44: =-H47*H33 | I44: =-I47*I33 | J44: =-J47*J33
B46: D&A as % of Sales | F46: 0.03 | G46: =+F46 | H46: =+G46 | I46: =+H46 | J46: =+I46
B47: Capex as % of D&A | F47: 0.8 | G47: =+F47 | H47: =+G47 | I47: =+H47 | J47: =+I47
A49: x | B49: WC Schedule | E49: 2013 | F49: =E49+1 | G49: =F49+1 | H49: =G49+1 | I49: =H49+1 | J49: =I49+1
B50: AR | E50: =+E26*E57/$I$5 | F50: =+F26*F57/$I$5 | G50: =+G26*G57/$I$5 | H50: =+H26*H57/$I$5 | I50: =+I26*I57/$I$5 | J50: =+J26*J57/$I$5
B51: Inventory | E51: =-E28/E58 | F51: =-F28/F58 | G51: =-G28/G58 | H51: =-H28/H58 | I51: =-I28/I58 | J51: =-J28/J58
B52: AP | E52: =-E28*E59/$I$5 | F52: =-F28*F59/$I$5 | G52: =-G28*G59/$I$5 | H52: =-H28*H59/$I$5 | I52: =-I28*I59/$I$5 | J52: =-J28*J59/$I$5
B53: WC | E53: =+E50+E51-E52 | F53: =+F50+F51-F52 | G53: =+G50+G51-G52 | H53: =+H50+H51-H52 | I53: =+I50+I51-I52 | J53: =+J50+J51-J52
B54: Change in WC | F54: =+F53-E53 | G54: =+G53-F53 | H54: =+H53-G53 | I54: =+I53-H53 | J54: =+J53-I53
B56: Metrics
B57: AR | E57: 45 | F57: =+E57 | G57: =+F57 | H57: =+G57 | I57: =+H57 | J57: =+I57
B58: Inventory | E58: 5 | F58: =+E58 | G58: =+F58 | H58: =+G58 | I58: =+H58 | J58: =+I58
B59: AP | E59: 45 | F59: =+E59 | G59: =+F59 | H59: =+G59 | I59: =+H59 | J59: =+I59
A61: x | B61: Cap Table | E61: 2013 | F61: =E61+1 | G61: =F61+1 | H61: =G61+1 | I61: =H61+1 | J61: =I61+1
B62: Cash | E62: 0 | F62: =+E62+F92 | G62: =+F62+G92 | H62: =+G62+H92 | I62: =+H62+I92 | J62: =+I62+J92
B64: Revolver | E64: 0 | F64: =+F111 | G64: =+G111 | H64: =+H111 | I64: =+I111 | J64: =+J111
B65: Term Loan | E65: =+E11 | F65: =+F121 | G65: =+G121 | H65: =+H121 | I65: =+I121 | J65: =+J121
B66: Mezz Loan | E66: =+E12 | F66: =+F132 | G66: =+G132 | H66: =+H132 | I66: =+I132 | J66: =+J132
B67: Total Debt | E67: =SUM(E64:E66) | F67: =SUM(F64:F66) | G67: =SUM(G64:G66) | H67: =SUM(H64:H66) | I67: =SUM(I64:I66) | J67: =SUM(J64:J66)
B68: Equity | E68: =SUM(E13:E14)-J12 | F68: =+E68+F40 | G68: =+F68+G40 | H68: =+G68+H40 | I68: =+H68+I40 | J68: =+I68+J40
B69: Total Cap | E69: =SUM(E67:E68) | F69: =SUM(F67:F68) | G69: =SUM(G67:G68) | H69: =SUM(H67:H68) | I69: =SUM(I67:I68) | J69: =SUM(J67:J68)
B71: Term Loan / EBITDA | E71: =+E65/$E$31 | F71: =+F65/$E$31 | G71: =+G65/$E$31 | H71: =+H65/$E$31 | I71: =+I65/$E$31 | J71: =+J65/$E$31
B72: Mezz Loan / EBITDA | E72: =+E66/$E$31 | F72: =+F66/$E$31 | G72: =+G66/$E$31 | H72: =+H66/$E$31 | I72: =+I66/$E$31 | J72: =+J66/$E$31
B73: Total Debt / EBITDA | E73: =+E67/$E$31 | F73: =+F67/$E$31 | G73: =+G67/$E$31 | H73: =+H67/$E$31 | I73: =+I67/$E$31 | J73: =+J67/$E$31
B74: Total Debt / Cap | E74: =+E67/E69 | F74: =+F67/F69 | G74: =+G67/G69 | H74: =+H67/H69 | I74: =+I67/I69 | J74: =+J67/J69
A76: x | B76: Cash Flow Statement | E76: 2013 | F76: =E76+1 | G76: =F76+1 | H76: =G76+1 | I76: =H76+1 | J76: =I76+1
B77: Net Income | F77: =+F40 | G77: =+G40 | H77: =+H40 | I77: =+I40 | J77: =+J40
B78: (+) D&A | F78: =+-F33 | G78: =+-G33 | H78: =+-H33 | I78: =+-I33 | J78: =+-J33
B79: (-) DTL | F79: =+F43 | G79: =+G43 | H79: =+H43 | I79: =+I43 | J79: =+J43
B80: (+) PIK | F80: =-+F139 | G80: =-+G139 | H80: =-+H139 | I80: =-+I139 | J80: =-+J139
B81: (+) Amort Fee | F81: =+-F37 | G81: =+-G37 | H81: =+-H37 | I81: =+-I37 | J81: =+-J37
B82: (-) Change WC | F82: =+-F54 | G82: =+-G54 | H82: =+-H54 | I82: =+-I54 | J82: =+-J54
B83: CFO | F83: =SUM(F77:F82) | G83: =SUM(G77:G82) | H83: =SUM(H77:H82) | I83: =SUM(I77:I82) | J83: =SUM(J77:J82)
B85: Capex | F85: =+-F44 | G85: =+-G44 | H85: =+-H44 | I85: =+-I44 | J85: =+-J44
B86: CFI | F86: =SUM(F85) | G86: =SUM(G85) | H86: =SUM(H85) | I86: =SUM(I85) | J86: =SUM(J85)
B88: Mand. Paymnet | F88: =+F119 | G88: =+G119 | H88: =+H119 | I88: =+I119 | J88: =+J119
B89: Optional Payment | F89: =+SUM(F100,F102,F104) | G89: =+SUM(G100,G102,G104) | H89: =+SUM(H100,H102,H104) | I89: =+SUM(I100,I102,I104) | J89: =+SUM(J100,J102,J104)
B90: CFF | F90: =SUM(F88:F89) | G90: =SUM(G88:G89) | H90: =SUM(H88:H89) | I90: =SUM(I88:I89) | J90: =SUM(J88:J89)
B92: Change in Cash | F92: =+SUM(F83,F86,F90) | G92: =+SUM(G83,G86,G90) | H92: =+SUM(H83,H86,H90) | I92: =+SUM(I83,I86,I90) | J92: =+SUM(J83,J86,J90)
A94: x | B94: Debt Paydown | E94: 2013 | F94: =E94+1 | G94: =F94+1 | H94: =G94+1 | I94: =H94+1 | J94: =I94+1
B95: Beg Cash | F95: =+E62 | G95: =+F62 | H95: =+G62 | I95: =+H62 | J95: =+I62
B96: (-) Min Cash | F96: -40 | G96: -40 | H96: -40 | I96: -40 | J96: -40
B97: (+) CFO + CFI | F97: =+F83+F86 | G97: =+G83+G86 | H97: =+H83+H86 | I97: =+I83+I86 | J97: =+J83+J86
B98: (-) Mand. Payment | F98: =+F88 | G98: =+G88 | H98: =+H88 | I98: =+I88 | J98: =+J88
B99: Cash Avail for Revolver | F99: =SUM(F95:F98) | G99: =SUM(G95:G98) | H99: =SUM(H95:H98) | I99: =SUM(I95:I98) | J99: =SUM(J95:J98)
B100: (-) Drawdown / Paydown | F100: =+SUM(F109:F110) | G100: =+SUM(G109:G110) | H100: =+SUM(H109:H110) | I100: =+SUM(I109:I110) | J100: =+SUM(J109:J110)
B101: Cash Avail for Term Loan | F101: =SUM(F99:F100) | G101: =SUM(G99:G100) | H101: =SUM(H99:H100) | I101: =SUM(I99:I100) | J101: =SUM(J99:J100)
B102: (-) Paydown | F102: =+F120 | G102: =+G120 | H102: =+H120 | I102: =+I120 | J102: =+J120
B103: Cash Avail for Mezz Loan | F103: =SUM(F101:F102) | G103: =SUM(G101:G102) | H103: =SUM(H101:H102) | I103: =SUM(I101:I102) | J103: =SUM(J101:J102)
B104: (-) Paydown | F104: =+F131 | G104: =+G131 | H104: =+H131 | I104: =+I131 | J104: =+J131
B105: Excess Cash | F105: =SUM(F103:F104) | G105: =SUM(G103:G104) | H105: =SUM(H103:H104) | I105: =SUM(I103:I104) | J105: =SUM(J103:J104)
B107: Revolver
B108: Beg | F108: =+E111 | G108: =+F111 | H108: =+G111 | I108: =+H111 | J108: =+I111
B109: Drawdown | F109: =+-MIN(F99,0) | G109: =+-MIN(G99,0) | H109: =+-MIN(H99,0) | I109: =+-MIN(I99,0) | J109: =+-MIN(J99,0)
B110: Paydown | F110: =+IF(F108>0,-MIN(F108,MAX(F99,0)),0) | G110: =+IF(G108>0,-MIN(G108,MAX(G99,0)),0) | H110: =+IF(H108>0,-MIN(H108,MAX(H99,0)),0) | I110: =+IF(I108>0,-MIN(I108,MAX(I99,0)),0) | J110: =+IF(J108>0,-MIN(J108,MAX(J99,0)),0)
B111: End | E111: 0 | F111: =SUM(F108:F110) | G111: =SUM(G108:G110) | H111: =SUM(H108:H110) | I111: =SUM(I108:I110) | J111: =SUM(J108:J110)
B113: Avg | F113: =+E111 | G113: =+F111 | H113: =+G111 | I113: =+H111 | J113: =+I111
B114: Interest Rate | F114: 0.07 | G114: =+F114 | H114: =+G114 | I114: =+H114 | J114: =+I114
B115: Int Expense | F115: =+-F113*F114 | G115: =+-G113*G114 | H115: =+-H113*H114 | I115: =+-I113*I114 | J115: =+-J113*J114
B117: Term Loan
B118: Beg | F118: =+E121 | G118: =+F121 | H118: =+G121 | I118: =+H121 | J118: =+I121
...

Sheet F03 Cerberus-Chrysler 2007
B1: Cerberus / Chrysler (2007-09) — Full LBO model (template: LBO Model Solution)
B2: Assumptions | L2: INPUT NOTES
B3: Entry Multiple | E3: 12.5 | G3: TL | I3: 6.667 | J3: 0.02 | L3: EBITDA at entry $1,500m and entry multiple 12.5x reproduce the filed/reported purchase price of $18,750m.
B4: Exit Multiple | E4: 6 | G4: Mezz | I4: 1.333 | J4: 0.02 | L4: Term loan 6.667x EBITDA at 8.50%; mezz/second-lien 1.333x at 12.00%.
B5: EBITDA at Entry | E5: 1500 | G5: Days | I5: 365 | L5: Purchase-accounting inputs (NPV of assets, PP&E allocation, DTL rate), working-capital days and D&A/capex ratios are assumptions unless the paper tab's source column says otherwise.
B6: Financing Fees Years | E6: 7 | G6: Tax Rate | I6: 0.35 | L6: Sensitivity tables (rows 173-186) are Excel data tables and recompute when opened in Excel; other spreadsheet apps may show the last cached values.
B7: D&A Life | E7: 10 | L7: Three template formulas are corrected on this tab so the model survives negative cash flow: CFF now includes the revolver draw (row 89); a negative cash balance no longer triggers a second revolver draw (row 110); the term-loan sweep only uses cash that exists (row 120). With positive cash flow the results are identical to the original.
B8: Rollover | E8: 0.0715 | G8: circ | I8: 1 | J8: << interest is charged on opening balances on this tab, so no iteration is needed; 1 keeps interest on | L8: Interest is charged on opening balances, which removes the template's circular reference; switch I8 is left at 1 so the interest lines stay live.
B10: Sources | G10: Uses
B11: Term Loan | E11: =+I3*$E$5 | G11: Equity purchase price | J11: =+E18
B12: Mezz Loan | E12: =+I4*$E$5 | G12: M&A fee | J12: 150
B13: Management Rollover | E13: =+E18*E8 | G13: Fin. Fee | J13: =+J3*E11+J4*E12
B14: Sponsor Equity | E14: =E15-SUM(E11:E13)
B15: Total Sources | E15: =J15 | G15: Total Uses | J15: =SUM(J11:J14)
B17: Purchase Acct
B18: Purchase Price | E18: =+E3*E5
B19: (-) NPV | E19: -12000
B20: Excess | E20: =SUM(E18:E19)
B21: (-) Alloc to PPE | D21: 0.3 | E21: =+-E20*D21
B22: DTL | D22: 0.35 | E22: =+-E21*D22
B23: Goodwill | E23: =SUM(E20:E22)
A25: x | B25: Income Statement | E25: 2006 | F25: =E25+1 | G25: =F25+1 | H25: =G25+1 | I25: =H25+1 | J25: =I25+1
B26: Revenue | E26: =+E31/E32 | F26: =+E26*(1+F27) | G26: =+F26*(1+G27) | H26: =+G26*(1+H27) | I26: =+H26*(1+I27) | J26: =+I26*(1+J27)
B27: % Growth | F27: 0 | G27: =+F27 | H27: =+G27 | I27: =+H27 | J27: =+I27
B28: (-) Cogs | E28: =E29-E26 | F28: =F29-F26 | G28: =G29-G26 | H28: =H29-H26 | I28: =I29-I26 | J28: =J29-J26
B29: Gross Profit | E29: =+E26*E30 | F29: =+F26*F30 | G29: =+G26*G30 | H29: =+H26*H30 | I29: =+I26*I30 | J29: =+J26*J30
B30: % Gross Margin | E30: 0.15 | F30: =+E30 | G30: =+F30 | H30: =+G30 | I30: =+H30 | J30: =+I30
B31: EBITDA | E31: =+E5 | F31: =+F26*F32 | G31: =+G26*G32 | H31: =+H26*H32 | I31: =+I26*I32 | J31: =+J26*J32
B32: % Margin | E32: 0.025 | F32: 0.035 | G32: 0.045 | H32: 0.055 | I32: 0.06 | J32: 0.06
B33: (-) D&A | F33: =+-F26*F46+F42 | G33: =+-G26*G46+G42 | H33: =+-H26*H46+H42 | I33: =+-I26*I46+I42 | J33: =+-J26*J46+J42
B34: EBIT | F34: =+F31+F33 | G34: =+G31+G33 | H34: =+H31+H33 | I34: =+I31+I33 | J34: =+J31+J33
B35: (-) Interest Expense | F35: =+$I$8*F150 | G35: =+$I$8*G150 | H35: =+$I$8*H150 | I35: =+$I$8*I150 | J35: =+$I$8*J150
B36: (+) Interest Income | F36: =+$I$8*F148 | G36: =+$I$8*G148 | H36: =+$I$8*H148 | I36: =+$I$8*I148 | J36: =+$I$8*J148
B37: (-) Amort. Of Fin Fee | F37: =+-$J$13/$E$6 | G37: =+-$J$13/$E$6 | H37: =+-$J$13/$E$6 | I37: =+-$J$13/$E$6 | J37: =+-$J$13/$E$6
B38: EBT | F38: =SUM(F34:F37) | G38: =SUM(G34:G37) | H38: =SUM(H34:H37) | I38: =SUM(I34:I37) | J38: =SUM(J34:J37)
B39: (-) Taxes | F39: =+-F38*$I$6 | G39: =+-G38*$I$6 | H39: =+-H38*$I$6 | I39: =+-I38*$I$6 | J39: =+-J38*$I$6
B40: Net Income | F40: =SUM(F38:F39) | G40: =SUM(G38:G39) | H40: =SUM(H38:H39) | I40: =SUM(I38:I39) | J40: =SUM(J38:J39)
B42: Incremental D&A | F42: =+$E$21/$E$7 | G42: =+$E$21/$E$7 | H42: =+$E$21/$E$7 | I42: =+$E$21/$E$7 | J42: =+$E$21/$E$7
B43: DTL | F43: =+F42*$D$22 | G43: =+G42*$D$22 | H43: =+H42*$D$22 | I43: =+I42*$D$22 | J43: =+J42*$D$22
B44: Capex | F44: =-F47*F33 | G44: =-G47*G33 | H44: =-H47*H33 | I44: =-I47*I33 | J44: =-J47*J33
B46: D&A as % of Sales | F46: 0.047 | G46: =+F46 | H46: =+G46 | I46: =+H46 | J46: =+I46
B47: Capex as % of D&A | F47: 0.72 | G47: =+F47 | H47: =+G47 | I47: =+H47 | J47: =+I47
A49: x | B49: WC Schedule | E49: 2013 | F49: =E49+1 | G49: =F49+1 | H49: =G49+1 | I49: =H49+1 | J49: =I49+1
B50: AR | E50: =+E26*E57/$I$5 | F50: =+F26*F57/$I$5 | G50: =+G26*G57/$I$5 | H50: =+H26*H57/$I$5 | I50: =+I26*I57/$I$5 | J50: =+J26*J57/$I$5
B51: Inventory | E51: =-E28/E58 | F51: =-F28/F58 | G51: =-G28/G58 | H51: =-H28/H58 | I51: =-I28/I58 | J51: =-J28/J58
B52: AP | E52: =-E28*E59/$I$5 | F52: =-F28*F59/$I$5 | G52: =-G28*G59/$I$5 | H52: =-H28*H59/$I$5 | I52: =-I28*I59/$I$5 | J52: =-J28*J59/$I$5
B53: WC | E53: =+E50+E51-E52 | F53: =+F50+F51-F52 | G53: =+G50+G51-G52 | H53: =+H50+H51-H52 | I53: =+I50+I51-I52 | J53: =+J50+J51-J52
B54: Change in WC | F54: =+F53-E53 | G54: =+G53-F53 | H54: =+H53-G53 | I54: =+I53-H53 | J54: =+J53-I53
B56: Metrics
B57: AR | E57: 20 | F57: =+E57 | G57: =+F57 | H57: =+G57 | I57: =+H57 | J57: =+I57
B58: Inventory | E58: 8 | F58: =+E58 | G58: =+F58 | H58: =+G58 | I58: =+H58 | J58: =+I58
B59: AP | E59: 60 | F59: =+E59 | G59: =+F59 | H59: =+G59 | I59: =+H59 | J59: =+I59
A61: x | B61: Cap Table | E61: 2013 | F61: =E61+1 | G61: =F61+1 | H61: =G61+1 | I61: =H61+1 | J61: =I61+1
B62: Cash | E62: 0 | F62: =+E62+F92 | G62: =+F62+G92 | H62: =+G62+H92 | I62: =+H62+I92 | J62: =+I62+J92
B64: Revolver | E64: 0 | F64: =+F111 | G64: =+G111 | H64: =+H111 | I64: =+I111 | J64: =+J111
B65: Term Loan | E65: =+E11 | F65: =+F121 | G65: =+G121 | H65: =+H121 | I65: =+I121 | J65: =+J121
B66: Mezz Loan | E66: =+E12 | F66: =+F132 | G66: =+G132 | H66: =+H132 | I66: =+I132 | J66: =+J132
B67: Total Debt | E67: =SUM(E64:E66) | F67: =SUM(F64:F66) | G67: =SUM(G64:G66) | H67: =SUM(H64:H66) | I67: =SUM(I64:I66) | J67: =SUM(J64:J66)
B68: Equity | E68: =SUM(E13:E14)-J12 | F68: =+E68+F40 | G68: =+F68+G40 | H68: =+G68+H40 | I68: =+H68+I40 | J68: =+I68+J40
B69: Total Cap | E69: =SUM(E67:E68) | F69: =SUM(F67:F68) | G69: =SUM(G67:G68) | H69: =SUM(H67:H68) | I69: =SUM(I67:I68) | J69: =SUM(J67:J68)
B71: Term Loan / EBITDA | E71: =+E65/$E$31 | F71: =+F65/$E$31 | G71: =+G65/$E$31 | H71: =+H65/$E$31 | I71: =+I65/$E$31 | J71: =+J65/$E$31
B72: Mezz Loan / EBITDA | E72: =+E66/$E$31 | F72: =+F66/$E$31 | G72: =+G66/$E$31 | H72: =+H66/$E$31 | I72: =+I66/$E$31 | J72: =+J66/$E$31
B73: Total Debt / EBITDA | E73: =+E67/$E$31 | F73: =+F67/$E$31 | G73: =+G67/$E$31 | H73: =+H67/$E$31 | I73: =+I67/$E$31 | J73: =+J67/$E$31
B74: Total Debt / Cap | E74: =+E67/E69 | F74: =+F67/F69 | G74: =+G67/G69 | H74: =+H67/H69 | I74: =+I67/I69 | J74: =+J67/J69
A76: x | B76: Cash Flow Statement | E76: 2013 | F76: =E76+1 | G76: =F76+1 | H76: =G76+1 | I76: =H76+1 | J76: =I76+1
B77: Net Income | F77: =+F40 | G77: =+G40 | H77: =+H40 | I77: =+I40 | J77: =+J40
B78: (+) D&A | F78: =+-F33 | G78: =+-G33 | H78: =+-H33 | I78: =+-I33 | J78: =+-J33
B79: (-) DTL | F79: =+F43 | G79: =+G43 | H79: =+H43 | I79: =+I43 | J79: =+J43
B80: (+) PIK | F80: =-+F139 | G80: =-+G139 | H80: =-+H139 | I80: =-+I139 | J80: =-+J139
B81: (+) Amort Fee | F81: =+-F37 | G81: =+-G37 | H81: =+-H37 | I81: =+-I37 | J81: =+-J37
B82: (-) Change WC | F82: =+-F54 | G82: =+-G54 | H82: =+-H54 | I82: =+-I54 | J82: =+-J54
B83: CFO | F83: =SUM(F77:F82) | G83: =SUM(G77:G82) | H83: =SUM(H77:H82) | I83: =SUM(I77:I82) | J83: =SUM(J77:J82)
B85: Capex | F85: =+-F44 | G85: =+-G44 | H85: =+-H44 | I85: =+-I44 | J85: =+-J44
B86: CFI | F86: =SUM(F85) | G86: =SUM(G85) | H86: =SUM(H85) | I86: =SUM(I85) | J86: =SUM(J85)
B88: Mand. Paymnet | F88: =+F119 | G88: =+G119 | H88: =+H119 | I88: =+I119 | J88: =+J119
B89: Optional Payment | F89: =+SUM(F100,F102,F104) | G89: =+SUM(G100,G102,G104) | H89: =+SUM(H100,H102,H104) | I89: =+SUM(I100,I102,I104) | J89: =+SUM(J100,J102,J104)
B90: CFF | F90: =SUM(F88:F89) | G90: =SUM(G88:G89) | H90: =SUM(H88:H89) | I90: =SUM(I88:I89) | J90: =SUM(J88:J89)
B92: Change in Cash | F92: =+SUM(F83,F86,F90) | G92: =+SUM(G83,G86,G90) | H92: =+SUM(H83,H86,H90) | I92: =+SUM(I83,I86,I90) | J92: =+SUM(J83,J86,J90)
A94: x | B94: Debt Paydown | E94: 2013 | F94: =E94+1 | G94: =F94+1 | H94: =G94+1 | I94: =H94+1 | J94: =I94+1
B95: Beg Cash | F95: =+E62 | G95: =+F62 | H95: =+G62 | I95: =+H62 | J95: =+I62
B96: (-) Min Cash | F96: -2000 | G96: -2000 | H96: -2000 | I96: -2000 | J96: -2000
B97: (+) CFO + CFI | F97: =+F83+F86 | G97: =+G83+G86 | H97: =+H83+H86 | I97: =+I83+I86 | J97: =+J83+J86
B98: (-) Mand. Payment | F98: =+F88 | G98: =+G88 | H98: =+H88 | I98: =+I88 | J98: =+J88
B99: Cash Avail for Revolver | F99: =SUM(F95:F98) | G99: =SUM(G95:G98) | H99: =SUM(H95:H98) | I99: =SUM(I95:I98) | J99: =SUM(J95:J98)
B100: (-) Drawdown / Paydown | F100: =+SUM(F109:F110) | G100: =+SUM(G109:G110) | H100: =+SUM(H109:H110) | I100: =+SUM(I109:I110) | J100: =+SUM(J109:J110)
B101: Cash Avail for Term Loan | F101: =SUM(F99:F100) | G101: =SUM(G99:G100) | H101: =SUM(H99:H100) | I101: =SUM(I99:I100) | J101: =SUM(J99:J100)
B102: (-) Paydown | F102: =+F120 | G102: =+G120 | H102: =+H120 | I102: =+I120 | J102: =+J120
B103: Cash Avail for Mezz Loan | F103: =SUM(F101:F102) | G103: =SUM(G101:G102) | H103: =SUM(H101:H102) | I103: =SUM(I101:I102) | J103: =SUM(J101:J102)
B104: (-) Paydown | F104: =+F131 | G104: =+G131 | H104: =+H131 | I104: =+I131 | J104: =+J131
B105: Excess Cash | F105: =SUM(F103:F104) | G105: =SUM(G103:G104) | H105: =SUM(H103:H104) | I105: =SUM(I103:I104) | J105: =SUM(J103:J104)
B107: Revolver
B108: Beg | F108: =+E111 | G108: =+F111 | H108: =+G111 | I108: =+H111 | J108: =+I111
B109: Drawdown | F109: =+-MIN(F99,0) | G109: =+-MIN(G99,0) | H109: =+-MIN(H99,0) | I109: =+-MIN(I99,0) | J109: =+-MIN(J99,0)
B110: Paydown | F110: =+IF(F108>0,-MIN(F108,MAX(F99,0)),0) | G110: =+IF(G108>0,-MIN(G108,MAX(G99,0)),0) | H110: =+IF(H108>0,-MIN(H108,MAX(H99,0)),0) | I110: =+IF(I108>0,-MIN(I108,MAX(I99,0)),0) | J110: =+IF(J108>0,-MIN(J108,MAX(J99,0)),0)
B111: End | E111: 0 | F111: =SUM(F108:F110) | G111: =SUM(G108:G110) | H111: =SUM(H108:H110) | I111: =SUM(I108:I110) | J111: =SUM(J108:J110)
B113: Avg | F113: =+E111 | G113: =+F111 | H113: =+G111 | I113: =+H111 | J113: =+I111
B114: Interest Rate | F114: 0.07 | G114: =+F114 | H114: =+G114 | I114: =+H114 | J114: =+I114
B115: Int Expense | F115: =+-F113*F114 | G115: =+-G113*G114 | H115: =+-H113*H114 | I115: =+-I113*I114 | J115: =+-J113*J114
B117: Term Loan
B118: Beg | F118: =+E121 | G118: =+F121 | H118: =+G121 | I118: =+H121 | J118: =+I121
...

Sheet F04 CAT-Bucyrus 2011 STRAT
B1: Caterpillar / Bucyrus (2011) [STRATEGIC] — Full LBO model (template: LBO Model Solution) | G1: STRATEGIC, NOT AN LBO — see the paper tab banner
B2: Assumptions | L2: INPUT NOTES
B3: Entry Multiple | E3: 13.81 | G3: TL | I3: 7.061 | J3: 0.005 | L3: EBITDA at entry $637.3m and entry multiple 13.81x reproduce the filed/reported purchase price of $8,801m.
B4: Exit Multiple | E4: 10 | G4: Mezz | I4: 0 | J4: 0 | L4: Term loan 7.061x EBITDA at 2.87%; mezz/second-lien 0.0x at 0.00%.
B5: EBITDA at Entry | E5: 637.3 | G5: Days | I5: 365 | L5: Purchase-accounting inputs (NPV of assets, PP&E allocation, DTL rate), working-capital days and D&A/capex ratios are assumptions unless the paper tab's source column says otherwise.
B6: Financing Fees Years | E6: 10 | G6: Tax Rate | I6: 0.3 | L6: Sensitivity tables (rows 173-186) are Excel data tables and recompute when opened in Excel; other spreadsheet apps may show the last cached values.
B7: D&A Life | E7: 15 | L7: Three template formulas are corrected on this tab so the model survives negative cash flow: CFF now includes the revolver draw (row 89); a negative cash balance no longer triggers a second revolver draw (row 110); the term-loan sweep only uses cash that exists (row 120). With positive cash flow the results are identical to the original.
B8: Rollover | E8: 0 | G8: circ | I8: 1 | J8: << interest is charged on opening balances on this tab, so no iteration is needed; 1 keeps interest on | L8: Interest is charged on opening balances, which removes the template's circular reference; switch I8 is left at 1 so the interest lines stay live.
B10: Sources | G10: Uses
B11: Term Loan | E11: =+I3*$E$5 | G11: Equity purchase price | J11: =+E18
B12: Mezz Loan | E12: =+I4*$E$5 | G12: M&A fee | J12: 60
B13: Management Rollover | E13: =+E18*E8 | G13: Fin. Fee | J13: =+J3*E11+J4*E12
B14: Sponsor Equity | E14: =E15-SUM(E11:E13)
B15: Total Sources | E15: =J15 | G15: Total Uses | J15: =SUM(J11:J14)
B17: Purchase Acct
B18: Purchase Price | E18: =+E3*E5
B19: (-) NPV | E19: -1500
B20: Excess | E20: =SUM(E18:E19)
B21: (-) Alloc to PPE | D21: 0.1 | E21: =+-E20*D21
B22: DTL | D22: 0.3 | E22: =+-E21*D22
B23: Goodwill | E23: =SUM(E20:E22)
A25: x | B25: Income Statement | E25: 2010 | F25: =E25+1 | G25: =F25+1 | H25: =G25+1 | I25: =H25+1 | J25: =I25+1
B26: Revenue | E26: =+E31/E32 | F26: =+E26*(1+F27) | G26: =+F26*(1+G27) | H26: =+G26*(1+H27) | I26: =+H26*(1+I27) | J26: =+I26*(1+J27)
B27: % Growth | F27: 0.1 | G27: =+F27 | H27: =+G27 | I27: =+H27 | J27: =+I27
B28: (-) Cogs | E28: =E29-E26 | F28: =F29-F26 | G28: =G29-G26 | H28: =H29-H26 | I28: =I29-I26 | J28: =J29-J26
B29: Gross Profit | E29: =+E26*E30 | F29: =+F26*F30 | G29: =+G26*G30 | H29: =+H26*H30 | I29: =+I26*I30 | J29: =+J26*J30
B30: % Gross Margin | E30: 0.3 | F30: =+E30 | G30: =+F30 | H30: =+G30 | I30: =+H30 | J30: =+I30
B31: EBITDA | E31: =+E5 | F31: =+F26*F32 | G31: =+G26*G32 | H31: =+H26*H32 | I31: =+I26*I32 | J31: =+J26*J32
B32: % Margin | E32: 0.1746 | F32: 0.19 | G32: 0.21 | H32: 0.23 | I32: 0.25 | J32: 0.26
B33: (-) D&A | F33: =+-F26*F46+F42 | G33: =+-G26*G46+G42 | H33: =+-H26*H46+H42 | I33: =+-I26*I46+I42 | J33: =+-J26*J46+J42
B34: EBIT | F34: =+F31+F33 | G34: =+G31+G33 | H34: =+H31+H33 | I34: =+I31+I33 | J34: =+J31+J33
B35: (-) Interest Expense | F35: =+$I$8*F150 | G35: =+$I$8*G150 | H35: =+$I$8*H150 | I35: =+$I$8*I150 | J35: =+$I$8*J150
B36: (+) Interest Income | F36: =+$I$8*F148 | G36: =+$I$8*G148 | H36: =+$I$8*H148 | I36: =+$I$8*I148 | J36: =+$I$8*J148
B37: (-) Amort. Of Fin Fee | F37: =+-$J$13/$E$6 | G37: =+-$J$13/$E$6 | H37: =+-$J$13/$E$6 | I37: =+-$J$13/$E$6 | J37: =+-$J$13/$E$6
B38: EBT | F38: =SUM(F34:F37) | G38: =SUM(G34:G37) | H38: =SUM(H34:H37) | I38: =SUM(I34:I37) | J38: =SUM(J34:J37)
B39: (-) Taxes | F39: =+-F38*$I$6 | G39: =+-G38*$I$6 | H39: =+-H38*$I$6 | I39: =+-I38*$I$6 | J39: =+-J38*$I$6
B40: Net Income | F40: =SUM(F38:F39) | G40: =SUM(G38:G39) | H40: =SUM(H38:H39) | I40: =SUM(I38:I39) | J40: =SUM(J38:J39)
B42: Incremental D&A | F42: =+$E$21/$E$7 | G42: =+$E$21/$E$7 | H42: =+$E$21/$E$7 | I42: =+$E$21/$E$7 | J42: =+$E$21/$E$7
B43: DTL | F43: =+F42*$D$22 | G43: =+G42*$D$22 | H43: =+H42*$D$22 | I43: =+I42*$D$22 | J43: =+J42*$D$22
B44: Capex | F44: =-F47*F33 | G44: =-G47*G33 | H44: =-H47*H33 | I44: =-I47*I33 | J44: =-J47*J33
B46: D&A as % of Sales | F46: 0.0276 | G46: =+F46 | H46: =+G46 | I46: =+H46 | J46: =+I46
B47: Capex as % of D&A | F47: 1 | G47: =+F47 | H47: =+G47 | I47: =+H47 | J47: =+I47
A49: x | B49: WC Schedule | E49: 2013 | F49: =E49+1 | G49: =F49+1 | H49: =G49+1 | I49: =H49+1 | J49: =I49+1
B50: AR | E50: =+E26*E57/$I$5 | F50: =+F26*F57/$I$5 | G50: =+G26*G57/$I$5 | H50: =+H26*H57/$I$5 | I50: =+I26*I57/$I$5 | J50: =+J26*J57/$I$5
B51: Inventory | E51: =-E28/E58 | F51: =-F28/F58 | G51: =-G28/G58 | H51: =-H28/H58 | I51: =-I28/I58 | J51: =-J28/J58
B52: AP | E52: =-E28*E59/$I$5 | F52: =-F28*F59/$I$5 | G52: =-G28*G59/$I$5 | H52: =-H28*H59/$I$5 | I52: =-I28*I59/$I$5 | J52: =-J28*J59/$I$5
B53: WC | E53: =+E50+E51-E52 | F53: =+F50+F51-F52 | G53: =+G50+G51-G52 | H53: =+H50+H51-H52 | I53: =+I50+I51-I52 | J53: =+J50+J51-J52
B54: Change in WC | F54: =+F53-E53 | G54: =+G53-F53 | H54: =+H53-G53 | I54: =+I53-H53 | J54: =+J53-I53
B56: Metrics
B57: AR | E57: 60 | F57: =+E57 | G57: =+F57 | H57: =+G57 | I57: =+H57 | J57: =+I57
B58: Inventory | E58: 2.5 | F58: =+E58 | G58: =+F58 | H58: =+G58 | I58: =+H58 | J58: =+I58
B59: AP | E59: 50 | F59: =+E59 | G59: =+F59 | H59: =+G59 | I59: =+H59 | J59: =+I59
A61: x | B61: Cap Table | E61: 2013 | F61: =E61+1 | G61: =F61+1 | H61: =G61+1 | I61: =H61+1 | J61: =I61+1
B62: Cash | E62: 0 | F62: =+E62+F92 | G62: =+F62+G92 | H62: =+G62+H92 | I62: =+H62+I92 | J62: =+I62+J92
B64: Revolver | E64: 0 | F64: =+F111 | G64: =+G111 | H64: =+H111 | I64: =+I111 | J64: =+J111
B65: Term Loan | E65: =+E11 | F65: =+F121 | G65: =+G121 | H65: =+H121 | I65: =+I121 | J65: =+J121
B66: Mezz Loan | E66: =+E12 | F66: =+F132 | G66: =+G132 | H66: =+H132 | I66: =+I132 | J66: =+J132
B67: Total Debt | E67: =SUM(E64:E66) | F67: =SUM(F64:F66) | G67: =SUM(G64:G66) | H67: =SUM(H64:H66) | I67: =SUM(I64:I66) | J67: =SUM(J64:J66)
B68: Equity | E68: =SUM(E13:E14)-J12 | F68: =+E68+F40 | G68: =+F68+G40 | H68: =+G68+H40 | I68: =+H68+I40 | J68: =+I68+J40
B69: Total Cap | E69: =SUM(E67:E68) | F69: =SUM(F67:F68) | G69: =SUM(G67:G68) | H69: =SUM(H67:H68) | I69: =SUM(I67:I68) | J69: =SUM(J67:J68)
B71: Term Loan / EBITDA | E71: =+E65/$E$31 | F71: =+F65/$E$31 | G71: =+G65/$E$31 | H71: =+H65/$E$31 | I71: =+I65/$E$31 | J71: =+J65/$E$31
B72: Mezz Loan / EBITDA | E72: =+E66/$E$31 | F72: =+F66/$E$31 | G72: =+G66/$E$31 | H72: =+H66/$E$31 | I72: =+I66/$E$31 | J72: =+J66/$E$31
B73: Total Debt / EBITDA | E73: =+E67/$E$31 | F73: =+F67/$E$31 | G73: =+G67/$E$31 | H73: =+H67/$E$31 | I73: =+I67/$E$31 | J73: =+J67/$E$31
B74: Total Debt / Cap | E74: =+E67/E69 | F74: =+F67/F69 | G74: =+G67/G69 | H74: =+H67/H69 | I74: =+I67/I69 | J74: =+J67/J69
A76: x | B76: Cash Flow Statement | E76: 2013 | F76: =E76+1 | G76: =F76+1 | H76: =G76+1 | I76: =H76+1 | J76: =I76+1
B77: Net Income | F77: =+F40 | G77: =+G40 | H77: =+H40 | I77: =+I40 | J77: =+J40
B78: (+) D&A | F78: =+-F33 | G78: =+-G33 | H78: =+-H33 | I78: =+-I33 | J78: =+-J33
B79: (-) DTL | F79: =+F43 | G79: =+G43 | H79: =+H43 | I79: =+I43 | J79: =+J43
B80: (+) PIK | F80: =-+F139 | G80: =-+G139 | H80: =-+H139 | I80: =-+I139 | J80: =-+J139
B81: (+) Amort Fee | F81: =+-F37 | G81: =+-G37 | H81: =+-H37 | I81: =+-I37 | J81: =+-J37
B82: (-) Change WC | F82: =+-F54 | G82: =+-G54 | H82: =+-H54 | I82: =+-I54 | J82: =+-J54
B83: CFO | F83: =SUM(F77:F82) | G83: =SUM(G77:G82) | H83: =SUM(H77:H82) | I83: =SUM(I77:I82) | J83: =SUM(J77:J82)
B85: Capex | F85: =+-F44 | G85: =+-G44 | H85: =+-H44 | I85: =+-I44 | J85: =+-J44
B86: CFI | F86: =SUM(F85) | G86: =SUM(G85) | H86: =SUM(H85) | I86: =SUM(I85) | J86: =SUM(J85)
B88: Mand. Paymnet | F88: =+F119 | G88: =+G119 | H88: =+H119 | I88: =+I119 | J88: =+J119
B89: Optional Payment | F89: =+SUM(F100,F102,F104) | G89: =+SUM(G100,G102,G104) | H89: =+SUM(H100,H102,H104) | I89: =+SUM(I100,I102,I104) | J89: =+SUM(J100,J102,J104)
B90: CFF | F90: =SUM(F88:F89) | G90: =SUM(G88:G89) | H90: =SUM(H88:H89) | I90: =SUM(I88:I89) | J90: =SUM(J88:J89)
B92: Change in Cash | F92: =+SUM(F83,F86,F90) | G92: =+SUM(G83,G86,G90) | H92: =+SUM(H83,H86,H90) | I92: =+SUM(I83,I86,I90) | J92: =+SUM(J83,J86,J90)
A94: x | B94: Debt Paydown | E94: 2013 | F94: =E94+1 | G94: =F94+1 | H94: =G94+1 | I94: =H94+1 | J94: =I94+1
B95: Beg Cash | F95: =+E62 | G95: =+F62 | H95: =+G62 | I95: =+H62 | J95: =+I62
B96: (-) Min Cash | F96: -200 | G96: -200 | H96: -200 | I96: -200 | J96: -200
B97: (+) CFO + CFI | F97: =+F83+F86 | G97: =+G83+G86 | H97: =+H83+H86 | I97: =+I83+I86 | J97: =+J83+J86
B98: (-) Mand. Payment | F98: =+F88 | G98: =+G88 | H98: =+H88 | I98: =+I88 | J98: =+J88
B99: Cash Avail for Revolver | F99: =SUM(F95:F98) | G99: =SUM(G95:G98) | H99: =SUM(H95:H98) | I99: =SUM(I95:I98) | J99: =SUM(J95:J98)
B100: (-) Drawdown / Paydown | F100: =+SUM(F109:F110) | G100: =+SUM(G109:G110) | H100: =+SUM(H109:H110) | I100: =+SUM(I109:I110) | J100: =+SUM(J109:J110)
B101: Cash Avail for Term Loan | F101: =SUM(F99:F100) | G101: =SUM(G99:G100) | H101: =SUM(H99:H100) | I101: =SUM(I99:I100) | J101: =SUM(J99:J100)
B102: (-) Paydown | F102: =+F120 | G102: =+G120 | H102: =+H120 | I102: =+I120 | J102: =+J120
B103: Cash Avail for Mezz Loan | F103: =SUM(F101:F102) | G103: =SUM(G101:G102) | H103: =SUM(H101:H102) | I103: =SUM(I101:I102) | J103: =SUM(J101:J102)
B104: (-) Paydown | F104: =+F131 | G104: =+G131 | H104: =+H131 | I104: =+I131 | J104: =+J131
B105: Excess Cash | F105: =SUM(F103:F104) | G105: =SUM(G103:G104) | H105: =SUM(H103:H104) | I105: =SUM(I103:I104) | J105: =SUM(J103:J104)
B107: Revolver
B108: Beg | F108: =+E111 | G108: =+F111 | H108: =+G111 | I108: =+H111 | J108: =+I111
B109: Drawdown | F109: =+-MIN(F99,0) | G109: =+-MIN(G99,0) | H109: =+-MIN(H99,0) | I109: =+-MIN(I99,0) | J109: =+-MIN(J99,0)
B110: Paydown | F110: =+IF(F108>0,-MIN(F108,MAX(F99,0)),0) | G110: =+IF(G108>0,-MIN(G108,MAX(G99,0)),0) | H110: =+IF(H108>0,-MIN(H108,MAX(H99,0)),0) | I110: =+IF(I108>0,-MIN(I108,MAX(I99,0)),0) | J110: =+IF(J108>0,-MIN(J108,MAX(J99,0)),0)
B111: End | E111: 0 | F111: =SUM(F108:F110) | G111: =SUM(G108:G110) | H111: =SUM(H108:H110) | I111: =SUM(I108:I110) | J111: =SUM(J108:J110)
B113: Avg | F113: =+E111 | G113: =+F111 | H113: =+G111 | I113: =+H111 | J113: =+I111
B114: Interest Rate | F114: 0.03 | G114: =+F114 | H114: =+G114 | I114: =+H114 | J114: =+I114
B115: Int Expense | F115: =+-F113*F114 | G115: =+-G113*G114 | H115: =+-H113*H114 | I115: =+-I113*I114 | J115: =+-J113*J114
B117: Term Loan
B118: Beg | F118: =+E121 | G118: =+F121 | H118: =+G121 | I118: =+H121 | J118: =+I121
...

Sheet M01 SUN-NuStar 2024
B2: Sunoco LP / NuStar Energy L.P. (2024) — acquisition model: accretion / dilution and pro forma leverage
B3: NOT AN LBO. All-equity MLP merger: 0.400 SUN common units per NuStar common unit. Not an LBO. The model answers the question a Sunoco unitholder had to answer: does issuing 51.5m units to buy $735m of EBITDA and $3.4bn of debt raise or lower distributable cash flow per unit, and where does leverage land.
B4: US$ millions unless stated. Blue on yellow = assumption; black = filed or derived from filed figures (see tag and source). Change any blue cell and the model recalculates.
B6: EXCHANGE RATE | C6: Native | D6: Ccy | E6: US$ | F6: Tag | G6: Source
B7: All inputs in US$; no conversion required | C7: 1 | E7: =C7
B9: ACQUIRER STANDALONE — Sunoco LP, latest twelve months before announcement (2024-01-22) | C9: Native | D9: Ccy | E9: US$ | F9: Tag | G9: Source
B10: Adjusted EBITDA | C10: 964 | D10: USD | E10: =C10 | F10: F | G10: Sunoco LP Q4/FY2023 results release, 14 Feb 2024: Adjusted EBITDA $964m
B11: Distributable cash flow, as adjusted | C11: 664 | D11: USD | E11: =C11 | F11: F | G11: Sunoco LP Q4/FY2023 results release: distributable cash flow, as adjusted, $664m
B12: Common units outstanding (millions) | C12: 84.408 | D12: USD | E12: =C12 | F12: F | G12: Sunoco LP Q4/FY2023 results: 84,408,014 common units outstanding at 31 Dec 2023
B13: Annualised distribution per unit (US$) | C13: 3.368 | D13: USD | E13: =C13 | F13: F | G13: Sunoco LP Q4 2023 distribution $0.8420 per unit, annualised
B14: Net debt | C14: 3551 | D14: USD | E14: =C14 | F14: D | G14: Sunoco LP 31 Dec 2023: long-term debt, net $3,580m less cash $29m
B15: Unit price at announcement (US$) | C15: 59.46 | D15: USD | E15: =C15 | F15: F | G15: NuStar DEFM14A proxy: SUN closing price 19 Jan 2024, last trading day before announcement
B16: Standalone DCF and EBITDA growth p.a. (accretion measured against this) | C16: 0 | D16: USD | E16: =C16 | F16: A | G16: Standalone DCF held flat so accretion isolates the deal; management gave no standalone forecast
B17: Distribution growth p.a. | C17: 0.04 | D17: USD | E17: =C17 | F17: F | G17: Sunoco raised the quarterly distribution 4% on closing (May 2024) and guided to continued annual growth
B19: TARGET — NuStar Energy L.P., latest twelve months before announcement | C19: Native | D19: Ccy | E19: US$ | F19: Tag | G19: Source
B20: Adjusted EBITDA (lease-excluded basis where target reports IFRS) | C20: 735.1 | D20: USD | E20: =C20 | F20: F | G20: NuStar Q4/FY2023 results release, 14 Feb 2024: Adjusted EBITDA $735.1m
B21: Maintenance capital expenditure | C21: 28 | D21: USD | E21: =C21 | F21: F | G21: NuStar FY2023 reliability capital expenditures $28.0m
B22: Cash taxes | C22: 5.4 | D22: USD | E22: =C22 | F22: F | G22: NuStar FY2023 income tax expense $5.4m (cash-paid figure not disclosed)
B23: Target net debt assumed and left outstanding | C23: 2572.1 | D23: USD | E23: =C23 | F23: F | G23: NuStar 10-K 31 Dec 2023: senior notes $2,250m (5.75%, 6.00%, 5.625%, 6.375%) plus GoZone bonds $322.1m, all left outstanding
B24: Cash interest rate on assumed debt | C24: 0.0595 | D24: USD | E24: =C24 | F24: D | G24: Weighted coupon of the notes left outstanding: $153m on $2,572m
B25: Target instruments refinanced at close (preferred, subordinated notes, revolver) | C25: 1641.5 | D25: USD | E25: =C25 | F25: F | G25: Refinanced at or after close: Series A/B/C preferred $784m (purchased at $25.00, 3 Jun 2024), 7.625% subordinated notes $402.5m, NuStar credit facility $455m
B26: Target shares / units outstanding (millions) | C26: 126.53 | D26: USD | E26: =C26 | F26: F | G26: NuStar 10-Q: 126,535,349 common units outstanding 26 Apr 2024
B27: Target share price before announcement (native currency) | C27: 18.03 | D27: USD | E27: =C27 | F27: D | G27: Derived from the proxy: $24.00 implied value was a 33.1% premium to the NuStar close on 19 Jan 2024
B29: DEAL TERMS AND FINANCING | C29: Native | D29: Ccy | E29: US$ | F29: Tag | G29: Source
B30: Acquirer units issued to target holders (millions) | C30: 51.5 | D30: USD | E30: =C30 | F30: F | G30: Sunoco 10-Q Q2 2024: approximately 51.5 million common units issued, fair value $2.85bn
B31: Cash consideration to target holders | C31: 0 | D31: USD | E31: =C31 | F31: F | G31: All-equity transaction: no cash paid to NuStar unitholders
B32: New senior notes issued | C32: 1500 | D32: USD | E32: =C32 | F32: F | G32: Sunoco senior notes priced 16 Apr 2024: $750m 7.000% due 2029 and $750m 7.250% due 2032
B33: Blended coupon on new notes | C33: 0.07125 | D33: USD | E33: =C33 | F33: D | G33: Blended coupon of the two tranches
B34: New preferred equity issued | C34: 0 | D34: USD | E34: =C34 | F34: F | G34: No preferred equity issued by Sunoco in this transaction
B35: Preferred distribution rate | C35: 0 | D35: USD | E35: =C35 | F35: F | G35: n/a
B36: Rate on revolver plug / cash retained | C36: 0.07 | D36: USD | E36: =C36 | F36: A | G36: Cost of the revolver draw that balances sources and uses (Sunoco unsecured revolver, SOFR-based, 2024)
B37: Transaction and financing costs | C37: 100 | D37: USD | E37: =C37 | F37: F | G37: Transaction costs; Sunoco reported roughly $100m of one-time transaction expenses in 2024 guidance
B38: Run-rate synergies by year 3 | C38: 150 | D38: USD | E38: =C38 | F38: F | G38: Sunoco 22 Jan 2024 release: at least $150m of run-rate synergies by year 3 (raised to $200m plus $60m financial in Aug 2024)
B39: Synergy realisation, year 1 | C39: 0.33 | D39: USD | E39: =C39 | F39: A | G39: Year-1 realisation; about $50m realised in 2024 per Sunoco Q2 2024 release, consistent with one third
B40: Synergy realisation, year 2 | C40: 0.67 | D40: USD | E40: =C40 | F40: A | G40: Year-2 realisation, straight-line to the year-3 run-rate
B41: Synergy realisation, year 3 | C41: 1 | D41: USD | E41: =C41 | F41: F | G41: Year-3 run-rate as stated
B43: SOURCES AND USES AT CLOSE | C43: Value
B44: Uses: cash to target holders + refinanced target instruments + fees | C44: =E31+E25+E37
B45: Sources: new senior notes + new preferred | C45: =E32+E34
B46: Revolver draw (positive) or cash retained (negative) to balance | C46: =C44-C45 | G46: Negative means the financing raised more than the cash uses; the surplus reduces net debt, as Sunoco did by repaying its revolver.
B47: Value of acquirer units issued at announcement price | C47: =E30*E15
B48: Target enterprise value at offer (units + cash + debt assumed + refinanced instruments) | C48: =C47+E31+E23+E25
B49: EV / target LTM EBITDA | C49: =C48/E20
B50: EV / (target LTM EBITDA + run-rate synergies) | C50: =C48/(E20+E38)
B51: Offer value per target share (native currency) | C51: =(C47+E31)/E26*E7
B52: Premium to pre-announcement price | C52: =C51/C27-1
B54: PRO FORMA DISTRIBUTABLE CASH FLOW PER UNIT | C54: Year 1 | D54: Year 2 | E54: Year 3
B55: Synergies realised | C55: =E38*E39 | D55: =E38*E40 | E55: =E38*E41
B56: Acquirer standalone DCF (grown at the standalone rate) | C56: =E11*(1+E16)^1 | D56: =E11*(1+E16)^2 | E56: =E11*(1+E16)^3
B57: Target DCF contribution before synergies: EBITDA - maintenance capex - cash taxes - interest on assumed debt - new notes interest - preferred distributions - interest on plug | C57: =E20-E21-E22-E23*E24-E32*E33-E34*E35-C46*E36
B58: Pro forma DCF to common units | C58: =C56+C57+C55 | D58: =D56+C57+D55 | E58: =E56+C57+E55
B59: Pro forma common units (millions) | C59: =E12+E30
B60: Standalone DCF per unit (US$) | C60: =C56/E12 | D60: =D56/E12 | E60: =E56/E12
B61: Pro forma DCF per unit (US$) | C61: =C58/C59 | D61: =D58/C59 | E61: =E58/C59
B62: Accretion / (dilution) to DCF per unit | C62: =C61/C60-1 | D62: =D61/D60-1 | E62: =E61/E60-1 | G62: Management: 10%+ accretive to DCF per common unit by year 3; immediately accretive (Sunoco, 22 Jan 2024)
B63: Distribution per unit (US$) | C63: =E13*(1+E17)^1 | D63: =E13*(1+E17)^2 | E63: =E13*(1+E17)^3
B64: Distributions paid (all common units incl. those issued) | C64: =C63*C59 | D64: =D63*C59 | E64: =E63*C59
B65: Distribution coverage (pro forma DCF / distributions) | C65: =C58/C64 | D65: =D58/D64 | E65: =E58/E64
B66: Excess cash after distributions, applied to debt | C66: =C58-C64 | D66: =D58-D64 | E66: =E58-E64 | G66: Growth capital expenditure is ignored, so the deleveraging path is the fastest the cash flows allow.
B68: PRO FORMA LEVERAGE | C68: Year 1 | D68: Year 2 | E68: Year 3
B69: Net debt at close: acquirer net debt + target debt assumed + new notes + plug | C69: =E14+E23+E32+C46
B70: Leverage at close on combined LTM EBITDA, no synergies | C70: =C69/(E10+E20)
B71: Leverage at close crediting full run-rate synergies (the convention Sunoco reports) | C71: =C69/(E10+E20+E38)
B72: Leverage at close treating the new preferred as debt | C72: =(C69+E34)/(E10+E20)
B73: Net debt, end of year (after excess cash applied) | C73: =C69-C66 | D73: =C69-C66-D66 | E73: =C69-C66-D66-E66
B74: Pro forma EBITDA incl. synergies realised | C74: =E10*(1+E16)^1+E20+C55 | D74: =E10*(1+E16)^2+E20+D55 | E74: =E10*(1+E16)^3+E20+E55
B75: Net debt / EBITDA, end of year | C75: =C73/C74 | D75: =D73/D74 | E75: =E73/E74 | G75: Management: Return to 4.0x long-term leverage target within 12 to 18 months of close (Sunoco, 22 Jan 2024)
B76: Including preferred as debt | C76: =(C73+E34)/C74 | D76: =(D73+E34)/D74 | E76: =(E73+E34)/E74
B78: WHAT ACTUALLY HAPPENED
B79: Closed 3 May 2024. Sunoco FY2024: Adjusted EBITDA $1,563m excluding transaction costs, DCF as adjusted $1,081m, 136.2m units, leverage 4.1x at 31 Dec 2024. FY2024 DCF per unit of $7.94 on the year-end unit count compares with $7.87 standalone in 2023, with only eight months of NuStar and before most synergies. Purchase accounting: total consideration $2,850m, debt assumed $3,500m at fair value, preferred $801m, goodwill $16m.
B81: SOURCES
B82: Sunoco LP: to acquire NuStar Energy L.P. in transaction valued at $7.3 billion (22 Jan 2024) | G82: https://www.sunocolp.com/press-release/item/sunoco-lp-to-acquire-nustar-energy-l.p.-in-transaction-valued-at-7.3-billion-2024
B83: Sunoco LP acquisition of NuStar investor presentation (22 Jan 2024) | G83: https://s24.q4cdn.com/191304019/files/doc_presentations/2024/01/Sunoco-Acquisition-of-NuStar-Investor-Presentation-01-22-24.pdf
B84: NuStar Energy DEFM14A proxy statement (Mar 2024) | G84: https://www.sec.gov/Archives/edgar/data/1110805/000119312524086017/d464008ddefm14a.htm
B85: Sunoco LP Q4 and full-year 2023 results (14 Feb 2024) | G85: https://www.prnewswire.com/news-releases/sunoco-lp-announces-fourth-quarter-and-full-year-2023-financial-and-operating-results-302061250.html
B86: NuStar Energy Q4 and full-year 2023 results (14 Feb 2024) | G86: https://www.businesswire.com/news/home/20240214468139/en/NuStar-Energy-L.P.-Reports-Solid-Fourth-Quarter-and-Full-Year-2023-Earnings-Results
B87: NuStar Energy 10-K for 2023 | G87: https://www.sec.gov/Archives/edgar/data/1110805/000111080524000007/ns-20231231.htm
B88: Sunoco LP pricing of $1.5bn senior notes (Apr 2024) | G88: https://www.prnewswire.com/news-releases/sunoco-lp-announces-pricing-of-private-offering-of-senior-notes-302118723.html
B89: Sunoco LP completes NuStar acquisition, 4% distribution increase (3 May 2024) | G89: https://www.prnewswire.com/news-releases/sunoco-lp-completes-acquisition-of-nustar-energy-lp-announces-a-4-increase-in-quarterly-distribution-302135594.html
B90: Sunoco LP purchase of NuStar preferred units and redemption of subordinated notes (May 2024) | G90: https://www.prnewswire.com/news-releases/sunoco-lp-announces-purchase-of-nustar-preferred-units-and-full-redemption-of-nustar-logistics-subordinated-notes-302135935.html
B91: Sunoco LP 10-Q Q3 2024 (purchase price allocation) | G91: https://www.sec.gov/Archives/edgar/data/1552275/000155227524000086/sun-20240930.htm
B92: Sunoco LP Q4 and full-year 2024 results (Feb 2025) | G92: https://www.sunocolp.com/press-release/item/sunoco-lp-reports-fourth-quarter-and-record-full-year-2024-financial-and-operating-results-2025

Sheet M02 SUN-Parkland 2025
B2: Sunoco LP / Parkland Corporation (2025) — acquisition model: accretion / dilution and pro forma leverage
B3: NOT AN LBO. Cross-border cash-and-units acquisition by plan of arrangement: C$19.80 cash plus 0.295 SunocoCorp units per Parkland share, funded with $1.9bn of senior notes and $1.5bn of 7.875% perpetual preferred. Not an LBO. The model tests the two numbers Sunoco put on the table: 10%+ DCF-per-unit accretion by year 3 and a return to 4.0x leverage. Parkland reports in C$ under IFRS; EBITDA and net debt are taken on Parkland's own lease-excluded "Leverage" basis so they are comparable with Sunoco's US GAAP figures.
B4: US$ millions unless stated. Blue on yellow = assumption; black = filed or derived from filed figures (see tag and source). Change any blue cell and the model recalculates.
B6: EXCHANGE RATE | C6: Native | D6: Ccy | E6: US$ | F6: Tag | G6: Source
B7: USD/CAD (C$ per US$1) | C7: 1.3813 | D7: USD | E7: =C7 | F7: F | G7: Bank of Canada USD/CAD daily rate, 5 May 2025 (announcement date); 1.4018 at close 31 Oct 2025
B9: ACQUIRER STANDALONE — Sunoco LP, latest twelve months before announcement (2025-05-05) | C9: Native | D9: Ccy | E9: US$ | F9: Tag | G9: Source
B10: Adjusted EBITDA | C10: 1774 | D10: USD | E10: =C10 | F10: D | G10: Sunoco LTM to 31 Mar 2025, Adjusted EBITDA excluding transaction expenses: Q2-24 $400m, Q3-24 $470m, Q4-24 $446m, Q1-25 $458m
B11: Distributable cash flow, as adjusted | C11: 1215 | D11: USD | E11: =C11 | F11: D | G11: Sunoco LTM to 31 Mar 2025, DCF as adjusted: Q2-24 $295m, Q3-24 $349m, Q4-24 $261m, Q1-25 $310m
B12: Common units outstanding (millions) | C12: 136.6 | D12: USD | E12: =C12 | F12: F | G12: Sunoco Q2 2025 results: 136,603,182 common units outstanding at 30 Jun 2025
B13: Annualised distribution per unit (US$) | C13: 3.59 | D13: USD | E13: =C13 | F13: F | G13: Sunoco Q1 2025 distribution $0.8976 per unit, annualised
B14: Net debt | C14: 7689 | D14: USD | E14: =C14 | F14: D | G14: Sunoco 30 Jun 2025: long-term debt, net $7,803m plus current maturities $2m less cash $116m
B15: Unit price at announcement (US$) | C15: 57.74 | D15: USD | E15: =C15 | F15: D | G15: Implied from the announced C$43.33 blended value: (43.33 - 19.80) / 0.295 = C$79.76 per unit, at 1.3813
B16: Standalone DCF and EBITDA growth p.a. (accretion measured against this) | C16: 0 | D16: USD | E16: =C16 | F16: A | G16: Standalone DCF held flat so accretion isolates the deal
B17: Distribution growth p.a. | C17: 0.05 | D17: USD | E17: =C17 | F17: F | G17: Sunoco raised the quarterly distribution about 1.25% per quarter through 2025 ($0.8865 to $0.9317)
B19: TARGET — Parkland Corporation, latest twelve months before announcement | C19: Native | D19: Ccy | E19: US$ | F19: Tag | G19: Source
B20: Adjusted EBITDA (lease-excluded basis where target reports IFRS) | C20: 1468 | D20: CAD | E20: =C20/E7 | F20: F | G20: Parkland Q2 2025 release: Leverage EBITDA (TTM Adjusted EBITDA less IFRS 16 lease reversal) C$1,468m at 30 Jun 2025; headline Adjusted EBITDA TTM C$1,742m
B21: Maintenance capital expenditure | C21: 279 | D21: CAD | E21: =C21/E7 | F21: F | G21: Parkland FY2024 maintenance capital expenditures C$279m
B22: Cash taxes | C22: 60 | D22: CAD | E22: =C22/E7 | F22: F | G22: Parkland FY2024 income taxes paid C$60m (cash flow statement)
B23: Target net debt assumed and left outstanding | C23: 4979 | D23: CAD | E23: =C23/E7 | F23: F | G23: Parkland Q2 2025 release: Leverage Debt C$4,979m at 30 Jun 2025 (long-term debt excluding leases, net of cash); Sunoco deck: about $3.5bn of Parkland net debt assumed
B24: Cash interest rate on assumed debt | C24: 0.055 | D24: USD | E24: =C24 | F24: A | G24: Parkland senior notes carry coupons between 4.375% and 6.625%; 5.5% blended is an assumption
B25: Target instruments refinanced at close (preferred, subordinated notes, revolver) | C25: 0 | D25: USD | E25: =C25 | F25: F | G25: Parkland senior notes remained outstanding after consent solicitations; Sunoco 10-K shows about $3.65bn of assumed Parkland notes
B26: Target shares / units outstanding (millions) | C26: 174.6 | D26: USD | E26: =C26 | F26: F | G26: Parkland circular record-date count 174,425,568; implied at close 174.6m (C$3,457.8m cash / C$19.80)
B27: Target share price before announcement (native currency) | C27: 34.66 | D27: CAD | E27: =C27/E7 | F27: D | G27: Derived: C$43.33 implied value was a 25% premium to 7-day VWAPs as of 2 May 2025
B29: DEAL TERMS AND FINANCING | C29: Native | D29: Ccy | E29: US$ | F29: Tag | G29: Source
B30: Acquirer units issued to target holders (millions) | C30: 51.517 | D30: USD | E30: =C30 | F30: F | G30: Parkland completion release, 31 Oct 2025: 51,517,198 SunocoCorp units issued; each mirrors one Sunoco LP common unit and receives the same distribution
B31: Cash consideration to target holders | C31: 3457.8 | D31: CAD | E31: =C31/E7 | F31: F | G31: Parkland completion release: C$3,457,770,643.42 paid in cash
B32: New senior notes issued | C32: 1900 | D32: USD | E32: =C32 | F32: F | G32: Sunoco senior notes priced 4 Sep 2025: $1.0bn 5.625% due 2031 and $900m 5.875% due 2034
B33: Blended coupon on new notes | C33: 0.05743 | D33: USD | E33: =C33 | F33: D | G33: Blended coupon of the two tranches
B34: New preferred equity issued | C34: 1500 | D34: USD | E34: =C34 | F34: F | G34: Sunoco Series A 7.875% fixed-rate reset perpetual preferred units, 1.5m units at $1,000, Sep 2025
B35: Preferred distribution rate | C35: 0.07875 | D35: USD | E35: =C35 | F35: F | G35: Fixed to 18 Sep 2030, then five-year Treasury plus 4.230%
B36: Rate on revolver plug / cash retained | C36: 0.06 | D36: USD | E36: =C36 | F36: A | G36: Rate on the revolver balance that absorbs any surplus or shortfall between sources and uses
B37: Transaction and financing costs | C37: 100 | D37: USD | E37: =C37 | F37: A | G37: Transaction and financing costs; Sunoco booked bridge, advisory and integration costs in 2025
B38: Run-rate synergies by year 3 | C38: 250 | D38: USD | E38: =C38 | F38: F | G38: Sunoco 5 May 2025 release: at least $250m of run-rate synergies by year 3
B39: Synergy realisation, year 1 | C39: 0.5 | D39: USD | E39: =C39 | F39: F | G39: Sunoco 2026 guidance includes approximately $125m of Parkland synergies, i.e. half the run-rate in year 1
B40: Synergy realisation, year 2 | C40: 0.75 | D40: USD | E40: =C40 | F40: A | G40: Year-2 realisation, straight-line to the year-3 run-rate
B41: Synergy realisation, year 3 | C41: 1 | D41: USD | E41: =C41 | F41: F | G41: Year-3 run-rate as stated ("by 2028" on the Q3 2025 call)
B43: SOURCES AND USES AT CLOSE | C43: Value
B44: Uses: cash to target holders + refinanced target instruments + fees | C44: =E31+E25+E37
B45: Sources: new senior notes + new preferred | C45: =E32+E34
B46: Revolver draw (positive) or cash retained (negative) to balance | C46: =C44-C45 | G46: Negative means the financing raised more than the cash uses; the surplus reduces net debt, as Sunoco did by repaying its revolver.
B47: Value of acquirer units issued at announcement price | C47: =E30*E15
B48: Target enterprise value at offer (units + cash + debt assumed + refinanced instruments) | C48: =C47+E31+E23+E25
B49: EV / target LTM EBITDA | C49: =C48/E20
B50: EV / (target LTM EBITDA + run-rate synergies) | C50: =C48/(E20+E38)
B51: Offer value per target share (native currency) | C51: =(C47+E31)/E26*E7
B52: Premium to pre-announcement price | C52: =C51/C27-1
B54: PRO FORMA DISTRIBUTABLE CASH FLOW PER UNIT | C54: Year 1 | D54: Year 2 | E54: Year 3
B55: Synergies realised | C55: =E38*E39 | D55: =E38*E40 | E55: =E38*E41
B56: Acquirer standalone DCF (grown at the standalone rate) | C56: =E11*(1+E16)^1 | D56: =E11*(1+E16)^2 | E56: =E11*(1+E16)^3
B57: Target DCF contribution before synergies: EBITDA - maintenance capex - cash taxes - interest on assumed debt - new notes interest - preferred distributions - interest on plug | C57: =E20-E21-E22-E23*E24-E32*E33-E34*E35-C46*E36
B58: Pro forma DCF to common units | C58: =C56+C57+C55 | D58: =D56+C57+D55 | E58: =E56+C57+E55
B59: Pro forma common units (millions) | C59: =E12+E30
B60: Standalone DCF per unit (US$) | C60: =C56/E12 | D60: =D56/E12 | E60: =E56/E12
B61: Pro forma DCF per unit (US$) | C61: =C58/C59 | D61: =D58/C59 | E61: =E58/C59
B62: Accretion / (dilution) to DCF per unit | C62: =C61/C60-1 | D62: =D61/D60-1 | E62: =E61/E60-1 | G62: Management: 10%+ accretive to DCF per common unit by year 3; immediately accretive in year 1 (Sunoco, 5 May 2025)
B63: Distribution per unit (US$) | C63: =E13*(1+E17)^1 | D63: =E13*(1+E17)^2 | E63: =E13*(1+E17)^3
B64: Distributions paid (all common units incl. those issued) | C64: =C63*C59 | D64: =D63*C59 | E64: =E63*C59
B65: Distribution coverage (pro forma DCF / distributions) | C65: =C58/C64 | D65: =D58/D64 | E65: =E58/E64
B66: Excess cash after distributions, applied to debt | C66: =C58-C64 | D66: =D58-D64 | E66: =E58-E64 | G66: Growth capital expenditure is ignored, so the deleveraging path is the fastest the cash flows allow.
B68: PRO FORMA LEVERAGE | C68: Year 1 | D68: Year 2 | E68: Year 3
B69: Net debt at close: acquirer net debt + target debt assumed + new notes + plug | C69: =E14+E23+E32+C46
B70: Leverage at close on combined LTM EBITDA, no synergies | C70: =C69/(E10+E20)
B71: Leverage at close crediting full run-rate synergies (the convention Sunoco reports) | C71: =C69/(E10+E20+E38)
B72: Leverage at close treating the new preferred as debt | C72: =(C69+E34)/(E10+E20)
B73: Net debt, end of year (after excess cash applied) | C73: =C69-C66 | D73: =C69-C66-D66 | E73: =C69-C66-D66-E66
B74: Pro forma EBITDA incl. synergies realised | C74: =E10*(1+E16)^1+E20+C55 | D74: =E10*(1+E16)^2+E20+D55 | E74: =E10*(1+E16)^3+E20+E55
B75: Net debt / EBITDA, end of year | C75: =C73/C74 | D75: =D73/D74 | E75: =E73/E74 | G75: Management: Return to the 4.0x long-term leverage target within 12 to 18 months of close (Sunoco, 5 May 2025); "in 2026" per 2026 guidance
B76: Including preferred as debt | C76: =(C73+E34)/C74 | D76: =(D73+E34)/D74 | E76: =(E73+E34)/E74
B78: WHAT ACTUALLY HAPPENED
B79: Closed 31 Oct 2025. Sunoco at 31 Dec 2025: total debt $13,389m, cash $891m, net leverage ratio 4.03x per the 10-K, 136.9m common units plus 51.5m SunocoCorp units. 2026 guidance: Adjusted EBITDA $3.1bn to $3.3bn including about $125m of Parkland synergies, maintenance capex $400m to $450m, return to 4.0x in 2026. Purchase accounting (10-K): cash paid about $2.60bn, units at $49.44 fair value, Parkland debt assumed $3,797m, cash acquired $464m.
B81: SOURCES
B82: Sunoco LP: to acquire Parkland Corporation in transaction valued at $9.1 billion (5 May 2025) | G82: https://www.sunocolp.com/press-release/item/sunoco-lp-to-acquire-parkland-corporation-in-transaction-valued-at-9-1-billion-2025
B83: Sunoco Parkland acquisition presentation (May 2025) | G83: https://assets.ctfassets.net/tatgxebmkmwo/57W38z9yHvAOdECxPg8ft0/92f93573236692778ecd57be0ea3d35b/Parkland_Acquisition_Presentation_FINAL_ADA.pdf
B84: SEC Form 425: Sunoco / Parkland call transcript (May 2025) | G84: https://www.sec.gov/Archives/edgar/data/1552275/000119312525113456/d831300d425.htm
B85: Parkland Q2 2025 results (Leverage EBITDA, Leverage Debt) | G85: https://www.newswire.ca/news-releases/parkland-reports-2025-second-quarter-results-849756245.html
B86: Parkland Q4 and full-year 2024 results | G86: https://www.prnewswire.com/news-releases/parkland-reports-fourth-quarter-and-year-end-2024-results-initiates-review-of-strategic-alternatives-302393768.html
B87: Parkland FY2024 financial statements (capex, interest paid, taxes paid) | G87: https://assets.ctfassets.net/tatgxebmkmwo/ddeRzLN6OsU4YkPplZivb/168544db9ee755da99bc7543f2f712b7/FS_Q4_2024.pdf
B88: Parkland management information circular, 26 May 2025 | G88: https://assets.ctfassets.net/tatgxebmkmwo/6593EXMy1JOssY1GwVHKqv/9a17cc7f6e822992764667af88de4da8/2025_Information_Circular_dated_May_26__2025_-_Special_and_Annual_Meeting.pdf
B89: Sunoco LP Q2 2025 results | G89: https://www.sunocolp.com/press-release/item/sunoco-lp-reports-second-quarter-2025-financial-and-operating-results-2025
B90: Sunoco LP pricing of upsized $1.9bn senior notes (4 Sep 2025) | G90: https://www.sunocolp.com/press-release/item/sunoco-lp-announces-pricing-of-upsized-private-offering-of-senior-notes-6fc36d3f3-2025
B91: Sunoco LP pricing of upsized $1.5bn preferred equity (Sep 2025) | G91: https://www.sunocolp.com/press-release/item/sunoco-lp-announces-pricing-of-upsized-preferred-equity-offering-2025
B92: Parkland completion of acquisition by Sunoco LP (31 Oct 2025) | G92: https://www.prnewswire.com/news-releases/parkland-corporation-announces-completion-of-acquisition-by-sunoco-lp-302602282.html
B93: Sunoco LP 8-K pro forma financial information (Jan 2026) | G93: https://www.sec.gov/Archives/edgar/data/1552275/000155227526000008/ex992-sunocoxparklandprofo.htm
... B96: Bank of Canada USD/CAD daily rates | G96: https://www.bankofcanada.ca/valet/observations/FXUSDCAD/json?start_date=2025-04-28&end_date=2025-05-05

Sheet Paper LBO
B2: Paper LBO
B4: Sources | G4: Uses
B5: Debt | E5: =E12 | G5: Purchase Price | J5: =J12
B6: Equity (plug) | E6: =E7-E5
B7: Total Sources | E7: =J7 | G7: Total Uses | J7: =J5
B9: Build to Debt | G9: Build to Purchase Price
B10: 2023 EBITDA | E10: =F18 | G10: 2023 EBITDA | J10: =F18
B11: (x) Leverage | E11: 2 | G11: (x) Multiple of 2023 EBITDA | J11: 5
B12: Debt | E12: =E10*E11 | G12: Purchase Price | J12: =J10*J11
B14: Simple P&L | E14: 2022 | F14: =E14+1 | G14: =F14+1 | H14: =G14+1 | I14: =H14+1 | J14: =I14+1
B15: Revenue | E15: 100 | F15: =E15+F16 | G15: =F15+G16 | H15: =G15+H16 | I15: =H15+I16 | J15: =I15+J16
B16: $ Incremental Revenue | F16: 10 | G16: =F16 | H16: =G16 | I16: =H16 | J16: =I16
B18: EBITDA | E18: =E19*E15 | F18: =F19*F15 | G18: =G19*G15 | H18: =H19*H15 | I18: =I19*I15 | J18: =J19*J15
B19: % margin | E19: 0.2 | F19: =E19 | G19: =F19 | H19: =G19 | I19: =H19 | J19: =I19
B21: LFCF Build
B22: EBITDA | F22: =F18 | G22: =G18 | H22: =H18 | I22: =I18 | J22: =J18
B23: (-) D&A | F23: -10 | G23: =F23 | H23: =G23 | I23: =H23 | J23: =I23
B24: EBIT | F24: =F22+F23 | G24: =G22+G23 | H24: =H22+H23 | I24: =I22+I23 | J24: =J22+J23
B25: (-) Cash Interest | D25: 0.1 | F25: =$E$12*-$D$25 | G25: =$E$12*-$D$25 | H25: =$E$12*-$D$25 | I25: =$E$12*-$D$25 | J25: =$E$12*-$D$25
B26: EBT | F26: =F24+F25 | G26: =G24+G25 | H26: =H24+H25 | I26: =I24+I25 | J26: =J24+J25
B27: (-) Taxes | D27: 0.25 | F27: =F26*-$D27 | G27: =G26*-$D27 | H27: =H26*-$D27 | I27: =I26*-$D27 | J27: =J26*-$D27
B28: Net Income | F28: =F26+F27 | G28: =G26+G27 | H28: =H26+H27 | I28: =I26+I27 | J28: =J26+J27
B29: (+) D&A | F29: =-F23 | G29: =-G23 | H29: =-H23 | I29: =-I23 | J29: =-J23
B30: (-) Capex | F30: -10 | G30: -10 | H30: -10 | I30: -10 | J30: -10
B31: (-) Change in NWC | F31: 0 | G31: 0 | H31: 0 | I31: 0 | J31: 0
B32: Levered FCF | F32: =SUM(F28:F31) | G32: =SUM(G28:G31) | H32: =SUM(H28:H31) | I32: =SUM(I28:I31) | J32: =SUM(J28:J31)
B33: Cumulative LFCF | F33: =SUM($E32:F32) | G33: =SUM($E32:G32) | H33: =SUM($E32:H32) | I33: =SUM($E32:I32) | J33: =SUM($E32:J32)
B35: Returns
B37: Exit EBITDA (2027) | E37: =J18
B38: (x) Exit Multiple | E38: 5
B39: Enterprise Value | E39: =E37*E38
B40: (-) Debt | E40: =-E12
B41: (+) Cash | E41: =J33
B42: Equity Value at Exit | E42: =SUM(E39:E41)
B43: Initial Equity Investment | E43: =E6
B45: MoM | E45: =E42/E43
B46: IRR | E46: =XIRR(E48:E49,B48:B49)
B48: 44926 | E48: =-E6
B49: 46752 | E49: =E42

Sheet 45 Min LBO Prompt

Sheet LBO Model Solution
B2: Assumptions
B3: Entry Multiple | E3: 9 | G3: TL | I3: 4 | J3: 0.0225
B4: Exit Multiple | E4: 9 | G4: Mezz | I4: 2 | J4: 0.0225
B5: EBITDA at Entry | E5: 40 | G5: Days | I5: 365
B6: Financing Fees Years | E6: 10 | G6: Tax Rate | I6: 0.4
B7: D&A Life | E7: 15
B8: Rollover | E8: 0.1 | G8: circ | I8: 1 | J8: << remember to turn this on by making it 1
B10: Sources | G10: Uses
B11: Term Loan | E11: =+I3*$E$5 | G11: Equity purchase price | J11: =+E18
B12: Mezz Loan | E12: =+I4*$E$5 | G12: M&A fee | J12: 5
B13: Management Rollover | E13: =+E18*E8 | G13: Fin. Fee | J13: =+J3*E11+J4*E12
B14: Sponsor Equity | E14: =E15-SUM(E11:E13)
B15: Total Sources | E15: =J15 | G15: Total Uses | J15: =SUM(J11:J14)
B17: Purchase Acct
B18: Purchase Price | E18: =+E3*E5
B19: (-) NPV | E19: -100
B20: Excess | E20: =SUM(E18:E19)
B21: (-) Alloc to PPE | D21: 0.15 | E21: =+-E20*D21
B22: DTL | D22: 0.4 | E22: =+-E21*D22
B23: Goodwill | E23: =SUM(E20:E22)
A25: x | B25: Income Statement | E25: 2013 | F25: =E25+1 | G25: =F25+1 | H25: =G25+1 | I25: =H25+1 | J25: =I25+1
B26: Revenue | E26: =+E31/E32 | F26: =+E26*(1+F27) | G26: =+F26*(1+G27) | H26: =+G26*(1+H27) | I26: =+H26*(1+I27) | J26: =+I26*(1+J27)
B27: % Growth | F27: 0.05 | G27: =+F27 | H27: =+G27 | I27: =+H27 | J27: =+I27
B28: (-) Cogs | E28: =E29-E26 | F28: =F29-F26 | G28: =G29-G26 | H28: =H29-H26 | I28: =I29-I26 | J28: =J29-J26
B29: Gross Profit | E29: =+E26*E30 | F29: =+F26*F30 | G29: =+G26*G30 | H29: =+H26*H30 | I29: =+I26*I30 | J29: =+J26*J30
B30: % Gross Margin | E30: 0.6 | F30: =+E30 | G30: =+F30 | H30: =+G30 | I30: =+H30 | J30: =+I30
B31: EBITDA | E31: =+E5 | F31: =+F26*F32 | G31: =+G26*G32 | H31: =+H26*H32 | I31: =+I26*I32 | J31: =+J26*J32
B32: % Margin | E32: 0.4 | F32: =+E32 | G32: =+F32 | H32: =+G32 | I32: =+H32 | J32: =+I32
B33: (-) D&A | F33: =+-F26*F46+F42 | G33: =+-G26*G46+G42 | H33: =+-H26*H46+H42 | I33: =+-I26*I46+I42 | J33: =+-J26*J46+J42
B34: EBIT | F34: =+F31+F33 | G34: =+G31+G33 | H34: =+H31+H33 | I34: =+I31+I33 | J34: =+J31+J33
B35: (-) Interest Expense | F35: =+circ*F150 | G35: =+circ*G150 | H35: =+circ*H150 | I35: =+circ*I150 | J35: =+circ*J150
B36: (+) Interest Income | F36: =+circ*F148 | G36: =+circ*G148 | H36: =+circ*H148 | I36: =+circ*I148 | J36: =+circ*J148
B37: (-) Amort. Of Fin Fee | F37: =+-$J$13/$E$6 | G37: =+-$J$13/$E$6 | H37: =+-$J$13/$E$6 | I37: =+-$J$13/$E$6 | J37: =+-$J$13/$E$6
B38: EBT | F38: =SUM(F34:F37) | G38: =SUM(G34:G37) | H38: =SUM(H34:H37) | I38: =SUM(I34:I37) | J38: =SUM(J34:J37)
B39: (-) Taxes | F39: =+-F38*$I$6 | G39: =+-G38*$I$6 | H39: =+-H38*$I$6 | I39: =+-I38*$I$6 | J39: =+-J38*$I$6
B40: Net Income | F40: =SUM(F38:F39) | G40: =SUM(G38:G39) | H40: =SUM(H38:H39) | I40: =SUM(I38:I39) | J40: =SUM(J38:J39)
B42: Incremental D&A | F42: =+$E$21/$E$7 | G42: =+$E$21/$E$7 | H42: =+$E$21/$E$7 | I42: =+$E$21/$E$7 | J42: =+$E$21/$E$7
B43: DTL | F43: =+F42*$D$22 | G43: =+G42*$D$22 | H43: =+H42*$D$22 | I43: =+I42*$D$22 | J43: =+J42*$D$22
B44: Capex | F44: =-F47*F33 | G44: =-G47*G33 | H44: =-H47*H33 | I44: =-I47*I33 | J44: =-J47*J33
B46: D&A as % of Sales | F46: 0.03 | G46: =+F46 | H46: =+G46 | I46: =+H46 | J46: =+I46
B47: Capex as % of D&A | F47: 0.8 | G47: =+F47 | H47: =+G47 | I47: =+H47 | J47: =+I47
A49: x | B49: WC Schedule | E49: 2013 | F49: =E49+1 | G49: =F49+1 | H49: =G49+1 | I49: =H49+1 | J49: =I49+1
B50: AR | E50: =+E26*E57/$I$5 | F50: =+F26*F57/$I$5 | G50: =+G26*G57/$I$5 | H50: =+H26*H57/$I$5 | I50: =+I26*I57/$I$5 | J50: =+J26*J57/$I$5
B51: Inventory | E51: =-E28/E58 | F51: =-F28/F58 | G51: =-G28/G58 | H51: =-H28/H58 | I51: =-I28/I58 | J51: =-J28/J58
B52: AP | E52: =-E28*E59/$I$5 | F52: =-F28*F59/$I$5 | G52: =-G28*G59/$I$5 | H52: =-H28*H59/$I$5 | I52: =-I28*I59/$I$5 | J52: =-J28*J59/$I$5
B53: WC | E53: =+E50+E51-E52 | F53: =+F50+F51-F52 | G53: =+G50+G51-G52 | H53: =+H50+H51-H52 | I53: =+I50+I51-I52 | J53: =+J50+J51-J52
B54: Change in WC | F54: =+F53-E53 | G54: =+G53-F53 | H54: =+H53-G53 | I54: =+I53-H53 | J54: =+J53-I53
B56: Metrics
B57: AR | E57: 80 | F57: =+E57 | G57: =+F57 | H57: =+G57 | I57: =+H57 | J57: =+I57
B58: Inventory | E58: 0.5 | F58: =+E58 | G58: =+F58 | H58: =+G58 | I58: =+H58 | J58: =+I58
B59: AP | E59: 120 | F59: =+E59 | G59: =+F59 | H59: =+G59 | I59: =+H59 | J59: =+I59
A61: x | B61: Cap Table | E61: 2013 | F61: =E61+1 | G61: =F61+1 | H61: =G61+1 | I61: =H61+1 | J61: =I61+1
B62: Cash | E62: 0 | F62: =+E62+F92 | G62: =+F62+G92 | H62: =+G62+H92 | I62: =+H62+I92 | J62: =+I62+J92
B64: Revolver | E64: 0 | F64: =+F111 | G64: =+G111 | H64: =+H111 | I64: =+I111 | J64: =+J111
B65: Term Loan | E65: =+E11 | F65: =+F121 | G65: =+G121 | H65: =+H121 | I65: =+I121 | J65: =+J121
B66: Mezz Loan | E66: =+E12 | F66: =+F132 | G66: =+G132 | H66: =+H132 | I66: =+I132 | J66: =+J132
B67: Total Debt | E67: =SUM(E64:E66) | F67: =SUM(F64:F66) | G67: =SUM(G64:G66) | H67: =SUM(H64:H66) | I67: =SUM(I64:I66) | J67: =SUM(J64:J66)
B68: Equity | E68: =SUM(E13:E14)-J12 | F68: =+E68+F40 | G68: =+F68+G40 | H68: =+G68+H40 | I68: =+H68+I40 | J68: =+I68+J40
B69: Total Cap | E69: =SUM(E67:E68) | F69: =SUM(F67:F68) | G69: =SUM(G67:G68) | H69: =SUM(H67:H68) | I69: =SUM(I67:I68) | J69: =SUM(J67:J68)
B71: Term Loan / EBITDA | E71: =+E65/$E$31 | F71: =+F65/$E$31 | G71: =+G65/$E$31 | H71: =+H65/$E$31 | I71: =+I65/$E$31 | J71: =+J65/$E$31
B72: Mezz Loan / EBITDA | E72: =+E66/$E$31 | F72: =+F66/$E$31 | G72: =+G66/$E$31 | H72: =+H66/$E$31 | I72: =+I66/$E$31 | J72: =+J66/$E$31
B73: Total Debt / EBITDA | E73: =+E67/$E$31 | F73: =+F67/$E$31 | G73: =+G67/$E$31 | H73: =+H67/$E$31 | I73: =+I67/$E$31 | J73: =+J67/$E$31
B74: Total Debt / Cap | E74: =+E67/E69 | F74: =+F67/F69 | G74: =+G67/G69 | H74: =+H67/H69 | I74: =+I67/I69 | J74: =+J67/J69
A76: x | B76: Cash Flow Statement | E76: 2013 | F76: =E76+1 | G76: =F76+1 | H76: =G76+1 | I76: =H76+1 | J76: =I76+1
B77: Net Income | F77: =+F40 | G77: =+G40 | H77: =+H40 | I77: =+I40 | J77: =+J40
B78: (+) D&A | F78: =+-F33 | G78: =+-G33 | H78: =+-H33 | I78: =+-I33 | J78: =+-J33
B79: (-) DTL | F79: =+F43 | G79: =+G43 | H79: =+H43 | I79: =+I43 | J79: =+J43
B80: (+) PIK | F80: =-+F139 | G80: =-+G139 | H80: =-+H139 | I80: =-+I139 | J80: =-+J139
B81: (+) Amort Fee | F81: =+-F37 | G81: =+-G37 | H81: =+-H37 | I81: =+-I37 | J81: =+-J37
B82: (-) Change WC | F82: =+-F54 | G82: =+-G54 | H82: =+-H54 | I82: =+-I54 | J82: =+-J54
B83: CFO | F83: =SUM(F77:F82) | G83: =SUM(G77:G82) | H83: =SUM(H77:H82) | I83: =SUM(I77:I82) | J83: =SUM(J77:J82)
B85: Capex | F85: =+-F44 | G85: =+-G44 | H85: =+-H44 | I85: =+-I44 | J85: =+-J44
B86: CFI | F86: =SUM(F85) | G86: =SUM(G85) | H86: =SUM(H85) | I86: =SUM(I85) | J86: =SUM(J85)
B88: Mand. Paymnet | F88: =+F119 | G88: =+G119 | H88: =+H119 | I88: =+I119 | J88: =+J119
B89: Optional Payment | F89: =+SUM(F102,F104) | G89: =+SUM(G102,G104) | H89: =+SUM(H102,H104) | I89: =+SUM(I102,I104) | J89: =+SUM(J102,J104)
B90: CFF | F90: =SUM(F88:F89) | G90: =SUM(G88:G89) | H90: =SUM(H88:H89) | I90: =SUM(I88:I89) | J90: =SUM(J88:J89)
B92: Change in Cash | F92: =+SUM(F83,F86,F90) | G92: =+SUM(G83,G86,G90) | H92: =+SUM(H83,H86,H90) | I92: =+SUM(I83,I86,I90) | J92: =+SUM(J83,J86,J90)
A94: x | B94: Debt Paydown | E94: 2013 | F94: =E94+1 | G94: =F94+1 | H94: =G94+1 | I94: =H94+1 | J94: =I94+1
B95: Beg Cash | F95: =+E62 | G95: =+F62 | H95: =+G62 | I95: =+H62 | J95: =+I62
B96: (-) Min Cash | F96: -5 | G96: -5 | H96: -5 | I96: -5 | J96: -5
B97: (+) CFO + CFI | F97: =+F83+F86 | G97: =+G83+G86 | H97: =+H83+H86 | I97: =+I83+I86 | J97: =+J83+J86
B98: (-) Mand. Payment | F98: =+F88 | G98: =+G88 | H98: =+H88 | I98: =+I88 | J98: =+J88
B99: Cash Avail for Revolver | F99: =SUM(F95:F98) | G99: =SUM(G95:G98) | H99: =SUM(H95:H98) | I99: =SUM(I95:I98) | J99: =SUM(J95:J98)
B100: (-) Drawdown / Paydown | F100: =+SUM(F109:F110) | G100: =+SUM(G109:G110) | H100: =+SUM(H109:H110) | I100: =+SUM(I109:I110) | J100: =+SUM(J109:J110)
B101: Cash Avail for Term Loan | F101: =SUM(F99:F100) | G101: =SUM(G99:G100) | H101: =SUM(H99:H100) | I101: =SUM(I99:I100) | J101: =SUM(J99:J100)
B102: (-) Paydown | F102: =+F120 | G102: =+G120 | H102: =+H120 | I102: =+I120 | J102: =+J120
B103: Cash Avail for Mezz Loan | F103: =SUM(F101:F102) | G103: =SUM(G101:G102) | H103: =SUM(H101:H102) | I103: =SUM(I101:I102) | J103: =SUM(J101:J102)
B104: (-) Paydown | F104: =+F131 | G104: =+G131 | H104: =+H131 | I104: =+I131 | J104: =+J131
B105: Excess Cash | F105: =SUM(F103:F104) | G105: =SUM(G103:G104) | H105: =SUM(H103:H104) | I105: =SUM(I103:I104) | J105: =SUM(J103:J104)
B107: Revolver
B108: Beg | F108: =+E111 | G108: =+F111 | H108: =+G111 | I108: =+H111 | J108: =+I111
B109: Drawdown | F109: =+-MIN(F99,0) | G109: =+-MIN(G99,0) | H109: =+-MIN(H99,0) | I109: =+-MIN(I99,0) | J109: =+-MIN(J99,0)
B110: Paydown | F110: =+IF(F108>0,-MIN(F108,F99),0) | G110: =+IF(G108>0,-MIN(G108,G99),0) | H110: =+IF(H108>0,-MIN(H108,H99),0) | I110: =+IF(I108>0,-MIN(I108,I99),0) | J110: =+IF(J108>0,-MIN(J108,J99),0)
B111: End | E111: 0 | F111: =SUM(F108:F110) | G111: =SUM(G108:G110) | H111: =SUM(H108:H110) | I111: =SUM(I108:I110) | J111: =SUM(J108:J110)
B113: Avg | F113: =+AVERAGE(E111:F111) | G113: =+AVERAGE(F111:G111) | H113: =+AVERAGE(G111:H111) | I113: =+AVERAGE(H111:I111) | J113: =+AVERAGE(I111:J111)
B114: Interest Rate | F114: 0.04 | G114: =+F114 | H114: =+G114 | I114: =+H114 | J114: =+I114
B115: Int Expense | F115: =+-F113*F114 | G115: =+-G113*G114 | H115: =+-H113*H114 | I115: =+-I113*I114 | J115: =+-J113*J114
B117: Term Loan
B118: Beg | F118: =+E121 | G118: =+F121 | H118: =+G121 | I118: =+H121 | J118: =+I121
B119: Mand. Amort | F119: =-IF($E$121+F118*F126>0,$E$121*F126,0) | G119: =-IF($E$121+G118*G126>0,$E$121*G126,0) | H119: =-IF($E$121+H118*H126>0,$E$121*H126,0) | I119: =-IF($E$121+I118*I126>0,$E$121*I126,0) | J119: =-IF($E$121+J118*J126>0,$E$121*J126,0)
...
